Workbook

Sheet Income Statement
A1: Company: Demo Holdings Limited (DEMO)
A2: Statement: Income Statement
A3: Units: HKD in Millions
A4: Source: HK manual ingestion (HK)
A6: Line Item | B6: 44561 | C6: 44926 | D6: 45291 | E6: 45657 | F6: 46022
A7: Revenue | B7: 8500 | C7: 9200 | D7: 10100 | E7: 11200 | F7: 12500
A8: Cost of sales | B8: -3400 | C8: -3680 | D8: -4040 | E8: -4480 | F8: -5000
A9: Gross profit | B9: 5100 | C9: 5520 | D9: 6060 | E9: 6720 | F9: 7500
A10: Administrative expenses | B10: -1700 | C10: -1840 | D10: -2020 | E10: -2240 | F10: -2500
A11: Operating profit | B11: 3400 | C11: 3680 | D11: 4040 | E11: 4480 | F11: 5000
A12: Finance costs | B12: -120 | C12: -130 | D12: -140 | E12: -150 | F12: -160
A13: Finance income | B13: 45 | C13: 50 | D13: 55 | E13: 60 | F13: 65
A14: Profit before tax | B14: 3325 | C14: 3600 | D14: 3955 | E14: 4390 | F14: 4905
A15: Income tax expense | B15: -565 | C15: -612 | D15: -672 | E15: -746 | F15: -833
A16: Profit for the year | B16: 2760 | C16: 2988 | D16: 3283 | E16: 3644 | F16: 4072

Sheet Balance Sheet
A1: Company: Demo Holdings Limited (DEMO)
A2: Statement: Balance Sheet
A3: Units: HKD in Millions
A4: Source: HK manual ingestion (HK)
A6: Line Item | B6: 44561 | C6: 44926 | D6: 45291 | E6: 45657 | F6: 46022
A7: Cash and cash equivalents | B7: 1200 | C7: 1350 | D7: 1500 | E7: 1680 | F7: 1850
A8: Trade receivables | B8: 850 | C8: 920 | D8: 1010 | E8: 1120 | F8: 1250
A9: Inventories | B9: 680 | C9: 736 | D9: 808 | E9: 896 | F9: 1000
A10: Property, plant and equipment | B10: 3200 | C10: 3400 | D10: 3600 | E10: 3800 | F10: 4000
A11: Goodwill | B11: 900 | C11: 900 | D11: 900 | E11: 900 | F11: 900
A12: Total assets | B12: 8500 | C12: 9200 | D12: 10100 | E12: 11200 | F12: 12500
A13: Trade payables | B13: 595 | C13: 644 | D13: 707 | E13: 784 | F13: 875
A14: Bank borrowings | B14: 1500 | C14: 1400 | D14: 1300 | E14: 1200 | F14: 1100
A15: Total liabilities | B15: 3400 | C15: 3500 | D15: 3600 | E15: 3700 | F15: 3800
A16: Share capital and reserves | B16: 5100 | C16: 5700 | D16: 6500 | E16: 7500 | F16: 8700
A17: Total equity | B17: 5100 | C17: 5700 | D17: 6500 | E17: 7500 | F17: 8700

Sheet Cash Flow Statement
A1: Company: Demo Holdings Limited (DEMO)
A2: Statement: Cash Flow Statement
A3: Units: HKD in Millions
A4: Source: HK manual ingestion (HK)
A6: Line Item | B6: 44561 | C6: 44926 | D6: 45291 | E6: 45657 | F6: 46022
A7: Profit for the year | B7: 2760 | C7: 2988 | D7: 3283 | E7: 3644 | F7: 4072
A8: Depreciation and amortisation | B8: 340 | C8: 368 | D8: 404 | E8: 448 | F8: 500
A9: Net cash from operating activities | B9: 3500 | C9: 3800 | D9: 4200 | E9: 4600 | F9: 5100
A10: Net cash used in investing activities | B10: -800 | C10: -850 | D10: -900 | E10: -950 | F10: -1000
A11: Net cash from financing activities | B11: -500 | C11: -600 | D11: -700 | E11: -800 | F11: -900
A12: Net change in cash and cash equivalents | B12: 150 | C12: 150 | D12: 150 | E12: 180 | F12: 170

Sheet Condensed Financials
A1: Demo Holdings Limited (DEMO) — Condensed Financials
A2: ROE reformulation: classify balance sheet, compute NOPAT and NOA
A4: BALANCE SHEET CLASSIFICATION | B4: Classification
A5: Cash and cash equivalents | B5: Financial Asset
A6: Trade receivables | B6: Ambiguous — Operating
A7: Inventories | B7: Ambiguous — Operating
A8: Property, plant and equipment | B8: Operating Long-Term Asset
A9: Goodwill | B9: Operating Long-Term Asset
A10: Trade payables | B10: Ambiguous — Operating
A11: Bank borrowings | B11: Ambiguous — Operating
A12: Share capital and reserves | B12: Ambiguous — Operating
A14: CONDENSED INCOME STATEMENT | B14: 44561 | C14: 44926 | D14: 45291 | E14: 45657 | F14: 46022
A15: Net Income | B15: ='Income Statement'!B9 | C15: ='Income Statement'!C9 | D15: ='Income Statement'!D9 | E15: ='Income Statement'!E9 | F15: ='Income Statement'!F9
A16: Pretax Income | B16: ='Income Statement'!B14 | C16: ='Income Statement'!C14 | D16: ='Income Statement'!D14 | E16: ='Income Statement'!E14 | F16: ='Income Statement'!F14
A17: Tax Expense | B17: ='Income Statement'!B14 | C17: ='Income Statement'!C14 | D17: ='Income Statement'!D14 | E17: ='Income Statement'!E14 | F17: ='Income Statement'!F14
A18: Effective Tax Rate | B18: =-B17/B16 | C18: =-C17/C16 | D18: =-D17/D16 | E18: =-E17/E16 | F18: =-F17/F16
A19: NOPAT | B19: =B15 | C19: =C15 | D19: =D15 | E19: =E15 | F19: =F15
A21: CONDENSED BALANCE SHEET
A22: NOWC | B22: =SUMIF($B$5:$B$12,"Operating Working Capital Asset",'Balance Sheet'!B5:'Balance Sheet'!B12)-SUMIF($B$5:$B$12,"Operating Working Capital Liability",'Balance Sheet'!B5:'Balance Sheet'!B12) | C22: =SUMIF($B$5:$B$12,"Operating Working Capital Asset",'Balance Sheet'!C5:'Balance Sheet'!C12)-SUMIF($B$5:$B$12,"Operating Working Capital Liability",'Balance Sheet'!C5:'Balance Sheet'!C12) | D22: =SUMIF($B$5:$B$12,"Operating Working Capital Asset",'Balance Sheet'!D5:'Balance Sheet'!D12)-SUMIF($B$5:$B$12,"Operating Working Capital Liability",'Balance Sheet'!D5:'Balance Sheet'!D12) | E22: =SUMIF($B$5:$B$12,"Operating Working Capital Asset",'Balance Sheet'!E5:'Balance Sheet'!E12)-SUMIF($B$5:$B$12,"Operating Working Capital Liability",'Balance Sheet'!E5:'Balance Sheet'!E12) | F22: =SUMIF($B$5:$B$12,"Operating Working Capital Asset",'Balance Sheet'!F5:'Balance Sheet'!F12)-SUMIF($B$5:$B$12,"Operating Working Capital Liability",'Balance Sheet'!F5:'Balance Sheet'!F12)
A23: NOA | B23: =B22+SUMIF($B$5:$B$12,"Operating Long-Term Asset",'Balance Sheet'!B5:'Balance Sheet'!B12)-SUMIF($B$5:$B$12,"Operating Long-Term Liability",'Balance Sheet'!B5:'Balance Sheet'!B12) | C23: =C22+SUMIF($B$5:$B$12,"Operating Long-Term Asset",'Balance Sheet'!C5:'Balance Sheet'!C12)-SUMIF($B$5:$B$12,"Operating Long-Term Liability",'Balance Sheet'!C5:'Balance Sheet'!C12) | D23: =D22+SUMIF($B$5:$B$12,"Operating Long-Term Asset",'Balance Sheet'!D5:'Balance Sheet'!D12)-SUMIF($B$5:$B$12,"Operating Long-Term Liability",'Balance Sheet'!D5:'Balance Sheet'!D12) | E23: =E22+SUMIF($B$5:$B$12,"Operating Long-Term Asset",'Balance Sheet'!E5:'Balance Sheet'!E12)-SUMIF($B$5:$B$12,"Operating Long-Term Liability",'Balance Sheet'!E5:'Balance Sheet'!E12) | F23: =F22+SUMIF($B$5:$B$12,"Operating Long-Term Asset",'Balance Sheet'!F5:'Balance Sheet'!F12)-SUMIF($B$5:$B$12,"Operating Long-Term Liability",'Balance Sheet'!F5:'Balance Sheet'!F12)
A24: Net Debt | B24: =SUMIF($B$5:$B$12,"Financial Liability",'Balance Sheet'!B5:'Balance Sheet'!B12)-SUMIF($B$5:$B$12,"Financial Asset",'Balance Sheet'!B5:'Balance Sheet'!B12) | C24: =SUMIF($B$5:$B$12,"Financial Liability",'Balance Sheet'!C5:'Balance Sheet'!C12)-SUMIF($B$5:$B$12,"Financial Asset",'Balance Sheet'!C5:'Balance Sheet'!C12) | D24: =SUMIF($B$5:$B$12,"Financial Liability",'Balance Sheet'!D5:'Balance Sheet'!D12)-SUMIF($B$5:$B$12,"Financial Asset",'Balance Sheet'!D5:'Balance Sheet'!D12) | E24: =SUMIF($B$5:$B$12,"Financial Liability",'Balance Sheet'!E5:'Balance Sheet'!E12)-SUMIF($B$5:$B$12,"Financial Asset",'Balance Sheet'!E5:'Balance Sheet'!E12) | F24: =SUMIF($B$5:$B$12,"Financial Liability",'Balance Sheet'!F5:'Balance Sheet'!F12)-SUMIF($B$5:$B$12,"Financial Asset",'Balance Sheet'!F5:'Balance Sheet'!F12)

Sheet ALT DuPont
A1: Demo Holdings Limited — DuPont Decomposition
A2: ROE = RNOA + FLEV × Spread
A4: Metric | B4: 44926 | C4: 45291 | D4: 45657 | E4: 46022
A5: RNOA | B5: ='Condensed Financials'!C19/(('Condensed Financials'!C23+'Condensed Financials'!B23)/2)
A6: Spread | B6: =C5-0.04
A7: ROE (decomposed) | B7: =C5+1.5*(C6)
A8: Actual ROE | B8: ='Income Statement'!C13/(('Balance Sheet'!C7+'Balance Sheet'!B7)/2)
A9: RNOA | C9: ='Condensed Financials'!D19/(('Condensed Financials'!D23+'Condensed Financials'!C23)/2)
A10: Spread | C10: =D9-0.04
A11: ROE (decomposed) | C11: =D9+1.5*(D10)
A12: Actual ROE | C12: ='Income Statement'!D13/(('Balance Sheet'!D7+'Balance Sheet'!C7)/2)
A13: RNOA | D13: ='Condensed Financials'!E19/(('Condensed Financials'!E23+'Condensed Financials'!D23)/2)
A14: Spread | D14: =E13-0.04
A15: ROE (decomposed) | D15: =E13+1.5*(E14)
A16: Actual ROE | D16: ='Income Statement'!E13/(('Balance Sheet'!E7+'Balance Sheet'!D7)/2)
A17: RNOA | E17: ='Condensed Financials'!F19/(('Condensed Financials'!F23+'Condensed Financials'!E23)/2)
A18: Spread | E18: =F17-0.04
A19: ROE (decomposed) | E19: =F17+1.5*(F18)
A20: Actual ROE | E20: ='Income Statement'!F13/(('Balance Sheet'!F7+'Balance Sheet'!E7)/2)

Sheet Model_Bear
A1: Demo Holdings Limited — Bear Scenario
A2: 10-year residual income (abnormal earnings) model
A5: Cost of Equity (Ke) | B5: 0.105
A6: Terminal Growth (g) | B6: 0.03
A10: Metric | B10: Y1 | C10: Y2 | D10: Y3 | E10: Y4 | F10: Y5 | G10: Y6 | H10: Y7 | I10: Y8 | J10: Y9 | K10: Y10
A11: Sales | B11: ='Income Statement'!F7*(1+0.1)
A12: NOPAT Margin | B12: 0.15
A14: NOPAT | B14: =B11*B12
A18: Book Equity
A20: Abnormal Earnings
A22: PV Abnormal Earnings
A38: Intrinsic Value per Share | B38: =B18+SUM(B22:K22)

Sheet Model_Base
A1: Demo Holdings Limited — Base Scenario
A2: 10-year residual income (abnormal earnings) model
A5: Cost of Equity (Ke) | B5: 0.0975
A6: Terminal Growth (g) | B6: 0.03
A10: Metric | B10: Y1 | C10: Y2 | D10: Y3 | E10: Y4 | F10: Y5 | G10: Y6 | H10: Y7 | I10: Y8 | J10: Y9 | K10: Y10
A11: Sales | B11: ='Income Statement'!F7*(1+0.1)
A12: NOPAT Margin | B12: 0.15
A14: NOPAT | B14: =B11*B12
A18: Book Equity
A20: Abnormal Earnings
A22: PV Abnormal Earnings
A38: Intrinsic Value per Share | B38: =B18+SUM(B22:K22)

Sheet Model_Bull
A1: Demo Holdings Limited — Bull Scenario
A2: 10-year residual income (abnormal earnings) model
A5: Cost of Equity (Ke) | B5: 0.0925
A6: Terminal Growth (g) | B6: 0.03
A10: Metric | B10: Y1 | C10: Y2 | D10: Y3 | E10: Y4 | F10: Y5 | G10: Y6 | H10: Y7 | I10: Y8 | J10: Y9 | K10: Y10
A11: Sales | B11: ='Income Statement'!F7*(1+0.1)
A12: NOPAT Margin | B12: 0.15
A14: NOPAT | B14: =B11*B12
A18: Book Equity
A20: Abnormal Earnings
A22: PV Abnormal Earnings
A38: Intrinsic Value per Share | B38: =B18+SUM(B22:K22)

Sheet Scenario_Summary
A1: Demo Holdings Limited — Scenario Summary
A3: Scenario | B3: Probability | C3: IVPS | D3: Terminal RNOA
A4: Bear | B4: 0.25 | C4: ='Model_Bear'!B38
A5: Base | B5: 0.5 | C5: ='Model_Base'!B38
A6: Bull | B6: 0.25 | C6: ='Model_Bull'!B38
A8: Weighted IVPS | E8: =SUMPRODUCT(B4:B6,C4:C6)
