Workbook

Sheet Trainer
A1: BAV Excel Trainer
A2: Complete each historical model-construction and earnings-quality diagnostic formula schedule left-to-right in dependency order. Run Check to validate the yellow formula cells against the treatment currently selected in Accounting Judgment column F (blank F uses the supplied reference treatment). Generated Condensed Financials classification links are system-controlled and validated by Check—do not edit them or columns D:E. When Normalization Judgment is present, choose Recurring vs Non-recurring in column F (blank uses the supplied reference); Earnings Normalization formulas are checked against that choice. Also complete Accounting Judgment and Normalization Judgment rationale/consequence when cases are present; those responses are not graded by Check. Compare them with the matching Answer Key.
A4: Order | B4: Schedule | C4: Period scope | D4: Tab | E4: Practice cells | F4: Depends on
A5: 1 | B5: Revenue historical source link | C5: 2021–2025 (5 cells) | D5: Condensed Financials | E5: B44:F44 | F5: —
A6: 2 | B6: Net Income historical source link | C6: 2021–2025 (5 cells) | D6: Condensed Financials | E6: B45:F45 | F6: —
A7: 3 | B7: Effective tax rate | C7: 2021–2025 (5 cells) | D7: Condensed Financials | E7: B51:F51 | F7: —
A8: 4 | B8: Net interest | C8: 2021–2025 (5 cells) | D8: Condensed Financials | E8: B52:F52 | F8: —
A9: 5 | B9: Net interest after tax | C9: 2021–2025 (5 cells) | D9: Condensed Financials | E9: B53:F53 | F9: effective_tax_rate_fy, net_interest_fy
A10: 6 | B10: NOPAT | C10: 2021–2025 (5 cells) | D10: Condensed Financials | E10: B54:F54 | F10: net_income_link, net_interest_after_tax_fy
A11: 7 | B11: Operating working capital assets | C11: 2021–2025 (5 cells) | D11: Condensed Financials | E11: B57:F57 | F11: —
A12: 8 | B12: Operating working capital liabilities | C12: 2021–2025 (5 cells) | D12: Condensed Financials | E12: B58:F58 | F12: —
A13: 9 | B13: Net Operating Working Capital (NOWC) | C13: 2021–2025 (5 cells) | D13: Condensed Financials | E13: B59:F59 | F13: owca_agg, owcl_agg
A14: 10 | B14: Operating long-term assets | C14: 2021–2025 (5 cells) | D14: Condensed Financials | E14: B60:F60 | F14: —
A15: 11 | B15: Operating long-term liabilities | C15: 2021–2025 (5 cells) | D15: Condensed Financials | E15: B61:F61 | F15: —
A16: 12 | B16: Net operating long-term assets (NOLA) | C16: 2021–2025 (5 cells) | D16: Condensed Financials | E16: B62:F62 | F16: olta_agg, oltl_agg
... A119: 123 | B119: Lease Repayments / Revenue | C119: 2021–2025 (5 cells) | D119: ALT DuPont | E119: B83:F83 | F119: lease_repayments, revenue_link

Sheet Income Statement
A1: Company: FAST RETAILING CO., LTD. (6288.HK)
A2: Statement: Income Statement
A3: Units: JPY in Millions
A4: Source: manual ingestion (JP)
A6: Line Item | B6: 44439 | C6: 44804 | D6: 45169 | E6: 45535 | F6: 45900
A7: Basic (yen, dollar) | B7: 1663.12 | C7: 891.77 | D7: 966.09 | E7: 1212.88 | F7: 1411.44
A8: Cost of sales | B8: -1059036 | C8: -1094263 | D8: -1330196 | E8: -1430764 | F8: -1571681
A9: Diluted (yen, dollar) | B9: 1660.44 | C9: 890.43 | D9: 964.48 | E9: 1210.81 | F9: 1409.32
A10: Finance costs | B10: -6998 | C10: -7560 | D10: -9888 | E10: -11101 | F10: -12834
A11: Finance income | B11: 23859 | C11: 123820 | D11: 66716 | E11: 67399 | F11: 99143
A12: Gross profit | B12: 1073955 | C12: 1206859 | D12: 1436360 | E12: 1673071 | F12: 1828858
A13: Income tax expense | B13: -90188 | C13: -128834 | D13: -122746 | E13: -163596 | F13: -191421
A14: Non-controlling interests | B14: 5836 | C14: 11415 | D14: 18941 | E14: 21605 | F14: 26143
A15: Operating profit | B15: 249011 | C15: 297325 | D15: 381090 | E15: 500904 | F15: 564265
A16: Other expenses | B16: -25315 | C16: -27391 | D16: -14238 | E16: -6256 | F16: -8087
A17: Other income | B17: 18238 | C17: 16951 | D17: 12197 | E17: 20384 | F17: 19491
... A23: Share of profit of associates accounted for using the equity method | B23: 561 | C23: 1059 | D23: 1139 | E23: 1417 | F23: 1704
A25: SUPPLEMENTAL DISCLOSURES
A26: Lease interest expense (reported note) | B26: 4847 | C26: 4757 | D26: 5187 | E26: 6507 | F26: 8464

Sheet Balance Sheet
A1: Company: FAST RETAILING CO., LTD. (6288.HK)
A2: Statement: Balance Sheet
A3: Units: JPY in Millions
A4: Source: manual ingestion (JP)
A6: Line Item | B6: 44439 | C6: 44804 | D6: 45169 | E6: 45535 | F6: 45900
A7: Total assets | B7: 2509976 | C7: 3183762 | D7: 3303694 | E7: 3587565 | F7: 3859353
A8: Cash and cash equivalents | B8: 1177736 | C8: 1358292 | D8: 903280 | E8: 1193560 | F8: 893239
A9: Derivative financial assets | B9: 27103 | C9: 124551 | D9: 132101 | E9: 111658 | F9: 94803
A10: Income taxes receivable | B10: 2992 | C10: 2612 | D10: 23660 | E10: 2210 | F10: 8042
A11: Inventories | B11: 394868 | C11: 485928 | D11: 449254 | E11: 474460 | F11: 510958
A12: Other assets | B12: 15270 | C12: 23835 | D12: 25372 | E12: 26897 | F12: 24662
A13: Other financial assets | B13: 56157 | C13: 123446 | D13: 576194 | E13: 470554 | F13: 899701
A14: Total current assets | B14: 1724674 | C14: 2178851 | D14: 2176695 | E14: 2363271 | F14: 2527815
A15: Trade and other receivables | B15: 50546 | C15: 60184 | D15: 66831 | E15: 83929 | F15: 96407
A16: Current tax liabilities | B16: 38606 | C16: 77162 | D16: 65428 | E16: 65525 | F16: 73072
A17: Derivative financial liabilities | B17: 2493 | C17: 1513 | D17: 3600 | E17: 12716 | F17: 19250
... A50: Total non-current liabilities | B50: 766665 | C50: 692117 | D50: 701072 | E50: 666920 | F50: 620561

Sheet Cash Flow Statement
A1: Company: FAST RETAILING CO., LTD. (6288.HK)
A2: Statement: Cash Flow Statement
A3: Units: JPY in Millions
A4: Source: manual ingestion (JP)
A6: Line Item | B6: 44439 | C6: 44804 | D6: 45169 | E6: 45535 | F6: 45900
A7: (Increase)/decrease in inventories | B7: 36749 | C7: -50896 | D7: 46908 | E7: -23540 | F7: -29855
A8: (Increase)/decrease in other assets | B8: 3494 | C8: -7125 | D8: 8354 | E8: -876 | F8: -2479
A9: (Increase)/decrease in trade and other receivables | B9: 15334 | C9: -2651 | D9: -7535 | E9: -17394 | F9: -12718
A10: Amounts deposited into bank deposits with original maturities of three months or longer | B10: -102307 | C10: -143517 | D10: -387720 | E10: -441156 | F10: -1008113
A11: Amounts withdrawn from bank deposits with original maturities of three months or longer | B11: 99943 | C11: 126774 | D11: 182882 | E11: 460241 | F11: 798490
A12: Cash and cash equivalents at the beginning of year | B12: 1093531 | C12: 1177736 | D12: 1358292 | E12: 903280 | F12: 1193560
A13: Cash and cash equivalents at the end of year | B13: 1177736 | C13: 1358292 | D13: 903280 | E13: 1193560 | F13: 893239
A14: Cash generated from operations | B14: 509672 | C14: 518010 | D14: 610338 | E14: 739726 | F14: 728879
A15: Depreciation and amortization | B15: 177910 | C15: 180275 | D15: 186872 | E15: 204388 | F15: 216492
A16: Dividends paid to non-controlling interests | B16: -2342 | C16: -11623 | D16: -20460 | E16: -18369 | F16: -26428
A17: Dividends paid to owners of the Parent | B17: -48993 | C17: -53091 | D17: -73064 | E17: -104263 | F17: -142630
... A48: Share of (profit)/loss of associates accounted for using the equity method | B48: -561 | C48: -1059 | D48: -1139 | E48: -1417 | F48: -1704

Sheet Condensed Financials
A1: FAST RETAILING CO., LTD. (6288.HK) — Condensed Financials
A4: BALANCE SHEET CLASSIFICATION
A5: Line Item | B5: Classification | C5: 44439 | D5: 44804 | E5: 45169 | F5: 45535 | G5: 45900 | H5: Notes
A6: Cash and cash equivalents | B6: Financial Asset | C6: 1177736 | D6: 1358292 | E6: 903280 | F6: 1193560 | G6: 893239
A7: Derivative financial assets | B7: =IF('Accounting Judgment'!$F$5="","Financial Asset",'Accounting Judgment'!$F$5) | C7: 27103 | D7: 124551 | E7: 132101 | F7: 111658 | G7: 94803 | H7: ⚠ Review: Generic financial-asset concept — financial vs operating purpose/hedging judgment
A8: Income taxes receivable | B8: Operating Working Capital Asset | C8: 2992 | D8: 2612 | E8: 23660 | F8: 2210 | G8: 8042
A9: Inventories | B9: Operating Working Capital Asset | C9: 394868 | D9: 485928 | E9: 449254 | F9: 474460 | G9: 510958
A10: Other assets | B10: =IF('Accounting Judgment'!$F$6="","Operating Working Capital Asset",'Accounting Judgment'!$F$6) | C10: 15270 | D10: 23835 | E10: 25372 | F10: 26897 | G10: 24662 | H10: ⚠ Review: Explicit residual balance-sheet concept identifies side/horizon but not economic nature — operating vs financial judgment
A11: Other financial assets | B11: =IF('Accounting Judgment'!$F$7="","Financial Asset",'Accounting Judgment'!$F$7) | C11: 56157 | D11: 123446 | E11: 576194 | F11: 470554 | G11: 899701 | H11: ⚠ Review: Generic financial-asset concept — financial vs operating purpose/hedging judgment
A12: Trade and other receivables | B12: Operating Working Capital Asset | C12: 50546 | D12: 60184 | E12: 66831 | F12: 83929 | G12: 96407
A13: Current tax liabilities | B13: Operating Working Capital Liability | C13: 38606 | D13: 77162 | E13: 65428 | F13: 65525 | G13: 73072
A14: Derivative financial liabilities | B14: =IF('Accounting Judgment'!$F$8="","Financial Liability",'Accounting Judgment'!$F$8) | C14: 2493 | D14: 1513 | E14: 3600 | F14: 12716 | G14: 19250 | H14: ⚠ Review: Generic financial-liability concept — financial vs operating purpose/hedging judgment
A15: Lease liabilities | B15: =IF('Accounting Judgment'!$F$9="","Operating Long-Term Liability",'Accounting Judgment'!$F$9) | C15: 117083 | D15: 123885 | E15: 126992 | F15: 130744 | G15: 126830 | H15: ⚠ Review: Lease liability concept — operating vs financial judgment
A16: Other financial liabilities | B16: =IF('Accounting Judgment'!$F$10="","Financial Liability",'Accounting Judgment'!$F$10) | C16: 104969 | D16: 209286 | E16: 61913 | F16: 104770 | G16: 150942 | H16: ⚠ Review: Generic financial-liability concept — financial vs operating purpose/hedging judgment
A17: Other liabilities | B17: =IF('Accounting Judgment'!$F$11="","Operating Working Capital Liability",'Accounting Judgment'!$F$11) | C17: 95652 | D17: 111519 | E17: 129782 | F17: 148201 | G17: 149394 | H17: ⚠ Review: Explicit residual balance-sheet concept identifies side/horizon but not economic nature — operating vs financial judgment
A18: Provisions | B18: Operating Working Capital Liability | C18: 2149 | D18: 2581 | E18: 2642 | F18: 1774 | G18: 1651
A19: Trade and other payables | B19: Operating Working Capital Liability | C19: 220057 | D19: 350294 | E19: 338901 | F19: 388656 | G19: 390149
A20: Capital stock | B20: Equity | C20: 10273 | D20: 10273 | E20: 10273 | F20: 10273 | G20: 10273
A21: Capital surplus | B21: Equity | C21: 25360 | D21: 27834 | E21: 28531 | F21: 29712 | G21: 30998
A22: Equity attributable to owners of the Parent | B22: Equity | C22: 1116484 | D22: 1561652 | E22: 1821405 | F22: 2016535 | G22: 2273115
A23: Non-controlling interests | B23: Equity | C23: 45813 | D23: 53750 | E23: 51955 | F23: 51718 | G23: 54385
A24: Other components of equity | B24: Equity | C24: 41031 | D24: 263255 | E24: 298965 | F24: 225104 | G24: 189936
A25: Retained earnings | B25: Equity | C25: 1054791 | D25: 1275102 | E25: 1498348 | F25: 1766073 | G25: 2056437
A26: Treasury stock, at cost | B26: Equity | C26: -14973 | D26: -14813 | E26: -14714 | F26: -14628 | G26: -14529
A27: Deferred tax assets | B27: Operating Long-Term Asset | C27: 37125 | D27: 8506 | E27: 38208 | F27: 32432 | G27: 40889 | H27: ⚠ Review: Deferred tax asset concept — operating vs exclude judgment
A28: Derivative financial assets | B28: =IF('Accounting Judgment'!$F$12="","Financial Asset",'Accounting Judgment'!$F$12) | C28: 22552 | D28: 134240 | E28: 114151 | F28: 66995 | G28: 33882 | H28: ⚠ Review: Generic financial-asset concept — financial vs operating purpose/hedging judgment
A29: Financial assets | B29: =IF('Accounting Judgment'!$F$13="","Financial Asset",'Accounting Judgment'!$F$13) | C29: 67122 | D29: 164340 | E29: 240363 | F29: 336302 | G29: 312438 | H29: ⚠ Review: Generic financial-asset concept — financial vs operating purpose/hedging judgment
A30: Goodwill | B30: Operating Long-Term Asset | C30: 8092 | D30: 8092 | E30: 8092 | F30: 8092 | G30: 8092
A31: Intangible assets | B31: Operating Long-Term Asset | C31: 66939 | D31: 76621 | E31: 87300 | F31: 92568 | G31: 91606
A32: Investments in associates accounted for using the equity method | B32: =IF('Accounting Judgment'!$F$14="","Operating Long-Term Asset",'Accounting Judgment'!$F$14) | C32: 18236 | D32: 18557 | E32: 18974 | F32: 19559 | G32: 31361 | H32: ⚠ Review: Equity-method investment concept — operating vs financial judgment
A33: Other assets | B33: =IF('Accounting Judgment'!$F$15="","Operating Long-Term Asset",'Accounting Judgment'!$F$15) | C33: 6520 | D33: 3690 | E33: 8846 | F33: 5888 | G33: 3803 | H33: ⚠ Review: Explicit residual balance-sheet concept identifies side/horizon but not economic nature — operating vs financial judgment
A34: Property, plant and equipment | B34: Operating Long-Term Asset | C34: 168177 | D34: 195226 | E34: 221877 | F34: 245742 | G34: 332351
A35: Right-of-use assets | B35: Operating Long-Term Asset | C35: 390537 | D35: 395634 | E35: 389183 | F35: 416712 | G35: 477111 | H35: ⚠ Review: Lease/ROU asset concept — operating vs financial judgment
A36: Deferred tax liabilities | B36: Operating Long-Term Liability | C36: 9860 | D36: 44258 | E36: 67039 | F36: 31896 | G36: 22539 | H36: ⚠ Review: Deferred tax liability concept — operating vs exclude judgment
A37: Derivative financial liabilities | B37: =IF('Accounting Judgment'!$F$16="","Financial Liability",'Accounting Judgment'!$F$16) | C37: 1042 | D37: 44 | E37: 1410 | F37: 21385 | G37: 12110 | H37: ⚠ Review: Generic financial-liability concept — financial vs operating purpose/hedging judgment
A38: Financial liabilities | B38: =IF('Accounting Judgment'!$F$17="","Financial Liability",'Accounting Judgment'!$F$17) | C38: 370799 | D38: 241022 | E38: 241068 | F38: 211147 | G38: 141071 | H38: ⚠ Review: Generic financial-liability concept — financial vs operating purpose/hedging judgment
A39: Lease liabilities | B39: =IF('Accounting Judgment'!$F$18="","Operating Long-Term Liability",'Accounting Judgment'!$F$18) | C39: 343574 | D39: 356840 | E39: 338657 | F39: 347318 | G39: 386670 | H39: ⚠ Review: Lease liability concept — operating vs financial judgment
A40: Other liabilities | B40: =IF('Accounting Judgment'!$F$19="","Operating Long-Term Liability",'Accounting Judgment'!$F$19) | C40: 2342 | D40: 2171 | E40: 2007 | F40: 2521 | G40: 2457 | H40: ⚠ Review: Explicit residual balance-sheet concept identifies side/horizon but not economic nature — operating vs financial judgment
A41: Provisions | B41: Operating Long-Term Liability | C41: 39046 | D41: 47780 | E41: 50888 | F41: 52652 | G41: 55711
A43: CONDENSED INCOME STATEMENT | B43: 44439 | C43: 44804 | D43: 45169 | E43: 45535 | F43: 45900
A44: Revenue | B44: ='Income Statement'!B21 | C44: ='Income Statement'!C21 | D44: ='Income Statement'!D21 | E44: ='Income Statement'!E21 | F44: ='Income Statement'!F21
A45: Net Income | B45: ='Income Statement'!B20 | C45: ='Income Statement'!C20 | D45: ='Income Statement'!D20 | E45: ='Income Statement'!E20 | F45: ='Income Statement'!F20
A46: Pretax Income | B46: ='Income Statement'!B19 | C46: ='Income Statement'!C19 | D46: ='Income Statement'!D19 | E46: ='Income Statement'!E19 | F46: ='Income Statement'!F19
A47: Tax Expense | B47: ='Income Statement'!B13 | C47: ='Income Statement'!C13 | D47: ='Income Statement'!D13 | E47: ='Income Statement'!E13 | F47: ='Income Statement'!F13
A48: Interest Expense | B48: ='Income Statement'!B10 | C48: ='Income Statement'!C10 | D48: ='Income Statement'!D10 | E48: ='Income Statement'!E10 | F48: ='Income Statement'!F10
A49: Interest Income | B49: ='Income Statement'!B11 | C49: ='Income Statement'!C11 | D49: ='Income Statement'!D11 | E49: ='Income Statement'!E11 | F49: ='Income Statement'!F11
A50: Lease Interest Expense (disclosed) | B50: ='Income Statement'!B26 | C50: ='Income Statement'!C26 | D50: ='Income Statement'!D26 | E50: ='Income Statement'!E26 | F50: ='Income Statement'!F26
A51: Effective Tax Rate | B51: =IF(B46=0,NA(),-B47/B46) | C51: =IF(C46=0,NA(),-C47/C46) | D51: =IF(D46=0,NA(),-D47/D46) | E51: =IF(E46=0,NA(),-E47/E46) | F51: =IF(F46=0,NA(),-F47/F46)
A52: Net Interest | B52: =-(B48+B49)-IF(AND($B$15="Operating Long-Term Liability",$B$39="Operating Long-Term Liability"),B50,IF(AND($B$15="Financial Liability",$B$39="Financial Liability"),0,NA())) | C52: =-(C48+C49)-IF(AND($B$15="Operating Long-Term Liability",$B$39="Operating Long-Term Liability"),C50,IF(AND($B$15="Financial Liability",$B$39="Financial Liability"),0,NA())) | D52: =-(D48+D49)-IF(AND($B$15="Operating Long-Term Liability",$B$39="Operating Long-Term Liability"),D50,IF(AND($B$15="Financial Liability",$B$39="Financial Liability"),0,NA())) | E52: =-(E48+E49)-IF(AND($B$15="Operating Long-Term Liability",$B$39="Operating Long-Term Liability"),E50,IF(AND($B$15="Financial Liability",$B$39="Financial Liability"),0,NA())) | F52: =-(F48+F49)-IF(AND($B$15="Operating Long-Term Liability",$B$39="Operating Long-Term Liability"),F50,IF(AND($B$15="Financial Liability",$B$39="Financial Liability"),0,NA()))
A53: Net Interest After Tax | B53: =IF(B52=0,0,IF(ISNA(B51),NA(),B52*(1-B51))) | C53: =IF(C52=0,0,IF(ISNA(C51),NA(),C52*(1-C51))) | D53: =IF(D52=0,0,IF(ISNA(D51),NA(),D52*(1-D51))) | E53: =IF(E52=0,0,IF(ISNA(E51),NA(),E52*(1-E51))) | F53: =IF(F52=0,0,IF(ISNA(F51),NA(),F52*(1-F51)))
A54: NOPAT | B54: =B45+B53 | C54: =C45+C53 | D54: =D45+D53 | E54: =E45+E53 | F54: =F45+F53
A56: CONDENSED BALANCE SHEET
A57: Operating Working Capital Assets | B57: =SUMIF($B$6:$B$41,"Operating Working Capital Asset",C$6:C$41) | C57: =SUMIF($B$6:$B$41,"Operating Working Capital Asset",D$6:D$41) | D57: =SUMIF($B$6:$B$41,"Operating Working Capital Asset",E$6:E$41) | E57: =SUMIF($B$6:$B$41,"Operating Working Capital Asset",F$6:F$41) | F57: =SUMIF($B$6:$B$41,"Operating Working Capital Asset",G$6:G$41)
A58: Operating Working Capital Liabilities | B58: =SUMIF($B$6:$B$41,"Operating Working Capital Liability",C$6:C$41) | C58: =SUMIF($B$6:$B$41,"Operating Working Capital Liability",D$6:D$41) | D58: =SUMIF($B$6:$B$41,"Operating Working Capital Liability",E$6:E$41) | E58: =SUMIF($B$6:$B$41,"Operating Working Capital Liability",F$6:F$41) | F58: =SUMIF($B$6:$B$41,"Operating Working Capital Liability",G$6:G$41)
A59: NOWC | B59: =B57-B58 | C59: =C57-C58 | D59: =D57-D58 | E59: =E57-E58 | F59: =F57-F58
A60: Operating Long-Term Assets | B60: =SUMIF($B$6:$B$41,"Operating Long-Term Asset",C$6:C$41) | C60: =SUMIF($B$6:$B$41,"Operating Long-Term Asset",D$6:D$41) | D60: =SUMIF($B$6:$B$41,"Operating Long-Term Asset",E$6:E$41) | E60: =SUMIF($B$6:$B$41,"Operating Long-Term Asset",F$6:F$41) | F60: =SUMIF($B$6:$B$41,"Operating Long-Term Asset",G$6:G$41)
A61: Operating Long-Term Liabilities | B61: =SUMIF($B$6:$B$41,"Operating Long-Term Liability",C$6:C$41) | C61: =SUMIF($B$6:$B$41,"Operating Long-Term Liability",D$6:D$41) | D61: =SUMIF($B$6:$B$41,"Operating Long-Term Liability",E$6:E$41) | E61: =SUMIF($B$6:$B$41,"Operating Long-Term Liability",F$6:F$41) | F61: =SUMIF($B$6:$B$41,"Operating Long-Term Liability",G$6:G$41)
A62: NOLA | B62: =B60-B61 | C62: =C60-C61 | D62: =D60-D61 | E62: =E60-E61 | F62: =F60-F61
A63: NOA | B63: =B59+B62 | C63: =C59+C62 | D63: =D59+D62 | E63: =E59+E62 | F63: =F59+F62
A64: Financial Assets | B64: =SUMIF($B$6:$B$41,"Financial Asset",C$6:C$41) | C64: =SUMIF($B$6:$B$41,"Financial Asset",D$6:D$41) | D64: =SUMIF($B$6:$B$41,"Financial Asset",E$6:E$41) | E64: =SUMIF($B$6:$B$41,"Financial Asset",F$6:F$41) | F64: =SUMIF($B$6:$B$41,"Financial Asset",G$6:G$41)
A65: Financial Liabilities | B65: =SUMIF($B$6:$B$41,"Financial Liability",C$6:C$41) | C65: =SUMIF($B$6:$B$41,"Financial Liability",D$6:D$41) | D65: =SUMIF($B$6:$B$41,"Financial Liability",E$6:E$41) | E65: =SUMIF($B$6:$B$41,"Financial Liability",F$6:F$41) | F65: =SUMIF($B$6:$B$41,"Financial Liability",G$6:G$41)
A66: Net Debt | B66: =B65-B64 | C66: =C65-C64 | D66: =D65-D64 | E66: =E65-E64 | F66: =F65-F64
A67: Equity (NOA - Net Debt) | B67: =B63-B66 | C67: =C63-C66 | D67: =D63-D66 | E67: =E63-E66 | F67: =F63-F66
A68: Reported Equity | B68: ='Balance Sheet'!B30 | C68: ='Balance Sheet'!C30 | D68: ='Balance Sheet'!D30 | E68: ='Balance Sheet'!E30 | F68: ='Balance Sheet'!F30
A69: Total Capital | B69: =B66+B67 | C69: =C66+C67 | D69: =D66+D67 | E69: =E66+E67 | F69: =F66+F67
A70: CHECK | B70: =IF(ABS(B67-B68)<1,"OK","CHECK") | C70: =IF(ABS(C67-C68)<1,"OK","CHECK") | D70: =IF(ABS(D67-D68)<1,"OK","CHECK") | E70: =IF(ABS(E67-E68)<1,"OK","CHECK") | F70: =IF(ABS(F67-F68)<1,"OK","CHECK")

Sheet ALT DuPont
A1: FAST RETAILING CO., LTD. — DuPont Decomposition
A2: ROE = RNOA + FLEV × Spread
A4: Metric | B4: 44439 | C4: 44804 | D4: 45169 | E4: 45535 | F4: 45900
A5: Sales Growth | B5: N/A | C5: =IF('Condensed Financials'!B44=0,NA(),'Condensed Financials'!C44/'Condensed Financials'!B44-1) | D5: =IF('Condensed Financials'!C44=0,NA(),'Condensed Financials'!D44/'Condensed Financials'!C44-1) | E5: =IF('Condensed Financials'!D44=0,NA(),'Condensed Financials'!E44/'Condensed Financials'!D44-1) | F5: =IF('Condensed Financials'!E44=0,NA(),'Condensed Financials'!F44/'Condensed Financials'!E44-1)
A6: NOPAT Margin | B6: =IF('Condensed Financials'!B44=0,NA(),'Condensed Financials'!B54/'Condensed Financials'!B44) | C6: =IF('Condensed Financials'!C44=0,NA(),'Condensed Financials'!C54/'Condensed Financials'!C44) | D6: =IF('Condensed Financials'!D44=0,NA(),'Condensed Financials'!D54/'Condensed Financials'!D44) | E6: =IF('Condensed Financials'!E44=0,NA(),'Condensed Financials'!E54/'Condensed Financials'!E44) | F6: =IF('Condensed Financials'!F44=0,NA(),'Condensed Financials'!F54/'Condensed Financials'!F44)
A7: RNOA | B7: N/A | C7: =IF((('Condensed Financials'!C63+'Condensed Financials'!B63)/2)=0,NA(),'Condensed Financials'!C54/(('Condensed Financials'!C63+'Condensed Financials'!B63)/2)) | D7: =IF((('Condensed Financials'!D63+'Condensed Financials'!C63)/2)=0,NA(),'Condensed Financials'!D54/(('Condensed Financials'!D63+'Condensed Financials'!C63)/2)) | E7: =IF((('Condensed Financials'!E63+'Condensed Financials'!D63)/2)=0,NA(),'Condensed Financials'!E54/(('Condensed Financials'!E63+'Condensed Financials'!D63)/2)) | F7: =IF((('Condensed Financials'!F63+'Condensed Financials'!E63)/2)=0,NA(),'Condensed Financials'!F54/(('Condensed Financials'!F63+'Condensed Financials'!E63)/2))
A8: After-tax CoD | B8: N/A | C8: =IF((('Condensed Financials'!C66+'Condensed Financials'!B66)/2)=0,NA(),'Condensed Financials'!C53/(('Condensed Financials'!C66+'Condensed Financials'!B66)/2)) | D8: =IF((('Condensed Financials'!D66+'Condensed Financials'!C66)/2)=0,NA(),'Condensed Financials'!D53/(('Condensed Financials'!D66+'Condensed Financials'!C66)/2)) | E8: =IF((('Condensed Financials'!E66+'Condensed Financials'!D66)/2)=0,NA(),'Condensed Financials'!E53/(('Condensed Financials'!E66+'Condensed Financials'!D66)/2)) | F8: =IF((('Condensed Financials'!F66+'Condensed Financials'!E66)/2)=0,NA(),'Condensed Financials'!F53/(('Condensed Financials'!F66+'Condensed Financials'!E66)/2))
A9: Spread | B9: N/A | C9: =C7-C8 | D9: =D7-D8 | E9: =E7-E8 | F9: =F7-F8
A10: FLEV | B10: N/A | C10: =IF((('Condensed Financials'!C67+'Condensed Financials'!B67)/2)=0,NA(),(('Condensed Financials'!C66+'Condensed Financials'!B66)/2)/(('Condensed Financials'!C67+'Condensed Financials'!B67)/2)) | D10: =IF((('Condensed Financials'!D67+'Condensed Financials'!C67)/2)=0,NA(),(('Condensed Financials'!D66+'Condensed Financials'!C66)/2)/(('Condensed Financials'!D67+'Condensed Financials'!C67)/2)) | E10: =IF((('Condensed Financials'!E67+'Condensed Financials'!D67)/2)=0,NA(),(('Condensed Financials'!E66+'Condensed Financials'!D66)/2)/(('Condensed Financials'!E67+'Condensed Financials'!D67)/2)) | F10: =IF((('Condensed Financials'!F67+'Condensed Financials'!E67)/2)=0,NA(),(('Condensed Financials'!F66+'Condensed Financials'!E66)/2)/(('Condensed Financials'!F67+'Condensed Financials'!E67)/2))
A11: ROE (decomposed) | B11: N/A | C11: =C7+C10*(C9) | D11: =D7+D10*(D9) | E11: =E7+E10*(E9) | F11: =F7+F10*(F9)
A12: Actual ROE | B12: N/A | C12: =IF((('Condensed Financials'!C67+'Condensed Financials'!B67)/2)=0,NA(),'Condensed Financials'!C45/(('Condensed Financials'!C67+'Condensed Financials'!B67)/2)) | D12: =IF((('Condensed Financials'!D67+'Condensed Financials'!C67)/2)=0,NA(),'Condensed Financials'!D45/(('Condensed Financials'!D67+'Condensed Financials'!C67)/2)) | E12: =IF((('Condensed Financials'!E67+'Condensed Financials'!D67)/2)=0,NA(),'Condensed Financials'!E45/(('Condensed Financials'!E67+'Condensed Financials'!D67)/2)) | F12: =IF((('Condensed Financials'!F67+'Condensed Financials'!E67)/2)=0,NA(),'Condensed Financials'!F45/(('Condensed Financials'!F67+'Condensed Financials'!E67)/2))
A14: RNOA DRIVER DECOMPOSITION
A15: Average NOA | B15: N/A | C15: =('Condensed Financials'!B63+'Condensed Financials'!C63)/2 | D15: =('Condensed Financials'!C63+'Condensed Financials'!D63)/2 | E15: =('Condensed Financials'!D63+'Condensed Financials'!E63)/2 | F15: =('Condensed Financials'!E63+'Condensed Financials'!F63)/2
A16: NOA Turnover | B16: N/A | C16: =IF(C15=0,NA(),'Condensed Financials'!C44/C15) | D16: =IF(D15=0,NA(),'Condensed Financials'!D44/D15) | E16: =IF(E15=0,NA(),'Condensed Financials'!E44/E15) | F16: =IF(F15=0,NA(),'Condensed Financials'!F44/F15)
A17: NOA Intensity | B17: N/A | C17: =IF('Condensed Financials'!C44=0,NA(),C15/'Condensed Financials'!C44) | D17: =IF('Condensed Financials'!D44=0,NA(),D15/'Condensed Financials'!D44) | E17: =IF('Condensed Financials'!E44=0,NA(),E15/'Condensed Financials'!E44) | F17: =IF('Condensed Financials'!F44=0,NA(),F15/'Condensed Financials'!F44)
A18: RNOA from Margin × Turnover | B18: N/A | C18: =C6*C16 | D18: =D6*D16 | E18: =E6*E16 | F18: =F6*F16
A19: RNOA DRIVER CHECK | B19: N/A | C19: =IF(ISNA(C18),"N/A",IF(ISNA(C7),"CHECK",IF(ABS(C18-C7)<0.0000001,"OK","CHECK"))) | D19: =IF(ISNA(D18),"N/A",IF(ISNA(D7),"CHECK",IF(ABS(D18-D7)<0.0000001,"OK","CHECK"))) | E19: =IF(ISNA(E18),"N/A",IF(ISNA(E7),"CHECK",IF(ABS(E18-E7)<0.0000001,"OK","CHECK"))) | F19: =IF(ISNA(F18),"N/A",IF(ISNA(F7),"CHECK",IF(ABS(F18-F7)<0.0000001,"OK","CHECK")))
A21: RNOA CHANGE ATTRIBUTION
A22: Change in NOPAT Margin | B22: N/A | C22: N/A | D22: =D6-C6 | E22: =E6-D6 | F22: =F6-E6
A23: Change in NOA Turnover | B23: N/A | C23: N/A | D23: =D16-C16 | E23: =E16-D16 | F23: =F16-E16
A24: Direct Change in RNOA | B24: N/A | C24: N/A | D24: =D7-C7 | E24: =E7-D7 | F24: =F7-E7
A25: Margin Effect on RNOA Change | B25: N/A | C25: N/A | D25: =D22*((D16+C16)/2) | E25: =E22*((E16+D16)/2) | F25: =F22*((F16+E16)/2)
A26: Turnover Effect on RNOA Change | B26: N/A | C26: N/A | D26: =D23*((D6+C6)/2) | E26: =E23*((E6+D6)/2) | F26: =F23*((F6+E6)/2)
A27: RNOA Change from Drivers | B27: N/A | C27: N/A | D27: =D25+D26 | E27: =E25+E26 | F27: =F25+F26
A28: RNOA CHANGE DRIVER CHECK | B28: N/A | C28: N/A | D28: =IF(OR(ISNA(D27),ISNA(D24)),"N/A",IF(ABS(D27-D24)<0.0000001,"OK","CHECK")) | E28: =IF(OR(ISNA(E27),ISNA(E24)),"N/A",IF(ABS(E27-E24)<0.0000001,"OK","CHECK")) | F28: =IF(OR(ISNA(F27),ISNA(F24)),"N/A",IF(ABS(F27-F24)<0.0000001,"OK","CHECK"))
A30: ROE OPERATING / FINANCING ATTRIBUTION
A31: Financing Contribution to ROE | B31: N/A | C31: =C10*C9 | D31: =D10*D9 | E31: =E10*E9 | F31: =F10*F9
A32: ROE LEVEL ATTRIBUTION CHECK | B32: N/A | C32: =IF(OR(ISNA(C7),ISNA(C31),ISNA(C11)),"N/A",IF(ABS(C7+C31-C11)<0.0000001,"OK","CHECK")) | D32: =IF(OR(ISNA(D7),ISNA(D31),ISNA(D11)),"N/A",IF(ABS(D7+D31-D11)<0.0000001,"OK","CHECK")) | E32: =IF(OR(ISNA(E7),ISNA(E31),ISNA(E11)),"N/A",IF(ABS(E7+E31-E11)<0.0000001,"OK","CHECK")) | F32: =IF(OR(ISNA(F7),ISNA(F31),ISNA(F11)),"N/A",IF(ABS(F7+F31-F11)<0.0000001,"OK","CHECK"))
A34: ROE CHANGE ATTRIBUTION
A35: Direct Change in Decomposed ROE | B35: N/A | C35: N/A | D35: =D11-C11 | E35: =E11-D11 | F35: =F11-E11
A36: Operating Effect on Change in ROE | B36: N/A | C36: N/A | D36: =D24 | E36: =E24 | F36: =F24
A37: Leverage Effect on Change in ROE | B37: N/A | C37: N/A | D37: =(D10-C10)*((D9+C9)/2) | E37: =(E10-D10)*((E9+D9)/2) | F37: =(F10-E10)*((F9+E9)/2)
A38: Spread Effect on Change in ROE | B38: N/A | C38: N/A | D38: =(D9-C9)*((D10+C10)/2) | E38: =(E9-D9)*((E10+D10)/2) | F38: =(F9-E9)*((F10+E10)/2)
A39: Financing Effect on Change in ROE | B39: N/A | C39: N/A | D39: =D37+D38 | E39: =E37+E38 | F39: =F37+F38
A40: Change in ROE from Drivers | B40: N/A | C40: N/A | D40: =D36+D39 | E40: =E36+E39 | F40: =F36+F39
A41: ROE CHANGE ATTRIBUTION CHECK | B41: N/A | C41: N/A | D41: =IF(OR(ISNA(D40),ISNA(D35)),"N/A",IF(ABS(D40-D35)<0.0000001,"OK","CHECK")) | E41: =IF(OR(ISNA(E40),ISNA(E35)),"N/A",IF(ABS(E40-E35)<0.0000001,"OK","CHECK")) | F41: =IF(OR(ISNA(F40),ISNA(F35)),"N/A",IF(ABS(F40-F35)<0.0000001,"OK","CHECK"))
A43: FIXED-ASSET INTENSITY CONTEXT
A44: Property, Plant & Equipment | B44: ='Balance Sheet'!B41 | C44: ='Balance Sheet'!C41 | D44: ='Balance Sheet'!D41 | E44: ='Balance Sheet'!E41 | F44: ='Balance Sheet'!F41
A45: Depreciation & Amortisation | B45: ='Cash Flow Statement'!B15 | C45: ='Cash Flow Statement'!C15 | D45: ='Cash Flow Statement'!D15 | E45: ='Cash Flow Statement'!E15 | F45: ='Cash Flow Statement'!F15
A46: Average PP&E | B46: N/A | C46: =(B44+C44)/2 | D46: =(C44+D44)/2 | E46: =(D44+E44)/2 | F46: =(E44+F44)/2
A47: PP&E Turnover | B47: N/A | C47: =IF(C46=0,NA(),'Condensed Financials'!C44/C46) | D47: =IF(D46=0,NA(),'Condensed Financials'!D44/D46) | E47: =IF(E46=0,NA(),'Condensed Financials'!E44/E46) | F47: =IF(F46=0,NA(),'Condensed Financials'!F44/F46)
A48: PP&E Intensity | B48: N/A | C48: =IF('Condensed Financials'!C44=0,NA(),C46/'Condensed Financials'!C44) | D48: =IF('Condensed Financials'!D44=0,NA(),D46/'Condensed Financials'!D44) | E48: =IF('Condensed Financials'!E44=0,NA(),E46/'Condensed Financials'!E44) | F48: =IF('Condensed Financials'!F44=0,NA(),F46/'Condensed Financials'!F44)
A49: Change in PP&E | B49: N/A | C49: =C44-B44 | D49: =D44-C44 | E49: =E44-D44 | F49: =F44-E44
A50: D&A / Revenue | B50: =IF('Condensed Financials'!B44=0,NA(),B45/'Condensed Financials'!B44) | C50: =IF('Condensed Financials'!C44=0,NA(),C45/'Condensed Financials'!C44) | D50: =IF('Condensed Financials'!D44=0,NA(),D45/'Condensed Financials'!D44) | E50: =IF('Condensed Financials'!E44=0,NA(),E45/'Condensed Financials'!E44) | F50: =IF('Condensed Financials'!F44=0,NA(),F45/'Condensed Financials'!F44)
A51: D&A / Average PP&E | B51: N/A | C51: =IF(C46=0,NA(),C45/C46) | D51: =IF(D46=0,NA(),D45/D46) | E51: =IF(E46=0,NA(),E45/E46) | F51: =IF(F46=0,NA(),F45/F46)
A52: FIXED-ASSET INTENSITY CHECK | B52: N/A | C52: =IF(OR(ISNA(C47),ISNA(C48)),"N/A",IF(ABS(C47*C48-1)<0.0000001,"OK","CHECK")) | D52: =IF(OR(ISNA(D47),ISNA(D48)),"N/A",IF(ABS(D47*D48-1)<0.0000001,"OK","CHECK")) | E52: =IF(OR(ISNA(E47),ISNA(E48)),"N/A",IF(ABS(E47*E48-1)<0.0000001,"OK","CHECK")) | F52: =IF(OR(ISNA(F47),ISNA(F48)),"N/A",IF(ABS(F47*F48-1)<0.0000001,"OK","CHECK"))
A54: LEASE LIABILITY CONTEXT
A55: Lease Liability | B55: ='Balance Sheet'!B18+'Balance Sheet'!B47 | C55: ='Balance Sheet'!C18+'Balance Sheet'!C47 | D55: ='Balance Sheet'!D18+'Balance Sheet'!D47 | E55: ='Balance Sheet'!E18+'Balance Sheet'!E47 | F55: ='Balance Sheet'!F18+'Balance Sheet'!F47
A56: Lease Liability / Revenue | B56: =IF('Condensed Financials'!B44=0,NA(),B55/'Condensed Financials'!B44) | C56: =IF('Condensed Financials'!C44=0,NA(),C55/'Condensed Financials'!C44) | D56: =IF('Condensed Financials'!D44=0,NA(),D55/'Condensed Financials'!D44) | E56: =IF('Condensed Financials'!E44=0,NA(),E55/'Condensed Financials'!E44) | F56: =IF('Condensed Financials'!F44=0,NA(),F55/'Condensed Financials'!F44)
A57: Change in Lease Liability | B57: N/A | C57: =C55-B55 | D57: =D55-C55 | E57: =E55-D55 | F57: =F55-E55
A58: Lease Liability Growth | B58: N/A | C58: =IF(B55=0,NA(),C55/B55-1) | D58: =IF(C55=0,NA(),D55/C55-1) | E58: =IF(D55=0,NA(),E55/D55-1) | F58: =IF(E55=0,NA(),F55/E55-1)
A60: LEASE ROU-ASSET CONTEXT
A61: Right-of-use Assets | B61: ='Balance Sheet'!B42 | C61: ='Balance Sheet'!C42 | D61: ='Balance Sheet'!D42 | E61: ='Balance Sheet'!E42 | F61: ='Balance Sheet'!F42
A62: Change in Right-of-use Assets | C62: =C61-B61 | D62: =D61-C61 | E62: =E61-D61 | F62: =F61-E61
A63: Right-of-use Assets Growth | C63: =IF(B61=0,NA(),C61/B61-1) | D63: =IF(C61=0,NA(),D61/C61-1) | E63: =IF(D61=0,NA(),E61/D61-1) | F63: =IF(E61=0,NA(),F61/E61-1)
A64: Average Right-of-use Assets | C64: =(B61+C61)/2 | D64: =(C61+D61)/2 | E64: =(D61+E61)/2 | F64: =(E61+F61)/2
A65: Average Right-of-use Assets / Revenue | C65: =IF('Condensed Financials'!C44=0,NA(),C64/'Condensed Financials'!C44) | D65: =IF('Condensed Financials'!D44=0,NA(),D64/'Condensed Financials'!D44) | E65: =IF('Condensed Financials'!E44=0,NA(),E64/'Condensed Financials'!E44) | F65: =IF('Condensed Financials'!F44=0,NA(),F64/'Condensed Financials'!F44)
A67: DEFERRED-TAX BALANCE CONTEXT
A68: Deferred Tax Assets | B68: ='Balance Sheet'!B34 | C68: ='Balance Sheet'!C34 | D68: ='Balance Sheet'!D34 | E68: ='Balance Sheet'!E34 | F68: ='Balance Sheet'!F34
A69: Deferred Tax Liabilities | B69: ='Balance Sheet'!B44 | C69: ='Balance Sheet'!C44 | D69: ='Balance Sheet'!D44 | E69: ='Balance Sheet'!E44 | F69: ='Balance Sheet'!F44
A70: Net Deferred-Tax Asset Position (DTA − DTL) | B70: =B68-B69 | C70: =C68-C69 | D70: =D68-D69 | E70: =E68-E69 | F70: =F68-F69
A71: Change in Deferred Tax Assets | C71: =C68-B68 | D71: =D68-C68 | E71: =E68-D68 | F71: =F68-E68
A72: Change in Deferred Tax Liabilities | C72: =C69-B69 | D72: =D69-C69 | E72: =E69-D69 | F72: =F69-E69
A73: Change in Net Deferred-Tax Asset Position | C73: =C70-B70 | D73: =D70-C70 | E73: =E70-D70 | F73: =F70-E70
A75: PP&E CAPEX CONTEXT
A76: Payments for Property, Plant & Equipment (reported) | B76: ='Cash Flow Statement'!B41 | C76: ='Cash Flow Statement'!C41 | D76: ='Cash Flow Statement'!D41 | E76: ='Cash Flow Statement'!E41 | F76: ='Cash Flow Statement'!F41
A77: PP&E Capex (−reported) | B77: =-B76 | C77: =-C76 | D77: =-D76 | E77: =-E76 | F77: =-F76
A78: PP&E Capex / Revenue | B78: =IF('Condensed Financials'!B44=0,NA(),B77/'Condensed Financials'!B44) | C78: =IF('Condensed Financials'!C44=0,NA(),C77/'Condensed Financials'!C44) | D78: =IF('Condensed Financials'!D44=0,NA(),D77/'Condensed Financials'!D44) | E78: =IF('Condensed Financials'!E44=0,NA(),E77/'Condensed Financials'!E44) | F78: =IF('Condensed Financials'!F44=0,NA(),F77/'Condensed Financials'!F44)
A80: LEASE REPAYMENT CONTEXT
A81: Repayments of Lease Liabilities (reported) | B81: ='Cash Flow Statement'!B47 | C81: ='Cash Flow Statement'!C47 | D81: ='Cash Flow Statement'!D47 | E81: ='Cash Flow Statement'!E47 | F81: ='Cash Flow Statement'!F47
A82: Lease Repayments (−reported) | B82: =-B81 | C82: =-C81 | D82: =-D81 | E82: =-E81 | F82: =-F81
A83: Lease Repayments / Revenue | B83: =IF('Condensed Financials'!B44=0,NA(),B82/'Condensed Financials'!B44) | C83: =IF('Condensed Financials'!C44=0,NA(),C82/'Condensed Financials'!C44) | D83: =IF('Condensed Financials'!D44=0,NA(),D82/'Condensed Financials'!D44) | E83: =IF('Condensed Financials'!E44=0,NA(),E82/'Condensed Financials'!E44) | F83: =IF('Condensed Financials'!F44=0,NA(),F82/'Condensed Financials'!F44)
A85: GOODWILL & INTANGIBLES CONTEXT
A86: Goodwill | B86: ='Balance Sheet'!B37 | C86: ='Balance Sheet'!C37 | D86: ='Balance Sheet'!D37 | E86: ='Balance Sheet'!E37 | F86: ='Balance Sheet'!F37
A87: Change in Goodwill | C87: =C86-B86 | D87: =D86-C86 | E87: =E86-D86 | F87: =F86-E86
A88: Goodwill Growth | C88: =IF(B86=0,NA(),C86/B86-1) | D88: =IF(C86=0,NA(),D86/C86-1) | E88: =IF(D86=0,NA(),E86/D86-1) | F88: =IF(E86=0,NA(),F86/E86-1)
A89: Average Goodwill | C89: =(B86+C86)/2 | D89: =(C86+D86)/2 | E89: =(D86+E86)/2 | F89: =(E86+F86)/2
A90: Average Goodwill / Revenue | C90: =IF('Condensed Financials'!C44=0,NA(),C89/'Condensed Financials'!C44) | D90: =IF('Condensed Financials'!D44=0,NA(),D89/'Condensed Financials'!D44) | E90: =IF('Condensed Financials'!E44=0,NA(),E89/'Condensed Financials'!E44) | F90: =IF('Condensed Financials'!F44=0,NA(),F89/'Condensed Financials'!F44)
A91: Intangible Assets | B91: ='Balance Sheet'!B38 | C91: ='Balance Sheet'!C38 | D91: ='Balance Sheet'!D38 | E91: ='Balance Sheet'!E38 | F91: ='Balance Sheet'!F38
A92: Change in Intangible Assets | C92: =C91-B91 | D92: =D91-C91 | E92: =E91-D91 | F92: =F91-E91
A93: Intangible Assets Growth | C93: =IF(B91=0,NA(),C91/B91-1) | D93: =IF(C91=0,NA(),D91/C91-1) | E93: =IF(D91=0,NA(),E91/D91-1) | F93: =IF(E91=0,NA(),F91/E91-1)
A94: Average Intangible Assets | C94: =(B91+C91)/2 | D94: =(C91+D91)/2 | E94: =(D91+E91)/2 | F94: =(E91+F91)/2
A95: Average Intangible Assets / Revenue | C95: =IF('Condensed Financials'!C44=0,NA(),C94/'Condensed Financials'!C44) | D95: =IF('Condensed Financials'!D44=0,NA(),D94/'Condensed Financials'!D44) | E95: =IF('Condensed Financials'!E44=0,NA(),E94/'Condensed Financials'!E44) | F95: =IF('Condensed Financials'!F44=0,NA(),F94/'Condensed Financials'!F44)
A96: Goodwill & Intangibles | B96: =B86+B91 | C96: =C86+C91 | D96: =D86+D91 | E96: =E86+E91 | F96: =F86+F91
A97: Change in Goodwill & Intangibles | C97: =C96-B96 | D97: =D96-C96 | E97: =E96-D96 | F97: =F96-E96
A98: Goodwill & Intangibles Growth | C98: =IF(B96=0,NA(),C96/B96-1) | D98: =IF(C96=0,NA(),D96/C96-1) | E98: =IF(D96=0,NA(),E96/D96-1) | F98: =IF(E96=0,NA(),F96/E96-1)
A99: Average Goodwill & Intangibles | C99: =(B96+C96)/2 | D99: =(C96+D96)/2 | E99: =(D96+E96)/2 | F99: =(E96+F96)/2
A100: Average Goodwill & Intangibles / Revenue | C100: =IF('Condensed Financials'!C44=0,NA(),C99/'Condensed Financials'!C44) | D100: =IF('Condensed Financials'!D44=0,NA(),D99/'Condensed Financials'!D44) | E100: =IF('Condensed Financials'!E44=0,NA(),E99/'Condensed Financials'!E44) | F100: =IF('Condensed Financials'!F44=0,NA(),F99/'Condensed Financials'!F44)
A101: Payments for Intangible Assets (reported) | B101: ='Cash Flow Statement'!B38 | C101: ='Cash Flow Statement'!C38 | D101: ='Cash Flow Statement'!D38 | E101: ='Cash Flow Statement'!E38 | F101: ='Cash Flow Statement'!F38
A102: Intangible Payments (−reported) | B102: =-B101 | C102: =-C101 | D102: =-D101 | E102: =-E101 | F102: =-F101
A103: Intangible Payments / Revenue | B103: =IF('Condensed Financials'!B44=0,NA(),B102/'Condensed Financials'!B44) | C103: =IF('Condensed Financials'!C44=0,NA(),C102/'Condensed Financials'!C44) | D103: =IF('Condensed Financials'!D44=0,NA(),D102/'Condensed Financials'!D44) | E103: =IF('Condensed Financials'!E44=0,NA(),E102/'Condensed Financials'!E44) | F103: =IF('Condensed Financials'!F44=0,NA(),F102/'Condensed Financials'!F44)

Sheet Accounting Judgment
A1: Accounting Judgment
A2: The supplied treatment is the model's reference treatment, not a universal accounting truth. Compare it with the listed alternative(s), choose the treatment you would defend, and explain the economic consequence.
A3: Choose a treatment in column F only. That choice drives the matching Condensed Financials classification and downstream historical schedules; leaving F blank uses the supplied reference treatment. Columns D:E are display context and must not be edited. Enter your rationale and economic consequence in G:H. Formula Check grades formula cells against the treatment currently selected in F and validates that the generated classification links remain intact; it does not grade the judgment response itself. Do not edit the linked Condensed Financials classification cell directly.
A4: Order | B4: Line item | C4: Topic | D4: Supplied reference treatment | E4: Alternative(s) to evaluate | F4: Treatment to defend | G4: Rationale | H4: Economic consequence
A5: 1 | B5: Derivative financial assets | C5: Current financial asset: financial vs operating | D5: Financial Asset | E5: Operating Working Capital Asset | F5: Financial Asset | G5: The reference model treats a generically disclosed current financial instrument as a financial asset absent evidence that it is integral to normal operations or an operating hedge. | H5: Financial-asset treatment lowers Net Debt; operating-WC treatment raises NOWC/NOA by the same balance. Implied equity is unchanged by the classification switch alone.
A6: 2 | B6: Other assets | C6: Other current asset: operating vs financial | D6: Operating Working Capital Asset | E6: Financial Asset | F6: Operating Working Capital Asset | G6: The residual current-asset concept proves balance-sheet side and horizon but not whether the balance is operating working capital or a financial asset in economic substance. | H6: Operating-WC treatment raises NOWC/NOA; financial-asset treatment lowers Net Debt by the same balance. Implied equity is unchanged by the classification switch alone.
A7: 3 | B7: Other financial assets | C7: Current financial asset: financial vs operating | D7: Financial Asset | E7: Operating Working Capital Asset | F7: Financial Asset | G7: The reference model treats a generically disclosed current financial instrument as a financial asset absent evidence that it is integral to normal operations or an operating hedge. | H7: Financial-asset treatment lowers Net Debt; operating-WC treatment raises NOWC/NOA by the same balance. Implied equity is unchanged by the classification switch alone.
A8: 4 | B8: Derivative financial liabilities | C8: Current financial liability: financial vs operating | D8: Financial Liability | E8: Operating Working Capital Liability | F8: Financial Liability | G8: The reference model treats a generically disclosed current financial instrument as a financial liability absent evidence that it is an operating payable or operating hedge. | H8: Financial-liability treatment raises Net Debt; operating-WC-liability treatment lowers NOWC/NOA by the same balance. Implied equity is unchanged by the classification switch alone.
A9: 5 | B9: Lease liabilities | C9: Lease liability operating vs financing | D9: Operating Long-Term Liability | E9: Financial Liability | F9: Operating Long-Term Liability | G9: The reference model keeps the liability in operating long-term liabilities under its current lease convention. Treating it as a financial liability is also defensible when the lease obligation is viewed as debt-like financing. | H9: Operating-liability treatment lowers NOLA/NOA; financial-liability treatment raises Net Debt by the same balance. Implied equity is unchanged from this classification switch alone, but RNOA versus FLEV/Spread interpretation changes.
A10: 6 | B10: Other financial liabilities | C10: Current financial liability: financial vs operating | D10: Financial Liability | E10: Operating Working Capital Liability | F10: Financial Liability | G10: The reference model treats a generically disclosed current financial instrument as a financial liability absent evidence that it is an operating payable or operating hedge. | H10: Financial-liability treatment raises Net Debt; operating-WC-liability treatment lowers NOWC/NOA by the same balance. Implied equity is unchanged by the classification switch alone.
A11: 7 | B11: Other liabilities | C11: Other current liability: operating vs financial | D11: Operating Working Capital Liability | E11: Financial Liability | F11: Operating Working Capital Liability | G11: The residual current-liability concept proves balance-sheet side and horizon but not whether the balance is an operating working-capital liability or a financial liability in economic substance. | H11: Operating-WC-liability treatment lowers NOWC/NOA; financial-liability treatment raises Net Debt by the same balance. Implied equity is unchanged by the classification switch alone.
A12: 8 | B12: Derivative financial assets | C12: Non-current financial asset: financial vs operating | D12: Financial Asset | E12: Operating Long-Term Asset | F12: Financial Asset | G12: The reference model treats a generically disclosed non-current financial instrument as a financial asset absent evidence that it is strategically or operationally required. | H12: Financial-asset treatment lowers Net Debt; operating-LT treatment raises NOLA/NOA by the same balance. Implied equity is unchanged by the classification switch alone.
A13: 9 | B13: Financial assets | C13: Non-current financial asset: financial vs operating | D13: Financial Asset | E13: Operating Long-Term Asset | F13: Financial Asset | G13: The reference model treats a generically disclosed non-current financial instrument as a financial asset absent evidence that it is strategically or operationally required. | H13: Financial-asset treatment lowers Net Debt; operating-LT treatment raises NOLA/NOA by the same balance. Implied equity is unchanged by the classification switch alone.
A14: 10 | B14: Investments in associates accounted for using the equity method | C14: Equity-method investment operating vs financing | D14: Operating Long-Term Asset | E14: Financial Asset | F14: Operating Long-Term Asset | G14: The reference model treats the investment as an operating long-term asset when it is viewed as strategically tied to the operating business. Financial-asset treatment is defensible when the holding is primarily non-operating/investment in nature. | H14: Operating-asset treatment raises NOLA/NOA; financial-asset treatment lowers Net Debt by the same balance. Implied equity is unchanged from this classification switch alone, but RNOA and leverage interpretation change.
A15: 11 | B15: Other assets | C15: Other non-current asset: operating vs financial | D15: Operating Long-Term Asset | E15: Financial Asset | F15: Operating Long-Term Asset | G15: The residual non-current-asset concept proves balance-sheet side and horizon but not whether the balance is an operating long-term asset or a financial asset in economic substance. | H15: Operating-LT treatment raises NOLA/NOA; financial-asset treatment lowers Net Debt by the same balance. Implied equity is unchanged by the classification switch alone.
A16: 12 | B16: Derivative financial liabilities | C16: Non-current financial liability: financial vs operating | D16: Financial Liability | E16: Operating Long-Term Liability | F16: Financial Liability | G16: The reference model treats a generically disclosed non-current financial instrument as a financial liability absent evidence that it is an operating long-term obligation or operating hedge. | H16: Financial-liability treatment raises Net Debt; operating-LT-liability treatment lowers NOLA/NOA by the same balance. Implied equity is unchanged by the classification switch alone.
... A19: 15 | B19: Other liabilities | C19: Other non-current liability: operating vs financial | D19: Operating Long-Term Liability | E19: Financial Liability | F19: Operating Long-Term Liability | G19: The residual non-current-liability concept proves balance-sheet side and horizon but not whether the balance is an operating long-term liability or a financial liability in economic substance. | H19: Operating-LT-liability treatment lowers NOLA/NOA; financial-liability treatment raises Net Debt by the same balance. Implied equity is unchanged by the classification switch alone.

Sheet Ownership Attribution
A1: FAST RETAILING CO., LTD. — Ownership Attribution
A2: Parent / NCI profit and equity bridges and parent ROE. Consolidated DuPont / NOA / Net Debt remain unchanged; parent ROE is a separate shareholder-attribution diagnostic.
A4: Metric | B4: 44439 | C4: 44804 | D4: 45169 | E4: 45535 | F4: 45900
A5: Parent Profit | B5: ='Income Statement'!B18 | C5: ='Income Statement'!C18 | D5: ='Income Statement'!D18 | E5: ='Income Statement'!E18 | F5: ='Income Statement'!F18
A6: NCI Profit | B6: ='Income Statement'!B14 | C6: ='Income Statement'!C14 | D6: ='Income Statement'!D14 | E6: ='Income Statement'!E14 | F6: ='Income Statement'!F14
A7: Total Profit | B7: ='Income Statement'!B20 | C7: ='Income Statement'!C20 | D7: ='Income Statement'!D20 | E7: ='Income Statement'!E20 | F7: ='Income Statement'!F20
A8: Profit Attribution Gap | B8: =B5+B6-B7 | C8: =C5+C6-C7 | D8: =D5+D6-D7 | E8: =E5+E6-E7 | F8: =F5+F6-F7
A10: Parent Equity | B10: ='Balance Sheet'!B26 | C10: ='Balance Sheet'!C26 | D10: ='Balance Sheet'!D26 | E10: ='Balance Sheet'!E26 | F10: ='Balance Sheet'!F26
A11: NCI Equity | B11: ='Balance Sheet'!B27 | C11: ='Balance Sheet'!C27 | D11: ='Balance Sheet'!D27 | E11: ='Balance Sheet'!E27 | F11: ='Balance Sheet'!F27
A12: Total Equity | B12: ='Balance Sheet'!B30 | C12: ='Balance Sheet'!C30 | D12: ='Balance Sheet'!D30 | E12: ='Balance Sheet'!E30 | F12: ='Balance Sheet'!F30
A13: Equity Attribution Gap | B13: =B10+B11-B12 | C13: =C10+C11-C12 | D13: =D10+D11-D12 | E13: =E10+E11-E12 | F13: =F10+F11-F12
A15: Parent ROE | B15: N/A | C15: =IF((C10+B10)=0,NA(),C5/((C10+B10)/2)) | D15: =IF((D10+C10)=0,NA(),D5/((D10+C10)/2)) | E15: =IF((E10+D10)=0,NA(),E5/((E10+D10)/2)) | F15: =IF((F10+E10)=0,NA(),F5/((F10+E10)/2))

Sheet Earnings Quality
A1: FAST RETAILING CO., LTD. — Earnings Quality
A2: Historical cash-conversion and accrual diagnostics. These are mechanical diagnostics, not an automatic quality score.
A4: Metric | B4: 44439 | C4: 44804 | D4: 45169 | E4: 45535 | F4: 45900
A5: Operating Cash Flow | B5: ='Cash Flow Statement'!B30 | C5: ='Cash Flow Statement'!C30 | D5: ='Cash Flow Statement'!D30 | E5: ='Cash Flow Statement'!E30 | F5: ='Cash Flow Statement'!F30
A6: Reported Net Income | B6: ='Condensed Financials'!B45 | C6: ='Condensed Financials'!C45 | D6: ='Condensed Financials'!D45 | E6: ='Condensed Financials'!E45 | F6: ='Condensed Financials'!F45
A7: Cash Conversion Ratio | B7: =IF(B6=0,NA(),B5/B6) | C7: =IF(C6=0,NA(),C5/C6) | D7: =IF(D6=0,NA(),D5/D6) | E7: =IF(E6=0,NA(),E5/E6) | F7: =IF(F6=0,NA(),F5/F6)
A8: Total Accruals (Net Income - CFO) | B8: =B6-B5 | C8: =C6-C5 | D8: =D6-D5 | E8: =E6-E5 | F8: =F6-F5
A10: Total Assets | B10: ='Balance Sheet'!B7 | C10: ='Balance Sheet'!C7 | D10: ='Balance Sheet'!D7 | E10: ='Balance Sheet'!E7 | F10: ='Balance Sheet'!F7
A11: Average Total Assets | C11: =(B10+C10)/2 | D11: =(C10+D10)/2 | E11: =(D10+E10)/2 | F11: =(E10+F10)/2
A12: Accrual Ratio | C12: =IF(C11=0,NA(),C8/C11) | D12: =IF(D11=0,NA(),D8/D11) | E12: =IF(E11=0,NA(),E8/E11) | F12: =IF(F11=0,NA(),F8/F11)
A14: EARNINGS QUALITY TREND DIAGNOSTICS
A15: Change in Operating Cash Flow | B15: N/A | C15: =C5-B5 | D15: =D5-C5 | E15: =E5-D5 | F15: =F5-E5
A16: Change in Cash Conversion Ratio | B16: N/A | C16: =C7-B7 | D16: =D7-C7 | E16: =E7-D7 | F16: =F7-E7
A17: Change in Total Accruals | B17: N/A | C17: =C8-B8 | D17: =D8-C8 | E17: =E8-D8 | F17: =F8-E8
A18: Change in Accrual Ratio | B18: N/A | C18: N/A | D18: =D12-C12 | E18: =E12-D12 | F18: =F12-E12
A19: EARNINGS QUALITY CHANGE CHECK | B19: N/A | C19: =IF(ABS(C17-((C6-B6)-C15))<0.01,"OK","CHECK") | D19: =IF(ABS(D17-((D6-C6)-D15))<0.01,"OK","CHECK") | E19: =IF(ABS(E17-((E6-D6)-E15))<0.01,"OK","CHECK") | F19: =IF(ABS(F17-((F6-E6)-F15))<0.01,"OK","CHECK")

Sheet Working Capital Analysis
A1: Working Capital Analysis
A2: Relate classified operating working capital to Revenue and identify how much incremental NOWC accompanies changes in sales.
A3: These are diagnostics, not automatic judgments. Positive Change in NOWC is an operating cash use; negative Change in NOWC is a release. Annual data alone does not prove seasonality or deterioration.
A5: Metric | B5: 44439 | C5: 44804 | D5: 45169 | E5: 45535 | F5: 45900
A6: Revenue | B6: ='Condensed Financials'!B44 | C6: ='Condensed Financials'!C44 | D6: ='Condensed Financials'!D44 | E6: ='Condensed Financials'!E44 | F6: ='Condensed Financials'!F44
A7: Operating Working Capital Assets | B7: ='Condensed Financials'!B57 | C7: ='Condensed Financials'!C57 | D7: ='Condensed Financials'!D57 | E7: ='Condensed Financials'!E57 | F7: ='Condensed Financials'!F57
A8: Operating Working Capital Liabilities | B8: ='Condensed Financials'!B58 | C8: ='Condensed Financials'!C58 | D8: ='Condensed Financials'!D58 | E8: ='Condensed Financials'!E58 | F8: ='Condensed Financials'!F58
A9: NOWC | B9: ='Condensed Financials'!B59 | C9: ='Condensed Financials'!C59 | D9: ='Condensed Financials'!D59 | E9: ='Condensed Financials'!E59 | F9: ='Condensed Financials'!F59
A11: OWCA / Revenue | B11: =IF(B6=0,NA(),B7/B6) | C11: =IF(C6=0,NA(),C7/C6) | D11: =IF(D6=0,NA(),D7/D6) | E11: =IF(E6=0,NA(),E7/E6) | F11: =IF(F6=0,NA(),F7/F6)
A12: OWCL / Revenue | B12: =IF(B6=0,NA(),B8/B6) | C12: =IF(C6=0,NA(),C8/C6) | D12: =IF(D6=0,NA(),D8/D6) | E12: =IF(E6=0,NA(),E8/E6) | F12: =IF(F6=0,NA(),F8/F6)
A13: NOWC / Revenue | B13: =IF(B6=0,NA(),B9/B6) | C13: =IF(C6=0,NA(),C9/C6) | D13: =IF(D6=0,NA(),D9/D6) | E13: =IF(E6=0,NA(),E9/E6) | F13: =IF(F6=0,NA(),F9/F6)
A14: Change in Revenue | B14: N/A | C14: =C6-B6 | D14: =D6-C6 | E14: =E6-D6 | F14: =F6-E6
A15: Change in NOWC | B15: N/A | C15: =C9-B9 | D15: =D9-C9 | E15: =E9-D9 | F15: =F9-E9
A16: Incremental NOWC / Change in Revenue | B16: N/A | C16: =IF(C14=0,NA(),C15/C14) | D16: =IF(D14=0,NA(),D15/D14) | E16: =IF(E14=0,NA(),E15/E14) | F16: =IF(F14=0,NA(),F15/F14)
A18: WORKING-CAPITAL DRIVER DECOMPOSITION
A19: Change in OWCA | B19: N/A | C19: =C7-B7 | D19: =D7-C7 | E19: =E7-D7 | F19: =F7-E7
A20: Change in OWCL | B20: N/A | C20: =C8-B8 | D20: =D8-C8 | E20: =E8-D8 | F20: =F8-E8
A21: Change in NOWC from Components | B21: N/A | C21: =C19-C20 | D21: =D19-D20 | E21: =E19-E20 | F21: =F19-F20
A22: Incremental OWCA / Change in Revenue | B22: N/A | C22: =IF(C14=0,NA(),C19/C14) | D22: =IF(D14=0,NA(),D19/D14) | E22: =IF(E14=0,NA(),E19/E14) | F22: =IF(F14=0,NA(),F19/F14)
A23: Incremental OWCL / Change in Revenue | B23: N/A | C23: =IF(C14=0,NA(),C20/C14) | D23: =IF(D14=0,NA(),D20/D14) | E23: =IF(E14=0,NA(),E20/E14) | F23: =IF(F14=0,NA(),F20/F14)
A24: DRIVER DECOMPOSITION CHECK | B24: N/A | C24: =IF(ABS(C21-C15)<0.01,"OK","CHECK") | D24: =IF(ABS(D21-D15)<0.01,"OK","CHECK") | E24: =IF(ABS(E21-E15)<0.01,"OK","CHECK") | F24: =IF(ABS(F21-F15)<0.01,"OK","CHECK")

Sheet Per Share Analysis
A1: FAST RETAILING CO., LTD. — Per Share Analysis
A2: Historical per-share diagnostics using supplied diluted weighted-average shares. Share counts are source inputs, not practice cells.
A4: Metric | B4: 44439 | C4: 44804 | D4: 45169 | E4: 45535 | F4: 45900
A5: Parent-Attributable Profit | B5: ='Income Statement'!B18 | C5: ='Income Statement'!C18 | D5: ='Income Statement'!D18 | E5: ='Income Statement'!E18 | F5: ='Income Statement'!F18
A6: NOPAT | B6: ='Condensed Financials'!B54 | C6: ='Condensed Financials'!C54 | D6: ='Condensed Financials'!D54 | E6: ='Condensed Financials'!E54 | F6: ='Condensed Financials'!F54
A7: Diluted Weighted-Average Shares | B7: 306.87178 | C7: 306.96962 | D7: 307.13887 | E7: 307.2318 | F7: 307.2478
A8: Share Basis: Split-adjusted comparable basis
A9: Diluted EPS (Comparable Basis) | B9: =IF(B7<=0,NA(),B5/B7) | C9: =IF(C7<=0,NA(),C5/C7) | D9: =IF(D7<=0,NA(),D5/D7) | E9: =IF(E7<=0,NA(),E5/E7) | F9: =IF(F7<=0,NA(),F5/F7)
A10: NOPAT per Diluted Share | B10: =IF(B7<=0,NA(),B6/B7) | C10: =IF(C7<=0,NA(),C6/C7) | D10: =IF(D7<=0,NA(),D6/D7) | E10: =IF(E7<=0,NA(),E6/E7) | F10: =IF(F7<=0,NA(),F6/F7)
A12: Change in Diluted EPS | B12: N/A | C12: =C9-B9 | D12: =D9-C9 | E12: =E9-D9 | F12: =F9-E9
A13: Change in Diluted Weighted-Average Shares | B13: N/A | C13: =C7-B7 | D13: =D7-C7 | E13: =E7-D7 | F13: =F7-E7
A15: DILUTED EPS CHANGE ATTRIBUTION
A16: Change in Per-Share Earnings Numerator | B16: N/A | C16: =C5-B5 | D16: =D5-C5 | E16: =E5-D5 | F16: =F5-E5
A17: Earnings Effect on Change in Diluted EPS | B17: N/A | C17: =C16*((1/C7+1/B7)/2) | D17: =D16*((1/D7+1/C7)/2) | E17: =E16*((1/E7+1/D7)/2) | F17: =F16*((1/F7+1/E7)/2)
A18: Share-Count Effect on Change in Diluted EPS | B18: N/A | C18: =((1/C7)-(1/B7))*((C5+B5)/2) | D18: =((1/D7)-(1/C7))*((D5+C5)/2) | E18: =((1/E7)-(1/D7))*((E5+D5)/2) | F18: =((1/F7)-(1/E7))*((F5+E5)/2)
A19: Diluted EPS Change from Drivers | B19: N/A | C19: =C17+C18 | D19: =D17+D18 | E19: =E17+E18 | F19: =F17+F18
A20: DILUTED EPS CHANGE ATTRIBUTION CHECK | B20: N/A | C20: =IF(ABS(C19-C12)<0.0000001,"OK","CHECK") | D20: =IF(ABS(D19-D12)<0.0000001,"OK","CHECK") | E20: =IF(ABS(E19-E12)<0.0000001,"OK","CHECK") | F20: =IF(ABS(F19-F12)<0.0000001,"OK","CHECK")

Sheet Model_Bear
A1: Deferred from historical-only v1

Sheet Model_Base
A1: Deferred from historical-only v1

Sheet Model_Bull
A1: Deferred from historical-only v1

Sheet Scenario_Summary
A1: Deferred from historical-only v1

Sheet _ComponentMap
A1: id | B1: order | C1: title | D1: short_hint | E1: semantic_key | F1: category | G1: tab | H1: cell | I1: formula | J1: expected_value | K1: tolerance | L1: depends_on | M1: hints | N1: related_cells | O1: status | P1: family_id | Q1: family_order | R1: period_index | S1: period_end
A2: revenue_link__20210831 | B2: 1 | C2: Revenue historical source link | D2: Link Revenue from the Income Statement into Condensed Financials. | E2: condensed.revenue_link.2021-08-31 | F2: accounting | G2: Condensed Financials | H2: B44 | I2: ='Income Statement'!B21 | J2: 2132992 | K2: 0.01 | M2: Pull the Revenue line from the Income Statement for the same fiscal period. | O2: pending | P2: revenue_link | Q2: 1 | R2: 0 | S2: 2021-08-31
A3: revenue_link__20220831 | B3: 2 | C3: Revenue historical source link | D3: Link Revenue from the Income Statement into Condensed Financials. | E3: condensed.revenue_link.2022-08-31 | F3: accounting | G3: Condensed Financials | H3: C44 | I3: ='Income Statement'!C21 | J3: 2301122 | K3: 0.01 | M3: Pull the Revenue line from the Income Statement for the same fiscal period. | O3: pending | P3: revenue_link | Q3: 1 | R3: 1 | S3: 2022-08-31
A4: revenue_link__20230831 | B4: 3 | C4: Revenue historical source link | D4: Link Revenue from the Income Statement into Condensed Financials. | E4: condensed.revenue_link.2023-08-31 | F4: accounting | G4: Condensed Financials | H4: D44 | I4: ='Income Statement'!D21 | J4: 2766557 | K4: 0.01 | M4: Pull the Revenue line from the Income Statement for the same fiscal period. | O4: pending | P4: revenue_link | Q4: 1 | R4: 2 | S4: 2023-08-31
A5: revenue_link__20240831 | B5: 4 | C5: Revenue historical source link | D5: Link Revenue from the Income Statement into Condensed Financials. | E5: condensed.revenue_link.2024-08-31 | F5: accounting | G5: Condensed Financials | H5: E44 | I5: ='Income Statement'!E21 | J5: 3103836 | K5: 0.01 | M5: Pull the Revenue line from the Income Statement for the same fiscal period. | O5: pending | P5: revenue_link | Q5: 1 | R5: 3 | S5: 2024-08-31
A6: revenue_link__20250831 | B6: 5 | C6: Revenue historical source link | D6: Link Revenue from the Income Statement into Condensed Financials. | E6: condensed.revenue_link.2025-08-31 | F6: accounting | G6: Condensed Financials | H6: F44 | I6: ='Income Statement'!F21 | J6: 3400539 | K6: 0.01 | M6: Pull the Revenue line from the Income Statement for the same fiscal period. | O6: pending | P6: revenue_link | Q6: 1 | R6: 4 | S6: 2025-08-31
A7: net_income_link__20210831 | B7: 6 | C7: Net Income historical source link | D7: Link Net Income from the Income Statement into Condensed Financials. | E7: condensed.net_income_link.2021-08-31 | F7: accounting | G7: Condensed Financials | H7: B45 | I7: ='Income Statement'!B20 | J7: 175684 | K7: 0.01 | M7: Pull Net Income from the Income Statement for the same fiscal period. | O7: pending | P7: net_income_link | Q7: 2 | R7: 0 | S7: 2021-08-31
A8: net_income_link__20220831 | B8: 7 | C8: Net Income historical source link | D8: Link Net Income from the Income Statement into Condensed Financials. | E8: condensed.net_income_link.2022-08-31 | F8: accounting | G8: Condensed Financials | H8: C45 | I8: ='Income Statement'!C20 | J8: 284750 | K8: 0.01 | M8: Pull Net Income from the Income Statement for the same fiscal period. | O8: pending | P8: net_income_link | Q8: 2 | R8: 1 | S8: 2022-08-31
A9: net_income_link__20230831 | B9: 8 | C9: Net Income historical source link | D9: Link Net Income from the Income Statement into Condensed Financials. | E9: condensed.net_income_link.2023-08-31 | F9: accounting | G9: Condensed Financials | H9: D45 | I9: ='Income Statement'!D20 | J9: 315171 | K9: 0.01 | M9: Pull Net Income from the Income Statement for the same fiscal period. | O9: pending | P9: net_income_link | Q9: 2 | R9: 2 | S9: 2023-08-31
A10: net_income_link__20240831 | B10: 9 | C10: Net Income historical source link | D10: Link Net Income from the Income Statement into Condensed Financials. | E10: condensed.net_income_link.2024-08-31 | F10: accounting | G10: Condensed Financials | H10: E45 | I10: ='Income Statement'!E20 | J10: 393605 | K10: 0.01 | M10: Pull Net Income from the Income Statement for the same fiscal period. | O10: pending | P10: net_income_link | Q10: 2 | R10: 3 | S10: 2024-08-31
A11: net_income_link__20250831 | B11: 10 | C11: Net Income historical source link | D11: Link Net Income from the Income Statement into Condensed Financials. | E11: condensed.net_income_link.2025-08-31 | F11: accounting | G11: Condensed Financials | H11: F45 | I11: ='Income Statement'!F20 | J11: 459153 | K11: 0.01 | M11: Pull Net Income from the Income Statement for the same fiscal period. | O11: pending | P11: net_income_link | Q11: 2 | R11: 4 | S11: 2025-08-31
A12: effective_tax_rate_fy__20210831 | B12: 11 | C12: Effective tax rate | D12: Relate tax expense to pretax income using the model's sign convention. | E12: condensed.effective_tax_rate.2021-08-31 | F12: accounting | G12: Condensed Financials | H12: B51 | I12: =IF(B46=0,NA(),-B47/B46) | J12: 0.33921586 | K12: 0.01 | M12: Effective tax rate uses pretax income in the denominator.|Preserve the model's sign convention for tax expense.|A zero Pretax Income makes Effective Tax Rate undefined (#N/A). | O12: pending | P12: effective_tax_rate_fy | Q12: 3 | R12: 0 | S12: 2021-08-31
A13: effective_tax_rate_fy__20220831 | B13: 12 | C13: Effective tax rate | D13: Relate tax expense to pretax income using the model's sign convention. | E13: condensed.effective_tax_rate.2022-08-31 | F13: accounting | G13: Condensed Financials | H13: C51 | I13: =IF(C46=0,NA(),-C47/C46) | J13: 0.31150625 | K13: 0.01 | M13: Effective tax rate uses pretax income in the denominator.|Preserve the model's sign convention for tax expense.|A zero Pretax Income makes Effective Tax Rate undefined (#N/A). | O13: pending | P13: effective_tax_rate_fy | Q13: 3 | R13: 1 | S13: 2022-08-31
A14: effective_tax_rate_fy__20230831 | B14: 13 | C14: Effective tax rate | D14: Relate tax expense to pretax income using the model's sign convention. | E14: condensed.effective_tax_rate.2023-08-31 | F14: accounting | G14: Condensed Financials | H14: D51 | I14: =IF(D46=0,NA(),-D47/D46) | J14: 0.28029448 | K14: 0.01 | M14: Effective tax rate uses pretax income in the denominator.|Preserve the model's sign convention for tax expense.|A zero Pretax Income makes Effective Tax Rate undefined (#N/A). | O14: pending | P14: effective_tax_rate_fy | Q14: 3 | R14: 2 | S14: 2023-08-31
A15: effective_tax_rate_fy__20240831 | B15: 14 | C15: Effective tax rate | D15: Relate tax expense to pretax income using the model's sign convention. | E15: condensed.effective_tax_rate.2024-08-31 | F15: accounting | G15: Condensed Financials | H15: E51 | I15: =IF(E46=0,NA(),-E47/E46) | J15: 0.29360321 | K15: 0.01 | M15: Effective tax rate uses pretax income in the denominator.|Preserve the model's sign convention for tax expense.|A zero Pretax Income makes Effective Tax Rate undefined (#N/A). | O15: pending | P15: effective_tax_rate_fy | Q15: 3 | R15: 3 | S15: 2024-08-31
A16: effective_tax_rate_fy__20250831 | B16: 15 | C16: Effective tax rate | D16: Relate tax expense to pretax income using the model's sign convention. | E16: condensed.effective_tax_rate.2025-08-31 | F16: accounting | G16: Condensed Financials | H16: F51 | I16: =IF(F46=0,NA(),-F47/F46) | J16: 0.29423401 | K16: 0.01 | M16: Effective tax rate uses pretax income in the denominator.|Preserve the model's sign convention for tax expense.|A zero Pretax Income makes Effective Tax Rate undefined (#N/A). | O16: pending | P16: effective_tax_rate_fy | Q16: 3 | R16: 4 | S16: 2025-08-31
A17: net_interest_fy__20210831 | B17: 16 | C17: Net interest | D17: Combine interest expense and interest income into the financing result. | E17: condensed.net_interest.2021-08-31 | F17: accounting | G17: Condensed Financials | H17: B52 | I17: =-(B48+B49)-IF(AND($B$15="Operating Long-Term Liability",$B$39="Operating Long-Term Liability"),B50,IF(AND($B$15="Financial Liability",$B$39="Financial Liability"),0,NA())) | J17: -21708 | K17: 0.01 | M17: Net interest consolidates interest expense and interest income.|Use the explicitly supplied Interest Expense and Interest Income lines with the model's sign convention. | O17: pending | P17: net_interest_fy | Q17: 4 | R17: 0 | S17: 2021-08-31
A18: net_interest_fy__20220831 | B18: 17 | C18: Net interest | D18: Combine interest expense and interest income into the financing result. | E18: condensed.net_interest.2022-08-31 | F18: accounting | G18: Condensed Financials | H18: C52 | I18: =-(C48+C49)-IF(AND($B$15="Operating Long-Term Liability",$B$39="Operating Long-Term Liability"),C50,IF(AND($B$15="Financial Liability",$B$39="Financial Liability"),0,NA())) | J18: -121017 | K18: 0.01 | M18: Net interest consolidates interest expense and interest income.|Use the explicitly supplied Interest Expense and Interest Income lines with the model's sign convention. | O18: pending | P18: net_interest_fy | Q18: 4 | R18: 1 | S18: 2022-08-31
A19: net_interest_fy__20230831 | B19: 18 | C19: Net interest | D19: Combine interest expense and interest income into the financing result. | E19: condensed.net_interest.2023-08-31 | F19: accounting | G19: Condensed Financials | H19: D52 | I19: =-(D48+D49)-IF(AND($B$15="Operating Long-Term Liability",$B$39="Operating Long-Term Liability"),D50,IF(AND($B$15="Financial Liability",$B$39="Financial Liability"),0,NA())) | J19: -62015 | K19: 0.01 | M19: Net interest consolidates interest expense and interest income.|Use the explicitly supplied Interest Expense and Interest Income lines with the model's sign convention. | O19: pending | P19: net_interest_fy | Q19: 4 | R19: 2 | S19: 2023-08-31
A20: net_interest_fy__20240831 | B20: 19 | C20: Net interest | D20: Combine interest expense and interest income into the financing result. | E20: condensed.net_interest.2024-08-31 | F20: accounting | G20: Condensed Financials | H20: E52 | I20: =-(E48+E49)-IF(AND($B$15="Operating Long-Term Liability",$B$39="Operating Long-Term Liability"),E50,IF(AND($B$15="Financial Liability",$B$39="Financial Liability"),0,NA())) | J20: -62805 | K20: 0.01 | M20: Net interest consolidates interest expense and interest income.|Use the explicitly supplied Interest Expense and Interest Income lines with the model's sign convention. | O20: pending | P20: net_interest_fy | Q20: 4 | R20: 3 | S20: 2024-08-31
A21: net_interest_fy__20250831 | B21: 20 | C21: Net interest | D21: Combine interest expense and interest income into the financing result. | E21: condensed.net_interest.2025-08-31 | F21: accounting | G21: Condensed Financials | H21: F52 | I21: =-(F48+F49)-IF(AND($B$15="Operating Long-Term Liability",$B$39="Operating Long-Term Liability"),F50,IF(AND($B$15="Financial Liability",$B$39="Financial Liability"),0,NA())) | J21: -94773 | K21: 0.01 | M21: Net interest consolidates interest expense and interest income.|Use the explicitly supplied Interest Expense and Interest Income lines with the model's sign convention. | O21: pending | P21: net_interest_fy | Q21: 4 | R21: 4 | S21: 2025-08-31
A22: net_interest_after_tax_fy__20210831 | B22: 21 | C22: Net interest after tax | D22: Apply the effective tax rate once to net interest. | E22: condensed.net_interest_after_tax.2021-08-31 | F22: accounting | G22: Condensed Financials | H22: B53 | I22: =IF(B52=0,0,IF(ISNA(B51),NA(),B52*(1-B51))) | J22: -14344.302 | K22: 0.01 | L22: effective_tax_rate_fy__20210831,net_interest_fy__20210831 | M22: After-tax net interest = Net Interest × (1 − Effective Tax Rate).|Do not tax-adjust a rate that is already after tax.|A zero Net Interest amount remains zero even if ETR is undefined; otherwise undefined ETR propagates. | O22: pending | P22: net_interest_after_tax_fy | Q22: 5 | R22: 0 | S22: 2021-08-31
A23: net_interest_after_tax_fy__20220831 | B23: 22 | C23: Net interest after tax | D23: Apply the effective tax rate once to net interest. | E23: condensed.net_interest_after_tax.2022-08-31 | F23: accounting | G23: Condensed Financials | H23: C53 | I23: =IF(C52=0,0,IF(ISNA(C51),NA(),C52*(1-C51))) | J23: -83319.448 | K23: 0.01 | L23: effective_tax_rate_fy__20220831,net_interest_fy__20220831 | M23: After-tax net interest = Net Interest × (1 − Effective Tax Rate).|Do not tax-adjust a rate that is already after tax.|A zero Net Interest amount remains zero even if ETR is undefined; otherwise undefined ETR propagates. | O23: pending | P23: net_interest_after_tax_fy | Q23: 5 | R23: 1 | S23: 2022-08-31
A24: net_interest_after_tax_fy__20230831 | B24: 23 | C24: Net interest after tax | D24: Apply the effective tax rate once to net interest. | E24: condensed.net_interest_after_tax.2023-08-31 | F24: accounting | G24: Condensed Financials | H24: D53 | I24: =IF(D52=0,0,IF(ISNA(D51),NA(),D52*(1-D51))) | J24: -44632.538 | K24: 0.01 | L24: effective_tax_rate_fy__20230831,net_interest_fy__20230831 | M24: After-tax net interest = Net Interest × (1 − Effective Tax Rate).|Do not tax-adjust a rate that is already after tax.|A zero Net Interest amount remains zero even if ETR is undefined; otherwise undefined ETR propagates. | O24: pending | P24: net_interest_after_tax_fy | Q24: 5 | R24: 2 | S24: 2023-08-31
A25: net_interest_after_tax_fy__20240831 | B25: 24 | C25: Net interest after tax | D25: Apply the effective tax rate once to net interest. | E25: condensed.net_interest_after_tax.2024-08-31 | F25: accounting | G25: Condensed Financials | H25: E53 | I25: =IF(E52=0,0,IF(ISNA(E51),NA(),E52*(1-E51))) | J25: -44365.251 | K25: 0.01 | L25: effective_tax_rate_fy__20240831,net_interest_fy__20240831 | M25: After-tax net interest = Net Interest × (1 − Effective Tax Rate).|Do not tax-adjust a rate that is already after tax.|A zero Net Interest amount remains zero even if ETR is undefined; otherwise undefined ETR propagates. | O25: pending | P25: net_interest_after_tax_fy | Q25: 5 | R25: 3 | S25: 2024-08-31
A26: net_interest_after_tax_fy__20250831 | B26: 25 | C26: Net interest after tax | D26: Apply the effective tax rate once to net interest. | E26: condensed.net_interest_after_tax.2025-08-31 | F26: accounting | G26: Condensed Financials | H26: F53 | I26: =IF(F52=0,0,IF(ISNA(F51),NA(),F52*(1-F51))) | J26: -66887.56 | K26: 0.01 | L26: effective_tax_rate_fy__20250831,net_interest_fy__20250831 | M26: After-tax net interest = Net Interest × (1 − Effective Tax Rate).|Do not tax-adjust a rate that is already after tax.|A zero Net Interest amount remains zero even if ETR is undefined; otherwise undefined ETR propagates. | O26: pending | P26: net_interest_after_tax_fy | Q26: 5 | R26: 4 | S26: 2025-08-31
A27: nopat_fy__20210831 | B27: 26 | C27: NOPAT | D27: Reformulate net income to operating profit after tax. | E27: condensed.nopat.2021-08-31 | F27: accounting | G27: Condensed Financials | H27: B54 | I27: =B45+B53 | J27: 161339.7 | K27: 0.01 | L27: net_income_link__20210831,net_interest_after_tax_fy__20210831 | M27: Start from Net Income on the Income Statement.|Add back after-tax net interest: Net Interest × (1 − Tax Rate).|NOPAT = Net Income + Net Interest After Tax.|Undefined tax-effected Net Interest propagates to NOPAT. | O27: pending | P27: nopat_fy | Q27: 6 | R27: 0 | S27: 2021-08-31
A28: nopat_fy__20220831 | B28: 27 | C28: NOPAT | D28: Reformulate net income to operating profit after tax. | E28: condensed.nopat.2022-08-31 | F28: accounting | G28: Condensed Financials | H28: C54 | I28: =C45+C53 | J28: 201430.55 | K28: 0.01 | L28: net_income_link__20220831,net_interest_after_tax_fy__20220831 | M28: Start from Net Income on the Income Statement.|Add back after-tax net interest: Net Interest × (1 − Tax Rate).|NOPAT = Net Income + Net Interest After Tax.|Undefined tax-effected Net Interest propagates to NOPAT. | O28: pending | P28: nopat_fy | Q28: 6 | R28: 1 | S28: 2022-08-31
A29: nopat_fy__20230831 | B29: 28 | C29: NOPAT | D29: Reformulate net income to operating profit after tax. | E29: condensed.nopat.2023-08-31 | F29: accounting | G29: Condensed Financials | H29: D54 | I29: =D45+D53 | J29: 270538.46 | K29: 0.01 | L29: net_income_link__20230831,net_interest_after_tax_fy__20230831 | M29: Start from Net Income on the Income Statement.|Add back after-tax net interest: Net Interest × (1 − Tax Rate).|NOPAT = Net Income + Net Interest After Tax.|Undefined tax-effected Net Interest propagates to NOPAT. | O29: pending | P29: nopat_fy | Q29: 6 | R29: 2 | S29: 2023-08-31
A30: nopat_fy__20240831 | B30: 29 | C30: NOPAT | D30: Reformulate net income to operating profit after tax. | E30: condensed.nopat.2024-08-31 | F30: accounting | G30: Condensed Financials | H30: E54 | I30: =E45+E53 | J30: 349239.75 | K30: 0.01 | L30: net_income_link__20240831,net_interest_after_tax_fy__20240831 | M30: Start from Net Income on the Income Statement.|Add back after-tax net interest: Net Interest × (1 − Tax Rate).|NOPAT = Net Income + Net Interest After Tax.|Undefined tax-effected Net Interest propagates to NOPAT. | O30: pending | P30: nopat_fy | Q30: 6 | R30: 3 | S30: 2024-08-31
A31: nopat_fy__20250831 | B31: 30 | C31: NOPAT | D31: Reformulate net income to operating profit after tax. | E31: condensed.nopat.2025-08-31 | F31: accounting | G31: Condensed Financials | H31: F54 | I31: =F45+F53 | J31: 392265.44 | K31: 0.01 | L31: net_income_link__20250831,net_interest_after_tax_fy__20250831 | M31: Start from Net Income on the Income Statement.|Add back after-tax net interest: Net Interest × (1 − Tax Rate).|NOPAT = Net Income + Net Interest After Tax.|Undefined tax-effected Net Interest propagates to NOPAT. | O31: pending | P31: nopat_fy | Q31: 6 | R31: 4 | S31: 2025-08-31
A32: owca_agg__20210831 | B32: 31 | C32: Operating working capital assets | D32: Aggregate the classified balance-sheet detail with the classification column. | E32: condensed.owca.2021-08-31 | F32: accounting | G32: Condensed Financials | H32: B57 | I32: =SUMIF($B$6:$B$41,"Operating Working Capital Asset",C$6:C$41) | J32: 463676 | K32: 0.01 | M32: Use SUMIF over the classification column for Operating Working Capital Asset. | O32: pending | P32: owca_agg | Q32: 7 | R32: 0 | S32: 2021-08-31
A33: owca_agg__20220831 | B33: 32 | C33: Operating working capital assets | D33: Aggregate the classified balance-sheet detail with the classification column. | E33: condensed.owca.2022-08-31 | F33: accounting | G33: Condensed Financials | H33: C57 | I33: =SUMIF($B$6:$B$41,"Operating Working Capital Asset",D$6:D$41) | J33: 572559 | K33: 0.01 | M33: Use SUMIF over the classification column for Operating Working Capital Asset. | O33: pending | P33: owca_agg | Q33: 7 | R33: 1 | S33: 2022-08-31
A34: owca_agg__20230831 | B34: 33 | C34: Operating working capital assets | D34: Aggregate the classified balance-sheet detail with the classification column. | E34: condensed.owca.2023-08-31 | F34: accounting | G34: Condensed Financials | H34: D57 | I34: =SUMIF($B$6:$B$41,"Operating Working Capital Asset",E$6:E$41) | J34: 565117 | K34: 0.01 | M34: Use SUMIF over the classification column for Operating Working Capital Asset. | O34: pending | P34: owca_agg | Q34: 7 | R34: 2 | S34: 2023-08-31
A35: owca_agg__20240831 | B35: 34 | C35: Operating working capital assets | D35: Aggregate the classified balance-sheet detail with the classification column. | E35: condensed.owca.2024-08-31 | F35: accounting | G35: Condensed Financials | H35: E57 | I35: =SUMIF($B$6:$B$41,"Operating Working Capital Asset",F$6:F$41) | J35: 587496 | K35: 0.01 | M35: Use SUMIF over the classification column for Operating Working Capital Asset. | O35: pending | P35: owca_agg | Q35: 7 | R35: 3 | S35: 2024-08-31
A36: owca_agg__20250831 | B36: 35 | C36: Operating working capital assets | D36: Aggregate the classified balance-sheet detail with the classification column. | E36: condensed.owca.2025-08-31 | F36: accounting | G36: Condensed Financials | H36: F57 | I36: =SUMIF($B$6:$B$41,"Operating Working Capital Asset",G$6:G$41) | J36: 640069 | K36: 0.01 | M36: Use SUMIF over the classification column for Operating Working Capital Asset. | O36: pending | P36: owca_agg | Q36: 7 | R36: 4 | S36: 2025-08-31
A37: owcl_agg__20210831 | B37: 36 | C37: Operating working capital liabilities | D37: Aggregate the classified balance-sheet detail with the classification column. | E37: condensed.owcl.2021-08-31 | F37: accounting | G37: Condensed Financials | H37: B58 | I37: =SUMIF($B$6:$B$41,"Operating Working Capital Liability",C$6:C$41) | J37: 356464 | K37: 0.01 | M37: Use SUMIF over the classification column for Operating Working Capital Liability. | O37: pending | P37: owcl_agg | Q37: 8 | R37: 0 | S37: 2021-08-31
A38: owcl_agg__20220831 | B38: 37 | C38: Operating working capital liabilities | D38: Aggregate the classified balance-sheet detail with the classification column. | E38: condensed.owcl.2022-08-31 | F38: accounting | G38: Condensed Financials | H38: C58 | I38: =SUMIF($B$6:$B$41,"Operating Working Capital Liability",D$6:D$41) | J38: 541556 | K38: 0.01 | M38: Use SUMIF over the classification column for Operating Working Capital Liability. | O38: pending | P38: owcl_agg | Q38: 8 | R38: 1 | S38: 2022-08-31
A39: owcl_agg__20230831 | B39: 38 | C39: Operating working capital liabilities | D39: Aggregate the classified balance-sheet detail with the classification column. | E39: condensed.owcl.2023-08-31 | F39: accounting | G39: Condensed Financials | H39: D58 | I39: =SUMIF($B$6:$B$41,"Operating Working Capital Liability",E$6:E$41) | J39: 536753 | K39: 0.01 | M39: Use SUMIF over the classification column for Operating Working Capital Liability. | O39: pending | P39: owcl_agg | Q39: 8 | R39: 2 | S39: 2023-08-31
A40: owcl_agg__20240831 | B40: 39 | C40: Operating working capital liabilities | D40: Aggregate the classified balance-sheet detail with the classification column. | E40: condensed.owcl.2024-08-31 | F40: accounting | G40: Condensed Financials | H40: E58 | I40: =SUMIF($B$6:$B$41,"Operating Working Capital Liability",F$6:F$41) | J40: 604156 | K40: 0.01 | M40: Use SUMIF over the classification column for Operating Working Capital Liability. | O40: pending | P40: owcl_agg | Q40: 8 | R40: 3 | S40: 2024-08-31
A41: owcl_agg__20250831 | B41: 40 | C41: Operating working capital liabilities | D41: Aggregate the classified balance-sheet detail with the classification column. | E41: condensed.owcl.2025-08-31 | F41: accounting | G41: Condensed Financials | H41: F58 | I41: =SUMIF($B$6:$B$41,"Operating Working Capital Liability",G$6:G$41) | J41: 614266 | K41: 0.01 | M41: Use SUMIF over the classification column for Operating Working Capital Liability. | O41: pending | P41: owcl_agg | Q41: 8 | R41: 4 | S41: 2025-08-31
A42: nowc_agg__20210831 | B42: 41 | C42: Net Operating Working Capital (NOWC) | D42: Sum operating WC assets minus operating WC liabilities. | E42: condensed.nowc.2021-08-31 | F42: accounting | G42: Condensed Financials | H42: B59 | I42: =B57-B58 | J42: 107212 | K42: 0.01 | L42: owca_agg__20210831,owcl_agg__20210831 | M42: Use SUMIF over the classification column for 'Operating Working Capital Asset'.|Subtract SUMIF for 'Operating Working Capital Liability'.|NOWC = Op. WC Assets − Op. WC Liabilities. | O42: pending | P42: nowc_agg | Q42: 9 | R42: 0 | S42: 2021-08-31
A43: nowc_agg__20220831 | B43: 42 | C43: Net Operating Working Capital (NOWC) | D43: Sum operating WC assets minus operating WC liabilities. | E43: condensed.nowc.2022-08-31 | F43: accounting | G43: Condensed Financials | H43: C59 | I43: =C57-C58 | J43: 31003 | K43: 0.01 | L43: owca_agg__20220831,owcl_agg__20220831 | M43: Use SUMIF over the classification column for 'Operating Working Capital Asset'.|Subtract SUMIF for 'Operating Working Capital Liability'.|NOWC = Op. WC Assets − Op. WC Liabilities. | O43: pending | P43: nowc_agg | Q43: 9 | R43: 1 | S43: 2022-08-31
A44: nowc_agg__20230831 | B44: 43 | C44: Net Operating Working Capital (NOWC) | D44: Sum operating WC assets minus operating WC liabilities. | E44: condensed.nowc.2023-08-31 | F44: accounting | G44: Condensed Financials | H44: D59 | I44: =D57-D58 | J44: 28364 | K44: 0.01 | L44: owca_agg__20230831,owcl_agg__20230831 | M44: Use SUMIF over the classification column for 'Operating Working Capital Asset'.|Subtract SUMIF for 'Operating Working Capital Liability'.|NOWC = Op. WC Assets − Op. WC Liabilities. | O44: pending | P44: nowc_agg | Q44: 9 | R44: 2 | S44: 2023-08-31
A45: nowc_agg__20240831 | B45: 44 | C45: Net Operating Working Capital (NOWC) | D45: Sum operating WC assets minus operating WC liabilities. | E45: condensed.nowc.2024-08-31 | F45: accounting | G45: Condensed Financials | H45: E59 | I45: =E57-E58 | J45: -16660 | K45: 0.01 | L45: owca_agg__20240831,owcl_agg__20240831 | M45: Use SUMIF over the classification column for 'Operating Working Capital Asset'.|Subtract SUMIF for 'Operating Working Capital Liability'.|NOWC = Op. WC Assets − Op. WC Liabilities. | O45: pending | P45: nowc_agg | Q45: 9 | R45: 3 | S45: 2024-08-31
A46: nowc_agg__20250831 | B46: 45 | C46: Net Operating Working Capital (NOWC) | D46: Sum operating WC assets minus operating WC liabilities. | E46: condensed.nowc.2025-08-31 | F46: accounting | G46: Condensed Financials | H46: F59 | I46: =F57-F58 | J46: 25803 | K46: 0.01 | L46: owca_agg__20250831,owcl_agg__20250831 | M46: Use SUMIF over the classification column for 'Operating Working Capital Asset'.|Subtract SUMIF for 'Operating Working Capital Liability'.|NOWC = Op. WC Assets − Op. WC Liabilities. | O46: pending | P46: nowc_agg | Q46: 9 | R46: 4 | S46: 2025-08-31
A47: olta_agg__20210831 | B47: 46 | C47: Operating long-term assets | D47: Aggregate the classified balance-sheet detail with the classification column. | E47: condensed.olta.2021-08-31 | F47: accounting | G47: Condensed Financials | H47: B60 | I47: =SUMIF($B$6:$B$41,"Operating Long-Term Asset",C$6:C$41) | J47: 695626 | K47: 0.01 | M47: Use SUMIF over the classification column for Operating Long-Term Asset. | O47: pending | P47: olta_agg | Q47: 10 | R47: 0 | S47: 2021-08-31
A48: olta_agg__20220831 | B48: 47 | C48: Operating long-term assets | D48: Aggregate the classified balance-sheet detail with the classification column. | E48: condensed.olta.2022-08-31 | F48: accounting | G48: Condensed Financials | H48: C60 | I48: =SUMIF($B$6:$B$41,"Operating Long-Term Asset",D$6:D$41) | J48: 706326 | K48: 0.01 | M48: Use SUMIF over the classification column for Operating Long-Term Asset. | O48: pending | P48: olta_agg | Q48: 10 | R48: 1 | S48: 2022-08-31
A49: olta_agg__20230831 | B49: 48 | C49: Operating long-term assets | D49: Aggregate the classified balance-sheet detail with the classification column. | E49: condensed.olta.2023-08-31 | F49: accounting | G49: Condensed Financials | H49: D60 | I49: =SUMIF($B$6:$B$41,"Operating Long-Term Asset",E$6:E$41) | J49: 772480 | K49: 0.01 | M49: Use SUMIF over the classification column for Operating Long-Term Asset. | O49: pending | P49: olta_agg | Q49: 10 | R49: 2 | S49: 2023-08-31
A50: olta_agg__20240831 | B50: 49 | C50: Operating long-term assets | D50: Aggregate the classified balance-sheet detail with the classification column. | E50: condensed.olta.2024-08-31 | F50: accounting | G50: Condensed Financials | H50: E60 | I50: =SUMIF($B$6:$B$41,"Operating Long-Term Asset",F$6:F$41) | J50: 820993 | K50: 0.01 | M50: Use SUMIF over the classification column for Operating Long-Term Asset. | O50: pending | P50: olta_agg | Q50: 10 | R50: 3 | S50: 2024-08-31
A51: olta_agg__20250831 | B51: 50 | C51: Operating long-term assets | D51: Aggregate the classified balance-sheet detail with the classification column. | E51: condensed.olta.2025-08-31 | F51: accounting | G51: Condensed Financials | H51: F60 | I51: =SUMIF($B$6:$B$41,"Operating Long-Term Asset",G$6:G$41) | J51: 985213 | K51: 0.01 | M51: Use SUMIF over the classification column for Operating Long-Term Asset. | O51: pending | P51: olta_agg | Q51: 10 | R51: 4 | S51: 2025-08-31
A52: oltl_agg__20210831 | B52: 51 | C52: Operating long-term liabilities | D52: Aggregate the classified balance-sheet detail with the classification column. | E52: condensed.oltl.2021-08-31 | F52: accounting | G52: Condensed Financials | H52: B61 | I52: =SUMIF($B$6:$B$41,"Operating Long-Term Liability",C$6:C$41) | J52: 511905 | K52: 0.01 | M52: Use SUMIF over the classification column for Operating Long-Term Liability. | O52: pending | P52: oltl_agg | Q52: 11 | R52: 0 | S52: 2021-08-31
A53: oltl_agg__20220831 | B53: 52 | C53: Operating long-term liabilities | D53: Aggregate the classified balance-sheet detail with the classification column. | E53: condensed.oltl.2022-08-31 | F53: accounting | G53: Condensed Financials | H53: C61 | I53: =SUMIF($B$6:$B$41,"Operating Long-Term Liability",D$6:D$41) | J53: 574934 | K53: 0.01 | M53: Use SUMIF over the classification column for Operating Long-Term Liability. | O53: pending | P53: oltl_agg | Q53: 11 | R53: 1 | S53: 2022-08-31
A54: oltl_agg__20230831 | B54: 53 | C54: Operating long-term liabilities | D54: Aggregate the classified balance-sheet detail with the classification column. | E54: condensed.oltl.2023-08-31 | F54: accounting | G54: Condensed Financials | H54: D61 | I54: =SUMIF($B$6:$B$41,"Operating Long-Term Liability",E$6:E$41) | J54: 585583 | K54: 0.01 | M54: Use SUMIF over the classification column for Operating Long-Term Liability. | O54: pending | P54: oltl_agg | Q54: 11 | R54: 2 | S54: 2023-08-31
A55: oltl_agg__20240831 | B55: 54 | C55: Operating long-term liabilities | D55: Aggregate the classified balance-sheet detail with the classification column. | E55: condensed.oltl.2024-08-31 | F55: accounting | G55: Condensed Financials | H55: E61 | I55: =SUMIF($B$6:$B$41,"Operating Long-Term Liability",F$6:F$41) | J55: 565131 | K55: 0.01 | M55: Use SUMIF over the classification column for Operating Long-Term Liability. | O55: pending | P55: oltl_agg | Q55: 11 | R55: 3 | S55: 2024-08-31
A56: oltl_agg__20250831 | B56: 55 | C56: Operating long-term liabilities | D56: Aggregate the classified balance-sheet detail with the classification column. | E56: condensed.oltl.2025-08-31 | F56: accounting | G56: Condensed Financials | H56: F61 | I56: =SUMIF($B$6:$B$41,"Operating Long-Term Liability",G$6:G$41) | J56: 594207 | K56: 0.01 | M56: Use SUMIF over the classification column for Operating Long-Term Liability. | O56: pending | P56: oltl_agg | Q56: 11 | R56: 4 | S56: 2025-08-31
A57: nola_agg__20210831 | B57: 56 | C57: Net operating long-term assets (NOLA) | D57: Operating long-term assets less operating long-term liabilities. | E57: condensed.nola.2021-08-31 | F57: accounting | G57: Condensed Financials | H57: B62 | I57: =B60-B61 | J57: 183721 | K57: 0.01 | L57: olta_agg__20210831,oltl_agg__20210831 | M57: NOLA = Operating LT Assets − Operating LT Liabilities. | O57: pending | P57: nola_agg | Q57: 12 | R57: 0 | S57: 2021-08-31
A58: nola_agg__20220831 | B58: 57 | C58: Net operating long-term assets (NOLA) | D58: Operating long-term assets less operating long-term liabilities. | E58: condensed.nola.2022-08-31 | F58: accounting | G58: Condensed Financials | H58: C62 | I58: =C60-C61 | J58: 131392 | K58: 0.01 | L58: olta_agg__20220831,oltl_agg__20220831 | M58: NOLA = Operating LT Assets − Operating LT Liabilities. | O58: pending | P58: nola_agg | Q58: 12 | R58: 1 | S58: 2022-08-31
A59: nola_agg__20230831 | B59: 58 | C59: Net operating long-term assets (NOLA) | D59: Operating long-term assets less operating long-term liabilities. | E59: condensed.nola.2023-08-31 | F59: accounting | G59: Condensed Financials | H59: D62 | I59: =D60-D61 | J59: 186897 | K59: 0.01 | L59: olta_agg__20230831,oltl_agg__20230831 | M59: NOLA = Operating LT Assets − Operating LT Liabilities. | O59: pending | P59: nola_agg | Q59: 12 | R59: 2 | S59: 2023-08-31
A60: nola_agg__20240831 | B60: 59 | C60: Net operating long-term assets (NOLA) | D60: Operating long-term assets less operating long-term liabilities. | E60: condensed.nola.2024-08-31 | F60: accounting | G60: Condensed Financials | H60: E62 | I60: =E60-E61 | J60: 255862 | K60: 0.01 | L60: olta_agg__20240831,oltl_agg__20240831 | M60: NOLA = Operating LT Assets − Operating LT Liabilities. | O60: pending | P60: nola_agg | Q60: 12 | R60: 3 | S60: 2024-08-31
A61: nola_agg__20250831 | B61: 60 | C61: Net operating long-term assets (NOLA) | D61: Operating long-term assets less operating long-term liabilities. | E61: condensed.nola.2025-08-31 | F61: accounting | G61: Condensed Financials | H61: F62 | I61: =F60-F61 | J61: 391006 | K61: 0.01 | L61: olta_agg__20250831,oltl_agg__20250831 | M61: NOLA = Operating LT Assets − Operating LT Liabilities. | O61: pending | P61: nola_agg | Q61: 12 | R61: 4 | S61: 2025-08-31
A62: noa_agg__20210831 | B62: 61 | C62: Net Operating Assets (NOA) | D62: NOWC plus net operating long-term assets. | E62: condensed.noa.2021-08-31 | F62: accounting | G62: Condensed Financials | H62: B63 | I62: =B59+B62 | J62: 290933 | K62: 0.01 | L62: nowc_agg__20210831,nola_agg__20210831 | M62: Net Operating LT Assets = Op. LT Assets − Op. LT Liabilities (SUMIF).|NOA = NOWC + Net Operating LT Assets. | O62: pending | P62: noa_agg | Q62: 13 | R62: 0 | S62: 2021-08-31
A63: noa_agg__20220831 | B63: 62 | C63: Net Operating Assets (NOA) | D63: NOWC plus net operating long-term assets. | E63: condensed.noa.2022-08-31 | F63: accounting | G63: Condensed Financials | H63: C63 | I63: =C59+C62 | J63: 162395 | K63: 0.01 | L63: nowc_agg__20220831,nola_agg__20220831 | M63: Net Operating LT Assets = Op. LT Assets − Op. LT Liabilities (SUMIF).|NOA = NOWC + Net Operating LT Assets. | O63: pending | P63: noa_agg | Q63: 13 | R63: 1 | S63: 2022-08-31
A64: noa_agg__20230831 | B64: 63 | C64: Net Operating Assets (NOA) | D64: NOWC plus net operating long-term assets. | E64: condensed.noa.2023-08-31 | F64: accounting | G64: Condensed Financials | H64: D63 | I64: =D59+D62 | J64: 215261 | K64: 0.01 | L64: nowc_agg__20230831,nola_agg__20230831 | M64: Net Operating LT Assets = Op. LT Assets − Op. LT Liabilities (SUMIF).|NOA = NOWC + Net Operating LT Assets. | O64: pending | P64: noa_agg | Q64: 13 | R64: 2 | S64: 2023-08-31
A65: noa_agg__20240831 | B65: 64 | C65: Net Operating Assets (NOA) | D65: NOWC plus net operating long-term assets. | E65: condensed.noa.2024-08-31 | F65: accounting | G65: Condensed Financials | H65: E63 | I65: =E59+E62 | J65: 239202 | K65: 0.01 | L65: nowc_agg__20240831,nola_agg__20240831 | M65: Net Operating LT Assets = Op. LT Assets − Op. LT Liabilities (SUMIF).|NOA = NOWC + Net Operating LT Assets. | O65: pending | P65: noa_agg | Q65: 13 | R65: 3 | S65: 2024-08-31
A66: noa_agg__20250831 | B66: 65 | C66: Net Operating Assets (NOA) | D66: NOWC plus net operating long-term assets. | E66: condensed.noa.2025-08-31 | F66: accounting | G66: Condensed Financials | H66: F63 | I66: =F59+F62 | J66: 416809 | K66: 0.01 | L66: nowc_agg__20250831,nola_agg__20250831 | M66: Net Operating LT Assets = Op. LT Assets − Op. LT Liabilities (SUMIF).|NOA = NOWC + Net Operating LT Assets. | O66: pending | P66: noa_agg | Q66: 13 | R66: 4 | S66: 2025-08-31
A67: financial_assets_agg__20210831 | B67: 66 | C67: Financial assets | D67: Aggregate the classified balance-sheet detail with the classification column. | E67: condensed.financial_assets.2021-08-31 | F67: accounting | G67: Condensed Financials | H67: B64 | I67: =SUMIF($B$6:$B$41,"Financial Asset",C$6:C$41) | J67: 1350670 | K67: 0.01 | M67: Use SUMIF over the classification column for Financial Asset. | O67: pending | P67: financial_assets_agg | Q67: 14 | R67: 0 | S67: 2021-08-31
A68: financial_assets_agg__20220831 | B68: 67 | C68: Financial assets | D68: Aggregate the classified balance-sheet detail with the classification column. | E68: condensed.financial_assets.2022-08-31 | F68: accounting | G68: Condensed Financials | H68: C64 | I68: =SUMIF($B$6:$B$41,"Financial Asset",D$6:D$41) | J68: 1904869 | K68: 0.01 | M68: Use SUMIF over the classification column for Financial Asset. | O68: pending | P68: financial_assets_agg | Q68: 14 | R68: 1 | S68: 2022-08-31
A69: financial_assets_agg__20230831 | B69: 68 | C69: Financial assets | D69: Aggregate the classified balance-sheet detail with the classification column. | E69: condensed.financial_assets.2023-08-31 | F69: accounting | G69: Condensed Financials | H69: D64 | I69: =SUMIF($B$6:$B$41,"Financial Asset",E$6:E$41) | J69: 1966089 | K69: 0.01 | M69: Use SUMIF over the classification column for Financial Asset. | O69: pending | P69: financial_assets_agg | Q69: 14 | R69: 2 | S69: 2023-08-31
A70: financial_assets_agg__20240831 | B70: 69 | C70: Financial assets | D70: Aggregate the classified balance-sheet detail with the classification column. | E70: condensed.financial_assets.2024-08-31 | F70: accounting | G70: Condensed Financials | H70: E64 | I70: =SUMIF($B$6:$B$41,"Financial Asset",F$6:F$41) | J70: 2179069 | K70: 0.01 | M70: Use SUMIF over the classification column for Financial Asset. | O70: pending | P70: financial_assets_agg | Q70: 14 | R70: 3 | S70: 2024-08-31
A71: financial_assets_agg__20250831 | B71: 70 | C71: Financial assets | D71: Aggregate the classified balance-sheet detail with the classification column. | E71: condensed.financial_assets.2025-08-31 | F71: accounting | G71: Condensed Financials | H71: F64 | I71: =SUMIF($B$6:$B$41,"Financial Asset",G$6:G$41) | J71: 2234063 | K71: 0.01 | M71: Use SUMIF over the classification column for Financial Asset. | O71: pending | P71: financial_assets_agg | Q71: 14 | R71: 4 | S71: 2025-08-31
A72: financial_liabilities_agg__20210831 | B72: 71 | C72: Financial liabilities | D72: Aggregate the classified balance-sheet detail with the classification column. | E72: condensed.financial_liabilities.2021-08-31 | F72: accounting | G72: Condensed Financials | H72: B65 | I72: =SUMIF($B$6:$B$41,"Financial Liability",C$6:C$41) | J72: 479303 | K72: 0.01 | M72: Use SUMIF over the classification column for Financial Liability. | O72: pending | P72: financial_liabilities_agg | Q72: 15 | R72: 0 | S72: 2021-08-31
A73: financial_liabilities_agg__20220831 | B73: 72 | C73: Financial liabilities | D73: Aggregate the classified balance-sheet detail with the classification column. | E73: condensed.financial_liabilities.2022-08-31 | F73: accounting | G73: Condensed Financials | H73: C65 | I73: =SUMIF($B$6:$B$41,"Financial Liability",D$6:D$41) | J73: 451865 | K73: 0.01 | M73: Use SUMIF over the classification column for Financial Liability. | O73: pending | P73: financial_liabilities_agg | Q73: 15 | R73: 1 | S73: 2022-08-31
A74: financial_liabilities_agg__20230831 | B74: 73 | C74: Financial liabilities | D74: Aggregate the classified balance-sheet detail with the classification column. | E74: condensed.financial_liabilities.2023-08-31 | F74: accounting | G74: Condensed Financials | H74: D65 | I74: =SUMIF($B$6:$B$41,"Financial Liability",E$6:E$41) | J74: 307991 | K74: 0.01 | M74: Use SUMIF over the classification column for Financial Liability. | O74: pending | P74: financial_liabilities_agg | Q74: 15 | R74: 2 | S74: 2023-08-31
A75: financial_liabilities_agg__20240831 | B75: 74 | C75: Financial liabilities | D75: Aggregate the classified balance-sheet detail with the classification column. | E75: condensed.financial_liabilities.2024-08-31 | F75: accounting | G75: Condensed Financials | H75: E65 | I75: =SUMIF($B$6:$B$41,"Financial Liability",F$6:F$41) | J75: 350018 | K75: 0.01 | M75: Use SUMIF over the classification column for Financial Liability. | O75: pending | P75: financial_liabilities_agg | Q75: 15 | R75: 3 | S75: 2024-08-31
A76: financial_liabilities_agg__20250831 | B76: 75 | C76: Financial liabilities | D76: Aggregate the classified balance-sheet detail with the classification column. | E76: condensed.financial_liabilities.2025-08-31 | F76: accounting | G76: Condensed Financials | H76: F65 | I76: =SUMIF($B$6:$B$41,"Financial Liability",G$6:G$41) | J76: 323373 | K76: 0.01 | M76: Use SUMIF over the classification column for Financial Liability. | O76: pending | P76: financial_liabilities_agg | Q76: 15 | R76: 4 | S76: 2025-08-31
A77: net_debt__20210831 | B77: 76 | C77: Net Debt | D77: Financial liabilities minus financial assets. | E77: condensed.net_debt.2021-08-31 | F77: accounting | G77: Condensed Financials | H77: B66 | I77: =B65-B64 | J77: -871367 | K77: 0.01 | L77: financial_assets_agg__20210831,financial_liabilities_agg__20210831 | M77: Net Debt = SUMIF(Financial Liability) − SUMIF(Financial Asset).|Positive net debt means the firm carries net financial obligations. | O77: pending | P77: net_debt | Q77: 16 | R77: 0 | S77: 2021-08-31
A78: net_debt__20220831 | B78: 77 | C78: Net Debt | D78: Financial liabilities minus financial assets. | E78: condensed.net_debt.2022-08-31 | F78: accounting | G78: Condensed Financials | H78: C66 | I78: =C65-C64 | J78: -1453004 | K78: 0.01 | L78: financial_assets_agg__20220831,financial_liabilities_agg__20220831 | M78: Net Debt = SUMIF(Financial Liability) − SUMIF(Financial Asset).|Positive net debt means the firm carries net financial obligations. | O78: pending | P78: net_debt | Q78: 16 | R78: 1 | S78: 2022-08-31
A79: net_debt__20230831 | B79: 78 | C79: Net Debt | D79: Financial liabilities minus financial assets. | E79: condensed.net_debt.2023-08-31 | F79: accounting | G79: Condensed Financials | H79: D66 | I79: =D65-D64 | J79: -1658098 | K79: 0.01 | L79: financial_assets_agg__20230831,financial_liabilities_agg__20230831 | M79: Net Debt = SUMIF(Financial Liability) − SUMIF(Financial Asset).|Positive net debt means the firm carries net financial obligations. | O79: pending | P79: net_debt | Q79: 16 | R79: 2 | S79: 2023-08-31
A80: net_debt__20240831 | B80: 79 | C80: Net Debt | D80: Financial liabilities minus financial assets. | E80: condensed.net_debt.2024-08-31 | F80: accounting | G80: Condensed Financials | H80: E66 | I80: =E65-E64 | J80: -1829051 | K80: 0.01 | L80: financial_assets_agg__20240831,financial_liabilities_agg__20240831 | M80: Net Debt = SUMIF(Financial Liability) − SUMIF(Financial Asset).|Positive net debt means the firm carries net financial obligations. | O80: pending | P80: net_debt | Q80: 16 | R80: 3 | S80: 2024-08-31
A81: net_debt__20250831 | B81: 80 | C81: Net Debt | D81: Financial liabilities minus financial assets. | E81: condensed.net_debt.2025-08-31 | F81: accounting | G81: Condensed Financials | H81: F66 | I81: =F65-F64 | J81: -1910690 | K81: 0.01 | L81: financial_assets_agg__20250831,financial_liabilities_agg__20250831 | M81: Net Debt = SUMIF(Financial Liability) − SUMIF(Financial Asset).|Positive net debt means the firm carries net financial obligations. | O81: pending | P81: net_debt | Q81: 16 | R81: 4 | S81: 2025-08-31
A82: equity_reformulated_fy__20210831 | B82: 81 | C82: Reformulated equity | D82: Use the operating/financing identity linking NOA, Net Debt, and Equity. | E82: condensed.equity.2021-08-31 | F82: accounting | G82: Condensed Financials | H82: B67 | I82: =B63-B66 | J82: 1162300 | K82: 0.01 | L82: noa_agg__20210831,net_debt__20210831 | M82: Reformulated Equity = NOA − Net Debt.|This identity must reconcile to reported equity within tolerance. | O82: pending | P82: equity_reformulated_fy | Q82: 17 | R82: 0 | S82: 2021-08-31
A83: equity_reformulated_fy__20220831 | B83: 82 | C83: Reformulated equity | D83: Use the operating/financing identity linking NOA, Net Debt, and Equity. | E83: condensed.equity.2022-08-31 | F83: accounting | G83: Condensed Financials | H83: C67 | I83: =C63-C66 | J83: 1615399 | K83: 0.01 | L83: noa_agg__20220831,net_debt__20220831 | M83: Reformulated Equity = NOA − Net Debt.|This identity must reconcile to reported equity within tolerance. | O83: pending | P83: equity_reformulated_fy | Q83: 17 | R83: 1 | S83: 2022-08-31
A84: equity_reformulated_fy__20230831 | B84: 83 | C84: Reformulated equity | D84: Use the operating/financing identity linking NOA, Net Debt, and Equity. | E84: condensed.equity.2023-08-31 | F84: accounting | G84: Condensed Financials | H84: D67 | I84: =D63-D66 | J84: 1873359 | K84: 0.01 | L84: noa_agg__20230831,net_debt__20230831 | M84: Reformulated Equity = NOA − Net Debt.|This identity must reconcile to reported equity within tolerance. | O84: pending | P84: equity_reformulated_fy | Q84: 17 | R84: 2 | S84: 2023-08-31
A85: equity_reformulated_fy__20240831 | B85: 84 | C85: Reformulated equity | D85: Use the operating/financing identity linking NOA, Net Debt, and Equity. | E85: condensed.equity.2024-08-31 | F85: accounting | G85: Condensed Financials | H85: E67 | I85: =E63-E66 | J85: 2068253 | K85: 0.01 | L85: noa_agg__20240831,net_debt__20240831 | M85: Reformulated Equity = NOA − Net Debt.|This identity must reconcile to reported equity within tolerance. | O85: pending | P85: equity_reformulated_fy | Q85: 17 | R85: 3 | S85: 2024-08-31
A86: equity_reformulated_fy__20250831 | B86: 85 | C86: Reformulated equity | D86: Use the operating/financing identity linking NOA, Net Debt, and Equity. | E86: condensed.equity.2025-08-31 | F86: accounting | G86: Condensed Financials | H86: F67 | I86: =F63-F66 | J86: 2327499 | K86: 0.01 | L86: noa_agg__20250831,net_debt__20250831 | M86: Reformulated Equity = NOA − Net Debt.|This identity must reconcile to reported equity within tolerance. | O86: pending | P86: equity_reformulated_fy | Q86: 17 | R86: 4 | S86: 2025-08-31
A87: sales_growth__20220831 | B87: 86 | C87: Sales Growth | D87: Current Revenue relative to the immediately preceding fiscal year. | E87: dupont.sales_growth.2022-08-31 | F87: dupont | G87: ALT DuPont | H87: C5 | I87: =IF('Condensed Financials'!B44=0,NA(),'Condensed Financials'!C44/'Condensed Financials'!B44-1) | J87: 0.078823549 | K87: 0.01 | L87: revenue_link__20220831,revenue_link__20210831 | M87: Sales Growth = Current Revenue / Prior Revenue − 1.|A zero denominator makes this ratio undefined (#N/A), not 0%. | O87: pending | P87: sales_growth | Q87: 18 | R87: 1 | S87: 2022-08-31
A88: sales_growth__20230831 | B88: 87 | C88: Sales Growth | D88: Current Revenue relative to the immediately preceding fiscal year. | E88: dupont.sales_growth.2023-08-31 | F88: dupont | G88: ALT DuPont | H88: D5 | I88: =IF('Condensed Financials'!C44=0,NA(),'Condensed Financials'!D44/'Condensed Financials'!C44-1) | J88: 0.20226437 | K88: 0.01 | L88: revenue_link__20230831,revenue_link__20220831 | M88: Sales Growth = Current Revenue / Prior Revenue − 1.|A zero denominator makes this ratio undefined (#N/A), not 0%. | O88: pending | P88: sales_growth | Q88: 18 | R88: 2 | S88: 2023-08-31
A89: sales_growth__20240831 | B89: 88 | C89: Sales Growth | D89: Current Revenue relative to the immediately preceding fiscal year. | E89: dupont.sales_growth.2024-08-31 | F89: dupont | G89: ALT DuPont | H89: E5 | I89: =IF('Condensed Financials'!D44=0,NA(),'Condensed Financials'!E44/'Condensed Financials'!D44-1) | J89: 0.1219129 | K89: 0.01 | L89: revenue_link__20240831,revenue_link__20230831 | M89: Sales Growth = Current Revenue / Prior Revenue − 1.|A zero denominator makes this ratio undefined (#N/A), not 0%. | O89: pending | P89: sales_growth | Q89: 18 | R89: 3 | S89: 2024-08-31
A90: sales_growth__20250831 | B90: 89 | C90: Sales Growth | D90: Current Revenue relative to the immediately preceding fiscal year. | E90: dupont.sales_growth.2025-08-31 | F90: dupont | G90: ALT DuPont | H90: F5 | I90: =IF('Condensed Financials'!E44=0,NA(),'Condensed Financials'!F44/'Condensed Financials'!E44-1) | J90: 0.095592357 | K90: 0.01 | L90: revenue_link__20250831,revenue_link__20240831 | M90: Sales Growth = Current Revenue / Prior Revenue − 1.|A zero denominator makes this ratio undefined (#N/A), not 0%. | O90: pending | P90: sales_growth | Q90: 18 | R90: 4 | S90: 2025-08-31
A91: nopat_margin__20210831 | B91: 90 | C91: NOPAT Margin | D91: NOPAT divided by Revenue for the same fiscal period. | E91: dupont.nopat_margin.2021-08-31 | F91: dupont | G91: ALT DuPont | H91: B6 | I91: =IF('Condensed Financials'!B44=0,NA(),'Condensed Financials'!B54/'Condensed Financials'!B44) | J91: 0.075640086 | K91: 0.01 | L91: nopat_fy__20210831,revenue_link__20210831 | M91: NOPAT Margin = NOPAT / Revenue.|A zero denominator makes this ratio undefined (#N/A), not 0%. | O91: pending | P91: nopat_margin | Q91: 19 | R91: 0 | S91: 2021-08-31
A92: nopat_margin__20220831 | B92: 91 | C92: NOPAT Margin | D92: NOPAT divided by Revenue for the same fiscal period. | E92: dupont.nopat_margin.2022-08-31 | F92: dupont | G92: ALT DuPont | H92: C6 | I92: =IF('Condensed Financials'!C44=0,NA(),'Condensed Financials'!C54/'Condensed Financials'!C44) | J92: 0.087535798 | K92: 0.01 | L92: nopat_fy__20220831,revenue_link__20220831 | M92: NOPAT Margin = NOPAT / Revenue.|A zero denominator makes this ratio undefined (#N/A), not 0%. | O92: pending | P92: nopat_margin | Q92: 19 | R92: 1 | S92: 2022-08-31
A93: nopat_margin__20230831 | B93: 92 | C93: NOPAT Margin | D93: NOPAT divided by Revenue for the same fiscal period. | E93: dupont.nopat_margin.2023-08-31 | F93: dupont | G93: ALT DuPont | H93: D6 | I93: =IF('Condensed Financials'!D44=0,NA(),'Condensed Financials'!D54/'Condensed Financials'!D44) | J93: 0.097788863 | K93: 0.01 | L93: nopat_fy__20230831,revenue_link__20230831 | M93: NOPAT Margin = NOPAT / Revenue.|A zero denominator makes this ratio undefined (#N/A), not 0%. | O93: pending | P93: nopat_margin | Q93: 19 | R93: 2 | S93: 2023-08-31
A94: nopat_margin__20240831 | B94: 93 | C94: NOPAT Margin | D94: NOPAT divided by Revenue for the same fiscal period. | E94: dupont.nopat_margin.2024-08-31 | F94: dupont | G94: ALT DuPont | H94: E6 | I94: =IF('Condensed Financials'!E44=0,NA(),'Condensed Financials'!E54/'Condensed Financials'!E44) | J94: 0.11251875 | K94: 0.01 | L94: nopat_fy__20240831,revenue_link__20240831 | M94: NOPAT Margin = NOPAT / Revenue.|A zero denominator makes this ratio undefined (#N/A), not 0%. | O94: pending | P94: nopat_margin | Q94: 19 | R94: 3 | S94: 2024-08-31
A95: nopat_margin__20250831 | B95: 94 | C95: NOPAT Margin | D95: NOPAT divided by Revenue for the same fiscal period. | E95: dupont.nopat_margin.2025-08-31 | F95: dupont | G95: ALT DuPont | H95: F6 | I95: =IF('Condensed Financials'!F44=0,NA(),'Condensed Financials'!F54/'Condensed Financials'!F44) | J95: 0.1153539 | K95: 0.01 | L95: nopat_fy__20250831,revenue_link__20250831 | M95: NOPAT Margin = NOPAT / Revenue.|A zero denominator makes this ratio undefined (#N/A), not 0%. | O95: pending | P95: nopat_margin | Q95: 19 | R95: 4 | S95: 2025-08-31
A96: rnoa__20220831 | B96: 95 | C96: Return on Net Operating Assets (RNOA) | D96: NOPAT divided by average NOA. | E96: dupont.rnoa.2022-08-31 | F96: dupont | G96: ALT DuPont | H96: C7 | I96: =IF((('Condensed Financials'!C63+'Condensed Financials'!B63)/2)=0,NA(),'Condensed Financials'!C54/(('Condensed Financials'!C63+'Condensed Financials'!B63)/2)) | J96: 0.88867465 | K96: 0.01 | L96: nopat_fy__20220831,noa_agg__20220831,noa_agg__20210831 | M96: RNOA = NOPAT / Average NOA.|Average NOA = (Beginning NOA + Ending NOA) / 2.|A zero denominator makes this ratio undefined (#N/A), not 0%. | O96: pending | P96: rnoa | Q96: 20 | R96: 1 | S96: 2022-08-31
A97: rnoa__20230831 | B97: 96 | C97: Return on Net Operating Assets (RNOA) | D97: NOPAT divided by average NOA. | E97: dupont.rnoa.2023-08-31 | F97: dupont | G97: ALT DuPont | H97: D7 | I97: =IF((('Condensed Financials'!D63+'Condensed Financials'!C63)/2)=0,NA(),'Condensed Financials'!D54/(('Condensed Financials'!D63+'Condensed Financials'!C63)/2)) | J97: 1.4327243 | K97: 0.01 | L97: nopat_fy__20230831,noa_agg__20230831,noa_agg__20220831 | M97: RNOA = NOPAT / Average NOA.|Average NOA = (Beginning NOA + Ending NOA) / 2.|A zero denominator makes this ratio undefined (#N/A), not 0%. | O97: pending | P97: rnoa | Q97: 20 | R97: 2 | S97: 2023-08-31
A98: rnoa__20240831 | B98: 97 | C98: Return on Net Operating Assets (RNOA) | D98: NOPAT divided by average NOA. | E98: dupont.rnoa.2024-08-31 | F98: dupont | G98: ALT DuPont | H98: E7 | I98: =IF((('Condensed Financials'!E63+'Condensed Financials'!D63)/2)=0,NA(),'Condensed Financials'!E54/(('Condensed Financials'!E63+'Condensed Financials'!D63)/2)) | J98: 1.5369337 | K98: 0.01 | L98: nopat_fy__20240831,noa_agg__20240831,noa_agg__20230831 | M98: RNOA = NOPAT / Average NOA.|Average NOA = (Beginning NOA + Ending NOA) / 2.|A zero denominator makes this ratio undefined (#N/A), not 0%. | O98: pending | P98: rnoa | Q98: 20 | R98: 3 | S98: 2024-08-31
A99: rnoa__20250831 | B99: 98 | C99: Return on Net Operating Assets (RNOA) | D99: NOPAT divided by average NOA. | E99: dupont.rnoa.2025-08-31 | F99: dupont | G99: ALT DuPont | H99: F7 | I99: =IF((('Condensed Financials'!F63+'Condensed Financials'!E63)/2)=0,NA(),'Condensed Financials'!F54/(('Condensed Financials'!F63+'Condensed Financials'!E63)/2)) | J99: 1.1959112 | K99: 0.01 | L99: nopat_fy__20250831,noa_agg__20250831,noa_agg__20240831 | M99: RNOA = NOPAT / Average NOA.|Average NOA = (Beginning NOA + Ending NOA) / 2.|A zero denominator makes this ratio undefined (#N/A), not 0%. | O99: pending | P99: rnoa | Q99: 20 | R99: 4 | S99: 2025-08-31
A100: after_tax_cod__20220831 | B100: 99 | C100: After-tax cost of debt | D100: Relate net interest after tax to average net debt. | E100: dupont.after_tax_cod.2022-08-31 | F100: dupont | G100: ALT DuPont | H100: C8 | I100: =IF((('Condensed Financials'!C66+'Condensed Financials'!B66)/2)=0,NA(),'Condensed Financials'!C53/(('Condensed Financials'!C66+'Condensed Financials'!B66)/2)) | J100: 0.071692039 | K100: 0.01 | L100: net_interest_after_tax_fy__20220831,net_debt__20220831,net_debt__20210831 | M100: After-tax CoD = Net Interest After Tax / Average Net Debt.|Do not apply the tax rate a second time.|A zero denominator makes this ratio undefined (#N/A), not 0%. | O100: pending | P100: after_tax_cod | Q100: 21 | R100: 1 | S100: 2022-08-31
...

Sheet _CheckContext
A1: BAV_CHECK_CONTEXT_V1
A2: {"base_classification_overrides":{},"judgment_bindings":[{"allowed_treatments":["Financial Asset","Operating Working Capital Asset"],"case_id":"classification::concept=derivative_financial_assets_current|label=derivative financial assets","line_identity":"concept=derivative_financial_assets_current|label=derivative financial assets","order":1,"override_selector":"identity:concept=derivative_financial_assets_current|label=derivative financial assets","reference_treatment":"Financial Asset","worksheet_row":5},{"allowed_treatments":["Operating Working Capital Asset","Financial Asset"],"case_id":"classification::concept=other_current_assets|label=other assets","line_identity":"concept=other_current_assets|label=other assets","order":2,"override_selector":"identity:concept=other_current_assets|label=other assets","reference_treatment":"Operating Working Capital Asset","worksheet_row":6},{"allowed_treatments":["Financial Asset","Operating Working Capital Asset"],"case_id":"classification::concept=other_financial_assets_current|label=other financial assets","line_identity":"concept=other_financial_assets_current|label=other financial assets","order":3,"override_selector":"identity:concept=other_financial_assets_current|label=other financial assets","reference_treatment":"Financial Asset","worksheet_row":7},{"allowed_treatments":["Financial Liability","Operating Working Capital Liability"],"case_id":"classification::concept=derivative_financial_liabilities_current|label=derivative financial liabilities","line_identity":"concept=derivative_financial_liabilities_current|label=derivative financial liabilities","order":4,"override_selector":"identity:concept=derivative_financial_liabilities_current|label=derivative financial liabilities","reference_treatment":"Financial Liability","worksheet_row":8},{"allowed_treatments":["Operating Long-Term Liability","Financial Liability"],"case_id":"classification::concept=lease_liability_current|label=lease liabilities","line_identity":"concept=lease_liability_current|label=lease liabilities","order":5,"override_selector":"identity:concept=lease_liability_current|label=lease liabilities","reference_treatment":"Operating Long-Term Liability","worksheet_row":9},{"allowed_treatments":["Financial Liability","Operating Working Capital Liability"],"case_id":"classification::concept=other_financial_liabilities_current|label=other financial liabilities","line_identity":"concept=other_financial_liabilities_current|label=other financial liabilities","order":6,"override_selector":"identity:concept=other_financial_liabilities_current|label=other financial liabilities","reference_treatment":"Financial Liability","worksheet_row":10},{"allowed_treatments":["Operating Working Capital Liability","Financial Liability"],"case_id":"classification::concept=other_current_liabilities|label=other liabilities","line_identity":"concept=other_current_liabilities|label=other liabilities","order":7,"override_selector":"identity:concept=other_current_liabilities|label=other liabilities","reference_treatment":"Operating Working Capital Liability","worksheet_row":11},{"allowed_treatments":["Financial Asset","Operating Long-Term Asset"],"case_id":"classification::concept=derivative_financial_assets_noncurrent|label=derivative financial assets","line_identity":"concept=derivative_financial_assets_noncurrent|label=derivative financial assets","order":8,"override_selector":"identity:concept=derivative_financial_assets_noncurrent|label=derivative financial assets","reference_treatment":"Financial Asset","worksheet_row":12},{"allowed_treatments":["Financial Asset","Operating Long-Term Asset"],"case_id":"classification::concept=financial_assets_noncurrent|label=financial assets","line_identity":"concept=financial_assets_noncurrent|label=financial assets","order":9,"override_selector":"identity:concept=financial_assets_noncurrent|label=financial assets","reference_treatment":"Financial Asset","worksheet_row":13},{"allowed_treatments":["Operating Long-Term Asset","Financial Asset"],"case_id":"classification::concept=investments_in_associates|label=investments in associates accounted for using the equity method","line_identity":"concept=investments_in_associates|label=investments in associates accounted for using the equity method","order":10,"override_selector":"identity:concept=investments_in_associates|label=investments in associates accounted for using the equity method","reference_treatment":"Operating Long-Term Asset","worksheet_row":14},{"allowed_treatments":["Operating Long-Term Asset","Financial Asset"],"case_id":"classification::concept=other_noncurrent_assets|label=other assets","line_identity":"concept=other_noncurrent_assets|label=other assets","order":11,"override_selector":"identity:concept=other_noncurrent_assets|label=other assets","reference_treatment":"Operating Long-Term Asset","worksheet_row":15},{"allowed_treatments":["Financial Liability","Operating Long-Term Liability"],"case_id":"classification::concept=derivative_financial_liabilities_noncurrent|label=derivative financial liabilities","line_identity":"concept=derivative_financial_liabilities_noncurrent|label=derivative financial liabilities","order":12,"override_selector":"identity:concept=derivative_financial_liabilities_noncurrent|label=derivative financial liabilities","reference_treatment":"Financial Liability","worksheet_row":16},{"allowed_treatments":["Financial Liability","Operating Long-Term Liability"],"case_id":"classification::concept=financial_liabilities_noncurrent|label=financial liabilities","line_identity":"concept=financial_liabilities_noncurrent|label=financial liabilities","order":13,"override_selector":"identity:concept=financial_liabilities_noncurrent|label=financial liabilities","reference_treatment":"Financial Liability","worksheet_row":17},{"allowed_treatments":["Operating Long-Term Liability","Financial Liability"],"case_id":"classification::concept=lease_liability_noncurrent|label=lease liabilities","line_identity":"concept=lease_liability_noncurrent|label=lease liabilities","order":14,"override_selector":"identity:concept=lease_liability_noncurrent|label=lease liabilities","reference_treatment":"Operating Long-Term Liability","worksheet_row":18},{"allowed_treatments":["Operating Long-Term Liability","Financial Liability"],"case_id":"classification::concept=other_noncurrent_liabilities|label=other liabilities","line_identity":"concept=other_noncurrent_liabilities|label=other liabilities","order":15,"override_selector":"identity:concept=other_noncurrent_liabilities|label=other liabilities","reference_treatment":"Operating Long-Term Liability","worksheet_row":19}],"modeled_periods":["2021-08-31","2022-08-31","2023-08-31","2024-08-31","2025-08-31"],"normalization_bindings":[],"schema_version":2,"source_payload":{"balance_sheet":[{"concept":"total_assets","label":"Total assets","values":{"2021-08-31":2509976.0,"2022-08-31":3183762.0,"2023-08-31":3303694.0,"2024-08-31":3587565.0,"2025-08-31":3859353.0}},{"concept":"cash","label":"Cash and cash equivalents","values":{"2021-08-31":1177736.0,"2022-08-31":1358292.0,"2023-08-31":903280.0,"2024-08-31":1193560.0,"2025-08-31":893239.0}},{"concept":"derivative_financial_assets_current","label":"Derivative financial assets","values":{"2021-08-31":27103.0,"2022-08-31":124551.0,"2023-08-31":132101.0,"2024-08-31":111658.0,"2025-08-31":94803.0}},{"concept":"income_taxes_receivable","label":"Income taxes receivable","values":{"2021-08-31":2992.0,"2022-08-31":2612.0,"2023-08-31":23660.0,"2024-08-31":2210.0,"2025-08-31":8042.0}},{"concept":"inventories","label":"Inventories","values":{"2021-08-31":394868.0,"2022-08-31":485928.0,"2023-08-31":449254.0,"2024-08-31":474460.0,"2025-08-31":510958.0}},{"concept":"other_current_assets","label":"Other assets","values":{"2021-08-31":15270.0,"2022-08-31":23835.0,"2023-08-31":25372.0,"2024-08-31":26897.0,"2025-08-31":24662.0}},{"concept":"other_financial_assets_current","label":"Other financial assets","values":{"2021-08-31":56157.0,"2022-08-31":123446.0,"2023-08-31":576194.0,"2024-08-31":470554.0,"2025-08-31":899701.0}},{"concept":"total_current_assets","label":"Total current assets","values":{"2021-08-31":1724674.0,"2022-08-31":2178851.0,"2023-08-31":2176695.0,"2024-08-31":2363271.0,"2025-08-31":2527815.0}},{"concept":"trade_and_other_receivables","label":"Trade and other receivables","values":{"2021-08-31":50546.0,"2022-08-31":60184.0,"2023-08-31":66831.0,"2024-08-31":83929.0,"2025-08-31":96407.0}},{"concept":"current_tax_liabilities","label":"Current tax liabilities","values":{"2021-08-31":38606.0,"2022-08-31":77162.0,"2023-08-31":65428.0,"2024-08-31":65525.0,"2025-08-31":73072.0}},{"concept":"derivative_financial_liabilities_current","label":"Derivative financial liabilities","values":{"2021-08-31":2493.0,"2022-08-31":1513.0,"2023-08-31":3600.0,"2024-08-31":12716.0,"2025-08-31":19250.0}},{"concept":"lease_liability_current","label":"Lease liabilities","values":{"2021-08-31":117083.0,"2022-08-31":123885.0,"2023-08-31":126992.0,"2024-08-31":130744.0,"2025-08-31":126830.0}},{"concept":"other_financial_liabilities_current","label":"Other financial liabilities","values":{"2021-08-31":104969.0,"2022-08-31":209286.0,"2023-08-31":61913.0,"2024-08-31":104770.0,"2025-08-31":150942.0}},{"concept":"other_current_liabilities","label":"Other liabilities","values":{"2021-08-31":95652.0,"2022-08-31":111519.0,"2023-08-31":129782.0,"2024-08-31":148201.0,"2025-08-31":149394.0}},{"concept":"provisions_current","label":"Provisions","values":{"2021-08-31":2149.0,"2022-08-31":2581.0,"2023-08-31":2642.0,"2024-08-31":1774.0,"2025-08-31":1651.0}},{"concept":"total_current_liabilities","label":"Total current liabilities","values":{"2021-08-31":581012.0,"2022-08-31":876242.0,"2023-08-31":729260.0,"2024-08-31":852390.0,"2025-08-31":911291.0}},{"concept":"trade_and_other_payables","label":"Trade and other payables","values":{"2021-08-31":220057.0,"2022-08-31":350294.0,"2023-08-31":338901.0,"2024-08-31":388656.0,"2025-08-31":390149.0}},{"concept":"capital_stock","label":"Capital stock","values":{"2021-08-31":10273.0,"2022-08-31":10273.0,"2023-08-31":10273.0,"2024-08-31":10273.0,"2025-08-31":10273.0}},{"concept":"capital_surplus","label":"Capital surplus","values":{"2021-08-31":25360.0,"2022-08-31":27834.0,"2023-08-31":28531.0,"2024-08-31":29712.0,"2025-08-31":30998.0}},{"concept":"equity_attributable_to_owners","label":"Equity attributable to owners of the Parent","values":{"2021-08-31":1116484.0,"2022-08-31":1561652.0,"2023-08-31":1821405.0,"2024-08-31":2016535.0,"2025-08-31":2273115.0}},{"concept":"noncontrolling_interests","label":"Non-controlling interests","values":{"2021-08-31":45813.0,"2022-08-31":53750.0,"2023-08-31":51955.0,"2024-08-31":51718.0,"2025-08-31":54385.0}},{"concept":"other_components_of_equity","label":"Other components of equity","values":{"2021-08-31":41031.0,"2022-08-31":263255.0,"2023-08-31":298965.0,"2024-08-31":225104.0,"2025-08-31":189936.0}},{"concept":"retained_earnings","label":"Retained earnings","values":{"2021-08-31":1054791.0,"2022-08-31":1275102.0,"2023-08-31":1498348.0,"2024-08-31":1766073.0,"2025-08-31":2056437.0}},{"concept":"total_equity","label":"Total equity","values":{"2021-08-31":1162298.0,"2022-08-31":1615402.0,"2023-08-31":1873360.0,"2024-08-31":2068254.0,"2025-08-31":2327501.0}},{"concept":"total_liabilities_and_equity","label":"Total liabilities and equity","values":{"2021-08-31":2509976.0,"2022-08-31":3183762.0,"2023-08-31":3303694.0,"2024-08-31":3587565.0,"2025-08-31":3859353.0}},{"concept":"treasury_stock","label":"Treasury stock, at cost","values":{"2021-08-31":-14973.0,"2022-08-31":-14813.0,"2023-08-31":-14714.0,"2024-08-31":-14628.0,"2025-08-31":-14529.0}},{"concept":"total_liabilities","label":"Total liabilities","values":{"2021-08-31":1347678.0,"2022-08-31":1568360.0,"2023-08-31":1430333.0,"2024-08-31":1519310.0,"2025-08-31":1531852.0}},{"concept":"deferred_tax_assets","label":"Deferred tax assets","values":{"2021-08-31":37125.0,"2022-08-31":8506.0,"2023-08-31":38208.0,"2024-08-31":32432.0,"2025-08-31":40889.0}},{"concept":"derivative_financial_assets_noncurrent","label":"Derivative financial assets","values":{"2021-08-31":22552.0,"2022-08-31":134240.0,"2023-08-31":114151.0,"2024-08-31":66995.0,"2025-08-31":33882.0}},{"concept":"financial_assets_noncurrent","label":"Financial assets","values":{"2021-08-31":67122.0,"2022-08-31":164340.0,"2023-08-31":240363.0,"2024-08-31":336302.0,"2025-08-31":312438.0}},{"concept":"goodwill","label":"Goodwill","values":{"2021-08-31":8092.0,"2022-08-31":8092.0,"2023-08-31":8092.0,"2024-08-31":8092.0,"2025-08-31":8092.0}},{"concept":"intangible_assets","label":"Intangible assets","values":{"2021-08-31":66939.0,"2022-08-31":76621.0,"2023-08-31":87300.0,"2024-08-31":92568.0,"2025-08-31":91606.0}},{"concept":"investments_in_associates","label":"Investments in associates accounted for using the equity method","values":{"2021-08-31":18236.0,"2022-08-31":18557.0,"2023-08-31":18974.0,"2024-08-31":19559.0,"2025-08-31":31361.0}},{"concept":"other_noncurrent_assets","label":"Other assets","values":{"2021-08-31":6520.0,"2022-08-31":3690.0,"2023-08-31":8846.0,"2024-08-31":5888.0,"2025-08-31":3803.0}},{"concept":"property_plant_equipment","label":"Property, plant and equipment","values":{"2021-08-31":168177.0,"2022-08-31":195226.0,"2023-08-31":221877.0,"2024-08-31":245742.0,"2025-08-31":332351.0}},{"concept":"right_of_use_assets","label":"Right-of-use assets","values":{"2021-08-31":390537.0,"2022-08-31":395634.0,"2023-08-31":389183.0,"2024-08-31":416712.0,"2025-08-31":477111.0}},{"concept":"total_noncurrent_assets","label":"Total non-current assets","values":{"2021-08-31":785302.0,"2022-08-31":1004911.0,"2023-08-31":1126998.0,"2024-08-31":1224294.0,"2025-08-31":1331538.0}},{"concept":"deferred_tax_liabilities","label":"Deferred tax liabilities","values":{"2021-08-31":9860.0,"2022-08-31":44258.0,"2023-08-31":67039.0,"2024-08-31":31896.0,"2025-08-31":22539.0}},{"concept":"derivative_financial_liabilities_noncurrent","label":"Derivative financial liabilities","values":{"2021-08-31":1042.0,"2022-08-31":44.0,"2023-08-31":1410.0,"2024-08-31":21385.0,"2025-08-31":12110.0}},{"concept":"financial_liabilities_noncurrent","label":"Financial liabilities","values":{"2021-08-31":370799.0,"2022-08-31":241022.0,"2023-08-31":241068.0,"2024-08-31":211147.0,"2025-08-31":141071.0}},{"concept":"lease_liability_noncurrent","label":"Lease liabilities","values":{"2021-08-31":343574.0,"2022-08-31":356840.0,"2023-08-31":338657.0,"2024-08-31":347318.0,"2025-08-31":386670.0}},{"concept":"other_noncurrent_liabilities","label":"Other liabilities","values":{"2021-08-31":2342.0,"2022-08-31":2171.0,"2023-08-31":2007.0,"2024-08-31":2521.0,"2025-08-31":2457.0}},{"concept":"provisions_noncurrent","label":"Provisions","values":{"2021-08-31":39046.0,"2022-08-31":47780.0,"2023-08-31":50888.0,"2024-08-31":52652.0,"2025-08-31":55711.0}},{"concept":"total_noncurrent_liabilities","label":"Total non-current liabilities","values":{"2021-08-31":766665.0,"2022-08-31":692117.0,"2023-08-31":701072.0,"2024-08-31":666920.0,"2025-08-31":620561.0}}],"cash_flow":[{"concept":"change_in_inventories","label":"(Increase)/decrease in inventories","values":{"2021-08-31":36749.0,"2022-08-31":-50896.0,"2023-08-31":46908.0,"2024-08-31":-23540.0,"2025-08-31":-29855.0}},{"concept":"change_in_other_assets","label":"(Increase)/decrease in other assets","values":{"2021-08-31":3494.0,"2022-08-31":-7125.0,"2023-08-31":8354.0,"2024-08-31":-876.0,"2025-08-31":-2479.0}},{"concept":"change_in_trade_and_other_receivables","label":"(Increase)/decrease in trade and other receivables","values":{"2021-08-31":15334.0,"2022-08-31":-2651.0,"2023-08-31":-7535.0,"2024-08-31":-17394.0,"2025-08-31":-12718.0}},{"concept":"bank_deposits_placed","label":"Amounts deposited into bank deposits with original maturities of three months or longer","values":{"2021-08-31":-102307.0,"2022-08-31":-143517.0,"2023-08-31":-387720.0,"2024-08-31":-441156.0,"2025-08-31":-1008113.0}},{"concept":"bank_deposits_withdrawn","label":"Amounts withdrawn from bank deposits with original maturities of three months or longer","values":{"2021-08-31":99943.0,"2022-08-31":126774.0,"2023-08-31":182882.0,"2024-08-31":460241.0,"2025-08-31":798490.0}},{"concept":"cash_beginning","label":"Cash and cash equivalents at the beginning of year","values":{"2021-08-31":1093531.0,"2022-08-31":1177736.0,"2023-08-31":1358292.0,"2024-08-31":903280.0,"2025-08-31":1193560.0}},{"concept":"cash_ending","label":"Cash and cash equivalents at the end of year","values":{"2021-08-31":1177736.0,"2022-08-31":1358292.0,"2023-08-31":903280.0,"2024-08-31":1193560.0,"2025-08-31":893239.0}},{"concept":"cash_generated_from_operations","label":"Cash generated from operations","values":{"2021-08-31":509672.0,"2022-08-31":518010.0,"2023-08-31":610338.0,"2024-08-31":739726.0,"2025-08-31":728879.0}},{"concept":"depreciation_amortization","label":"Depreciation and amortization","values":{"2021-08-31":177910.0,"2022-08-31":180275.0,"2023-08-31":186872.0,"2024-08-31":204388.0,"2025-08-31":216492.0}},{"concept":"dividends_paid_to_nci","label":"Dividends paid to non-controlling interests","values":{"2021-08-31":-2342.0,"2022-08-31":-11623.0,"2023-08-31":-20460.0,"2024-08-31":-18369.0,"2025-08-31":-26428.0}},{"concept":"dividends_paid_to_owners","label":"Dividends paid to owners of the Parent","values":{"2021-08-31":-48993.0,"2022-08-31":-53091.0,"2023-08-31":-73064.0,"2024-08-31":-104263.0,"2025-08-31":-142630.0}},{"concept":"effect_of_exchange_rate_on_cash","label":"Effect of exchange rate changes on the balance of cash held in foreign currencies","values":{"2021-08-31":40818.0,"2022-08-31":175015.0,"2023-08-31":20735.0,"2024-08-31":-10007.0,"2025-08-31":37122.0}},{"concept":"foreign_exchange_losses_gains","label":"Foreign exchange losses/(gains)","values":{"2021-08-31":-19222.0,"2022-08-31":-114324.0,"2023-08-31":-25385.0,"2024-08-31":-621.0,"2025-08-31":-33826.0}},{"concept":"impairment_losses","label":"Impairment losses/(Reversal of impairment losses)","values":{"2021-08-31":16908.0,"2022-08-31":23150.0,"2023-08-31":3958.0,"2024-08-31":-1700.0,"2025-08-31":598.0}},{"concept":"income_taxes_paid","label":"Income taxes paid","values":{"2021-08-31":-80555.0,"2022-08-31":-95867.0,"2023-08-31":-160368.0,"2024-08-31":-156361.0,"2025-08-31":-202242.0}},{"concept":"income_taxes_refunded","label":"Income taxes refunded","values":{"2021-08-31":1818.0,"2022-08-31":7711.0,"2023-08-31":493.0,"2024-08-31":22800.0,"2025-08-31":2225.0}},{"concept":"change_in_other_liabilities","label":"Increase/(decrease) in other liabilities","values":{"2021-08-31":9300.0,"2022-08-31":-9531.0,"2023-08-31":-3700.0,"2024-08-31":31520.0,"2025-08-31":3852.0}},{"concept":"change_in_trade_and_other_payables","label":"Increase/(decrease) in trade and other payables","values":{"2021-08-31":384.0,"2022-08-31":114600.0,"2023-08-31":-15909.0,"2024-08-31":47320.0,"2025-08-31":476.0}},{"concept":"interest_dividends_received","label":"Interest and dividends income received","values":{"2021-08-31":4134.0,"2022-08-31":8520.0,"2023-08-31":22613.0,"2024-08-31":56454.0,"2025-08-31":64625.0}},{"concept":"interest_and_dividends_income","label":"Interest and dividends income","values":{"2021-08-31":-4628.0,"2022-08-31":-9495.0,"2023-08-31":-41330.0,"2024-08-31":-66751.0,"2025-08-31":-65317.0}},{"concept":"interest_expenses_cf","label":"Interest expenses","values":{"2021-08-31":6990.0,"2022-08-31":7560.0,"2023-08-31":9791.0,"2024-08-31":11078.0,"2025-08-31":12834.0}},{"concept":"interest_paid","label":"Interest paid","values":{"2021-08-31":-6101.0,"2022-08-31":-7557.0,"2023-08-31":-9861.0,"2024-08-31":-11099.0,"2025-08-31":-12869.0}},{"concept":"losses_on_disposal_ppe","label":"Losses on disposal of property, plant and equipment","values":{"2021-08-31":985.0,"2022-08-31":1136.0,"2023-08-31":917.0,"2024-08-31":1397.0,"2025-08-31":1342.0}},{"concept":"operating_cash_flow","label":"Net cash generated by operating activities","values":{"2021-08-31":428968.0,"2022-08-31":430817.0,"2023-08-31":463216.0,"2024-08-31":651521.0,"2025-08-31":580618.0}},{"concept":"financing_cash_flow","label":"Net cash used in financing activities","values":{"2021-08-31":-302985.0,"2022-08-31":-213050.0,"2023-08-31":-364562.0,"2024-08-31":-269003.0,"2025-08-31":-339139.0}},{"concept":"investing_cash_flow","label":"Net cash used in investing activities","values":{"2021-08-31":-82597.0,"2022-08-31":-212226.0,"2023-08-31":-574402.0,"2024-08-31":-82231.0,"2025-08-31":-578922.0}},{"concept":"net_change_in_cash","label":"Net increase/(decrease) in cash and cash equivalents","values":{"2021-08-31":84204.0,"2022-08-31":180556.0,"2023-08-31":-455011.0,"2024-08-31":290279.0,"2025-08-31":-300320.0}},{"concept":"others_net_financing","label":"Others, net","values":{"2021-08-31":155.0,"2022-08-31":705.0,"2023-08-31":413.0,"2024-08-31":63.0,"2025-08-31":430.0}},{"concept":"others_net_investing","label":"Others, net","values":{"2021-08-31":407.0,"2022-08-31":3301.0,"2023-08-31":-1381.0,"2024-08-31":171.0,"2025-08-31":7399.0}},{"concept":"others_net_operating","label":"Others, net","values":{"2021-08-31":153.0,"2022-08-31":-27211.0,"2023-08-31":10617.0,"2024-08-31":-878.0,"2025-08-31":-11391.0}},{"concept":"payments_for_rou_assets","label":"Payments for acquisition of right-of-use assets","values":{"2021-08-31":-846.0,"2022-08-31":-796.0,"2023-08-31":-1851.0,"2024-08-31":-2015.0,"2025-08-31":-15924.0}},{"concept":"payments_for_intangible_assets","label":"Payments for intangible assets","values":{"2021-08-31":-19624.0,"2022-08-31":-28335.0,"2023-08-31":-33542.0,"2024-08-31":-30260.0,"2025-08-31":-27329.0}},{"concept":"payments_for_investment_securities","label":"Payments for investment securities","values":{"2021-08-31":0.0,"2022-08-31":-117521.0,"2023-08-31":-481399.0,"2024-08-31":-399523.0,"2025-08-31":-474222.0}},{"concept":"payments_for_lease_guarantee_deposits","label":"Payments for lease and guarantee deposits","values":{"2021-08-31":-3979.0,"2022-08-31":-5973.0,"2023-08-31":-4865.0,"2024-08-31":-6108.0,"2025-08-31":-6113.0}},{"concept":"payments_for_ppe","label":"Payments for property, plant and equipment","values":{"2021-08-31":-56500.0,"2022-08-31":-51271.0,"2023-08-31":-61764.0,"2024-08-31":-73728.0,"2025-08-31":-135535.0}},{"concept":"proceeds_from_lease_guarantee_deposits","label":"Proceeds from collection of lease and guarantee deposits","values":{"2021-08-31":4542.0,"2022-08-31":5112.0,"2023-08-31":5578.0,"2024-08-31":6302.0,"2025-08-31":6364.0}},{"concept":"proceeds_from_short_term_loans","label":"Proceeds from short-term loans payable","values":{"2021-08-31":64247.0,"2022-08-31":14059.0,"2023-08-31":6511.0,"2024-08-31":4835.0,"2025-08-31":566.0}},{"concept":"pretax_income","label":"Profit before income taxes","values":{"2021-08-31":265872.0,"2022-08-31":413584.0,"2023-08-31":437918.0,"2024-08-31":557201.0,"2025-08-31":650574.0}},{"concept":"repayment_of_bonds","label":"Repayment of redemption of corporate bonds","values":{"2021-08-31":-100000.0,"2022-08-31":0.0,"2023-08-31":-130000.0,"2024-08-31":0.0,"2025-08-31":-30000.0}},{"concept":"repayment_of_short_term_loans","label":"Repayment of short-term loans payable","values":{"2021-08-31":-67804.0,"2022-08-31":-26210.0,"2023-08-31":-7314.0,"2024-08-31":-4887.0,"2025-08-31":-226.0}},{"concept":"repayments_of_lease_liabilities","label":"Repayments of lease liabilities","values":{"2021-08-31":-148248.0,"2022-08-31":-136889.0,"2023-08-31":-140646.0,"2024-08-31":-146403.0,"2025-08-31":-140483.0}},{"concept":"share_of_associates_cf","label":"Share of (profit)/loss of associates accounted for using the equity method","values":{"2021-08-31":-561.0,"2022-08-31":-1059.0,"2023-08-31":-1139.0,"2024-08-31":-1417.0,"2025-08-31":-1704.0}}],"company_name":"FAST RETAILING CO., LTD.","currency":"JPY","historical_lease":{"lease_interest_expense":{"2021-08-31":4847.0,"2022-08-31":4757.0,"2023-08-31":5187.0,"2024-08-31":6507.0,"2025-08-31":8464.0}},"historical_shares":{"adjustment_factors":{"2021-08-31":3.0,"2022-08-31":1.0,"2023-08-31":1.0,"2024-08-31":1.0,"2025-08-31":1.0},"basis":"split_adjusted","diluted_weighted_average":{"2021-08-31":306.871785,"2022-08-31":306.969624,"2023-08-31":307.13887,"2024-08-31":307.231804,"2025-08-31":307.247804},"scale_basis":"financial_statement_units"},"income_statement":[{"concept":"basic_eps","label":"Basic (yen, dollar)","values":{"2021-08-31":1663.12,"2022-08-31":891.77,"2023-08-31":966.09,"2024-08-31":1212.88,"2025-08-31":1411.44}},{"concept":"cost_of_sales","label":"Cost of sales","values":{"2021-08-31":-1059036.0,"2022-08-31":-1094263.0,"2023-08-31":-1330196.0,"2024-08-31":-1430764.0,"2025-08-31":-1571681.0}},{"concept":"diluted_eps","label":"Diluted (yen, dollar)","values":{"2021-08-31":1660.44,"2022-08-31":890.43,"2023-08-31":964.48,"2024-08-31":1210.81,"2025-08-31":1409.32}},{"concept":"interest_expense","label":"Finance costs","values":{"2021-08-31":-6998.0,"2022-08-31":-7560.0,"2023-08-31":-9888.0,"2024-08-31":-11101.0,"2025-08-31":-12834.0}},{"concept":"interest_income","label":"Finance income","values":{"2021-08-31":23859.0,"2022-08-31":123820.0,"2023-08-31":66716.0,"2024-08-31":67399.0,"2025-08-31":99143.0}},{"concept":"gross_profit","label":"Gross profit","values":{"2021-08-31":1073955.0,"2022-08-31":1206859.0,"2023-08-31":1436360.0,"2024-08-31":1673071.0,"2025-08-31":1828858.0}},{"concept":"tax_expense","label":"Income tax expense","values":{"2021-08-31":-90188.0,"2022-08-31":-128834.0,"2023-08-31":-122746.0,"2024-08-31":-163596.0,"2025-08-31":-191421.0}},{"concept":"profit_attributable_to_nci","label":"Non-controlling interests","values":{"2021-08-31":5836.0,"2022-08-31":11415.0,"2023-08-31":18941.0,"2024-08-31":21605.0,"2025-08-31":26143.0}},{"concept":"operating_profit","label":"Operating profit","values":{"2021-08-31":249011.0,"2022-08-31":297325.0,"2023-08-31":381090.0,"2024-08-31":500904.0,"2025-08-31":564265.0}},{"concept":"other_expenses","label":"Other expenses","values":{"2021-08-31":-25315.0,"2022-08-31":-27391.0,"2023-08-31":-14238.0,"2024-08-31":-6256.0,"2025-08-31":-8087.0}},{"concept":"other_income","label":"Other income","values":{"2021-08-31":18238.0,"2022-08-31":16951.0,"2023-08-31":12197.0,"2024-08-31":20384.0,"2025-08-31":19491.0}},{"concept":"profit_attributable_to_owners","label":"Owners of the Parent","values":{"2021-08-31":169847.0,"2022-08-31":273335.0,"2023-08-31":296229.0,"2024-08-31":371999.0,"2025-08-31":433009.0}},{"concept":"pretax_income","label":"Profit before income taxes","values":{"2021-08-31":265872.0,"2022-08-31":413584.0,"2023-08-31":437918.0,"2024-08-31":557201.0,"2025-08-31":650574.0}},{"concept":"net_income","label":"Profit for the year","values":{"2021-08-31":175684.0,"2022-08-31":284750.0,"2023-08-31":315171.0,"2024-08-31":393605.0,"2025-08-31":459153.0}},{"concept":"revenue","label":"Revenue","values":{"2021-08-31":2132992.0,"2022-08-31":2301122.0,"2023-08-31":2766557.0,"2024-08-31":3103836.0,"2025-08-31":3400539.0}},{"concept":"selling_general_administrative","label":"Selling, general and administrative expenses","values":{"2021-08-31":-818427.0,"2022-08-31":-900154.0,"2023-08-31":-1054368.0,"2024-08-31":-1187713.0,"2025-08-31":-1277701.0}},{"concept":"share_of_profit_of_associates","label":"Share of profit of associates accounted for using the equity method","values":{"2021-08-31":561.0,"2022-08-31":1059.0,"2023-08-31":1139.0,"2024-08-31":1417.0,"2025-08-31":1704.0}}],"jurisdiction":"JP","periods":[{"end_date":"2021-08-31","is_interim":false,"label":"FY2021"},{"end_date":"2022-08-31","is_interim":false,"label":"FY2022"},{"end_date":"2023-08-31","is_interim":false,"label":"FY2023"},{"end_date":"2024-08-31","is_interim":false,"label":"FY2024"},{"end_date":"2025-08-31","is_interim":false,"label":"FY2025"}],"stock_code":"6288.HK","ticker":"6288.HK","units":"JPY in Millions"}}
