Workbook

Sheet Trainer
A1: BAV Excel Trainer
A2: Complete each historical model-construction and earnings-quality diagnostic formula schedule left-to-right in dependency order. Run Check to validate the yellow formula cells against the treatment currently selected in Accounting Judgment column F (blank F uses the supplied reference treatment). Generated Condensed Financials classification links are system-controlled and validated by Check—do not edit them or columns D:E. When Normalization Judgment is present, choose Recurring vs Non-recurring in column F (blank uses the supplied reference); Earnings Normalization formulas are checked against that choice. Also complete Accounting Judgment and Normalization Judgment rationale/consequence when cases are present; those responses are not graded by Check. Compare them with the matching Answer Key.
A4: Order | B4: Schedule | C4: Period scope | D4: Tab | E4: Practice cells | F4: Depends on
A5: 1 | B5: Revenue historical source link | C5: 2023–2026 (4 cells) | D5: Condensed Financials | E5: B34:E34 | F5: —
A6: 2 | B6: Net Income historical source link | C6: 2023–2026 (4 cells) | D6: Condensed Financials | E6: B35:E35 | F6: —
A7: 3 | B7: Effective tax rate | C7: 2023–2026 (4 cells) | D7: Condensed Financials | E7: B38:E38 | F7: —
A8: 7 | B8: Operating working capital assets | C8: 2023–2026 (4 cells) | D8: Condensed Financials | E8: B44:E44 | F8: —
A9: 8 | B9: Operating working capital liabilities | C9: 2023–2026 (4 cells) | D9: Condensed Financials | E9: B45:E45 | F9: —
A10: 9 | B10: Net Operating Working Capital (NOWC) | C10: 2023–2026 (4 cells) | D10: Condensed Financials | E10: B46:E46 | F10: owca_agg, owcl_agg
A11: 10 | B11: Operating long-term assets | C11: 2023–2026 (4 cells) | D11: Condensed Financials | E11: B47:E47 | F11: —
A12: 11 | B12: Operating long-term liabilities | C12: 2023–2026 (4 cells) | D12: Condensed Financials | E12: B48:E48 | F12: —
A13: 12 | B13: Net operating long-term assets (NOLA) | C13: 2023–2026 (4 cells) | D13: Condensed Financials | E13: B49:E49 | F13: olta_agg, oltl_agg
A14: 13 | B14: Net Operating Assets (NOA) | C14: 2023–2026 (4 cells) | D14: Condensed Financials | E14: B50:E50 | F14: nowc_agg, nola_agg
A15: 14 | B15: Financial assets | C15: 2023–2026 (4 cells) | D15: Condensed Financials | E15: B51:E51 | F15: —
A16: 15 | B16: Financial liabilities | C16: 2023–2026 (4 cells) | D16: Condensed Financials | E16: B52:E52 | F16: —
... A78: 121 | B78: PP&E Capex / Revenue | C78: 2023–2026 (4 cells) | D78: ALT DuPont | E78: B63:E63 | F78: ppe_capex, revenue_link

Sheet Income Statement
A1: Company: lululemon athletica inc. (LULU)
A2: Statement: Income Statement
A3: Units: USD in Thousands
A4: Source: manual ingestion (US)
A6: Line Item | B6: 44955 | C6: 45319 | D6: 45690 | E6: 46054
A7: Foreign currency translation adjustment | B7: -65571 | C7: -23077 | D7: -253209 | E7: 253160
A8: Net investment hedge gains (losses) | B8: 8904 | C8: 11405 | D8: 93024 | E8: -59409
A9: Amortization of intangible assets | B9: 8752 | C9: 5010 | D9: 2735 | E9: 6961
A10: Basic earnings per share | B10: 6.7 | C10: 12.23 | D10: 14.67 | E10: 13.27
A11: Comprehensive income | B11: 798133 | C11: 1538518 | D11: 1654431 | E11: 1772934
A12: Cost of goods sold | B12: 3618178 | C12: 4009873 | D12: 4317315 | E12: 4818468
A13: Diluted earnings per share | B13: 6.68 | C13: 12.2 | D13: 14.64 | E13: 13.26
A14: Gross profit | B14: 4492340 | C14: 5609405 | D14: 6270811 | E14: 6284132
A15: Income before income tax expense | B15: 1332571 | C15: 2175735 | D15: 2576077 | E15: 2238967
A16: Income from operations | B16: 1328408 | C16: 2132676 | D16: 2505697 | E16: 2210615
A17: Income tax expense | B17: 477771 | C17: 625545 | D17: 761461 | E17: 659784
... A22: Selling, general and administrative expenses | B22: 2757447 | C22: 3397218 | D22: 3762379 | E22: 4066556

Sheet Balance Sheet
A1: Company: lululemon athletica inc. (LULU)
A2: Statement: Balance Sheet
A3: Units: USD in Thousands
A4: Source: manual ingestion (US)
A6: Line Item | B6: 44955 | C6: 45319 | D6: 45690 | E6: 46054
A7: Accounts receivable, net | B7: 132906 | C7: 124769 | D7: 120173 | E7: 190657
A8: Cash and cash equivalents | B8: 1154867 | C8: 2243971 | D8: 1984336 | E8: 1807202
A9: Inventories | B9: 1447367 | C9: 1323602 | D9: 1442081 | E9: 1700753
A10: Prepaid and receivable income taxes | B10: 185641 | C10: 183733 | D10: 182253 | E10: 352469
A11: Prepaid expenses and other current assets | B11: 238672 | C11: 184502 | D11: 251459 | E11: 211620
A12: Total current assets | B12: 3159453 | C12: 4060577 | D12: 3980302 | E12: 4262701
A13: Accounts payable | B13: 172732 | C13: 348441 | D13: 271406 | E13: 331421
A14: Accrued compensation and related expenses | B14: 248167 | C14: 326110 | D14: 204543 | E14: 187887
A15: Accrued liabilities and other | B15: 399223 | C15: 348555 | D15: 559463 | E15: 662982
A16: Current income taxes payable | B16: 174221 | C16: 12098 | D16: 183126 | E16: 43948
A17: Current lease liabilities | B17: 207972 | C17: 249270 | D17: 275154 | E17: 298724
... A27: Deferred income tax liabilities | B27: 55084 | C27: 29522 | D27: 98188 | E27: 52278
A28: Non-current income taxes payable | B28: 28555 | C28: 15864 | D28: 0
A29: Non-current lease liabilities | B29: 862362 | C29: 1154012 | D29: 1300637 | E29: 1499717
A30: Other non-current liabilities | B30: 20040 | C30: 29201 | D30: 40790 | E30: 55360
A31: Accumulated other comprehensive loss | B31: -252584 | C31: -264256 | D31: -424441 | E31: -230690
A32: Additional paid-in capital | B32: 474645 | C32: 575369 | D32: 638190 | E32: 669392
A33: Common stock | B33: 611 | C33: 606 | D33: 581 | E33: 557
A34: Retained earnings | B34: 2926127 | C34: 3920362 | D34: 4109717 | E34: 4522581
A35: Total stockholders' equity | B35: 3148799 | C35: 4232081 | D35: 4324047 | E35: 4961840
A36: Total assets | B36: 5607038 | C36: 7091941 | D36: 7603292 | E36: 8456743
A37: Total liabilities and stockholders' equity | B37: 5607038 | C37: 7091941 | D37: 7603292 | E37: 8456743
A38: Total liabilities | B38: 2458239 | C38: 2859860 | D38: 3279245 | E38: 3494903

Sheet Cash Flow Statement
A1: Company: lululemon athletica inc. (LULU)
A2: Statement: Cash Flow Statement
A3: Units: USD in Thousands
A4: Source: manual ingestion (US)
A6: Line Item | B6: 44955 | C6: 45319 | D6: 45690 | E6: 46054
A7: Net cash used in financing activities | B7: -467487 | C7: -548828 | D7: -1652508 | E7: -1208656
A8: Other financing activities | B8: -32 | C8: -32 | D8: -32 | E8: -11312
A9: Proceeds from settlement of stock-based compensation | B9: 11704 | C9: 42430 | D9: 19813 | E9: 8377
A10: Repurchase of common stock | B10: -444001 | C10: -558652 | D10: -1636879 | E10: -1178349
A11: Shares withheld related to net share settlement of stock-based compensation | B11: -35158 | C11: -32574 | D11: -35410 | E11: -27372
A12: Acquisition, net of cash acquired | B12: 0 | C12: 0 | D12: -154146 | E12: 0
A13: Net cash used in investing activities | B13: -569937 | C13: -654132 | D13: -798174 | E13: -662118
A14: Other investing activities | B14: 20916 | C14: -658 | D14: -5009 | E14: -8521
A15: Purchase of property and equipment | B15: -638657 | C15: -651865 | D15: -689232 | E15: -680802
A16: Settlement of net investment hedges | B16: 47804 | C16: -1609 | D16: 50213 | E16: 27205
A17: Accounts payable | B17: -107280 | C17: 177367 | D17: -57044 | E17: 45856
... A40: Increase (decrease) in cash and cash equivalents | B40: -105004 | C40: 1089104 | D40: -259635 | E40: -177134

Sheet Condensed Financials
A1: lululemon athletica inc. (LULU) — Condensed Financials
A4: BALANCE SHEET CLASSIFICATION
A5: Line Item | B5: Classification | C5: 44955 | D5: 45319 | E5: 45690 | F5: 46054 | G5: Notes
A6: Accounts receivable, net | B6: Operating Working Capital Asset | C6: 132906 | D6: 124769 | E6: 120173 | F6: 190657
A7: Cash and cash equivalents | B7: Financial Asset | C7: 1154867 | D7: 2243971 | E7: 1984336 | F7: 1807202
A8: Inventories | B8: Operating Working Capital Asset | C8: 1447367 | D8: 1323602 | E8: 1442081 | F8: 1700753
A9: Prepaid and receivable income taxes | B9: Operating Working Capital Asset | C9: 185641 | D9: 183733 | E9: 182253 | F9: 352469
A10: Prepaid expenses and other current assets | B10: Operating Working Capital Asset | C10: 238672 | D10: 184502 | E10: 251459 | F10: 211620
A11: Accounts payable | B11: Operating Working Capital Liability | C11: 172732 | D11: 348441 | E11: 271406 | F11: 331421
A12: Accrued compensation and related expenses | B12: Operating Working Capital Liability | C12: 248167 | D12: 326110 | E12: 204543 | F12: 187887
A13: Accrued liabilities and other | B13: Operating Working Capital Liability | C13: 399223 | D13: 348555 | E13: 559463 | F13: 662982
A14: Current income taxes payable | B14: Operating Working Capital Liability | C14: 174221 | D14: 12098 | E14: 183126 | F14: 43948
A15: Current lease liabilities | B15: =IF('Accounting Judgment'!$F$5="","Operating Long-Term Liability",'Accounting Judgment'!$F$5) | C15: 207972 | D15: 249270 | E15: 275154 | F15: 298724 | G15: ⚠ Review: Lease liability concept — operating vs financial judgment
A16: Other current liabilities | B16: =IF('Accounting Judgment'!$F$6="","Operating Working Capital Liability",'Accounting Judgment'!$F$6) | C16: 38405 | D16: 40308 | E16: 37586 | F16: 45954 | G16: ⚠ Review: Explicit residual balance-sheet concept identifies side/horizon but not economic nature — operating vs financial judgment
A17: Unredeemed gift card liability | B17: Operating Working Capital Liability | C17: 251478 | D17: 306479 | E17: 308352 | F17: 316632
A18: Deferred income tax assets | B18: Operating Long-Term Asset | C18: 6402 | D18: 9176 | E18: 17085 | F18: 24037 | G18: ⚠ Review: Deferred tax asset concept — operating vs exclude judgment
A19: Goodwill | B19: Operating Long-Term Asset | C19: 24144 | D19: 24083 | E19: 159518 | F19: 184911
A20: Intangible assets, net | B20: Operating Long-Term Asset | C20: 21961 | D20: 0 | E20: 11673 | F20: 6283
A21: Other non-current assets | B21: =IF('Accounting Judgment'!$F$7="","Operating Long-Term Asset",'Accounting Judgment'!$F$7) | C21: 156045 | D21: 186684 | E21: 237841 | F21: 314910 | G21: ⚠ Review: Explicit residual balance-sheet concept identifies side/horizon but not economic nature — operating vs financial judgment
A22: Property and equipment, net | B22: Operating Long-Term Asset | C22: 1269614 | D22: 1545811 | E22: 1780617 | F22: 2033720
A23: Right-of-use lease assets | B23: Operating Long-Term Asset | C23: 969419 | D23: 1265610 | E23: 1416256 | F23: 1630181 | G23: ⚠ Review: Lease/ROU asset concept — operating vs financial judgment
A24: Deferred income tax liabilities | B24: Operating Long-Term Liability | C24: 55084 | D24: 29522 | E24: 98188 | F24: 52278 | G24: ⚠ Review: Deferred tax liability concept — operating vs exclude judgment
A25: Non-current income taxes payable | B25: Operating Working Capital Liability | C25: 28555 | D25: 15864 | E25: 0
A26: Non-current lease liabilities | B26: =IF('Accounting Judgment'!$F$8="","Operating Long-Term Liability",'Accounting Judgment'!$F$8) | C26: 862362 | D26: 1154012 | E26: 1300637 | F26: 1499717 | G26: ⚠ Review: Lease liability concept — operating vs financial judgment
A27: Other non-current liabilities | B27: =IF('Accounting Judgment'!$F$9="","Operating Long-Term Liability",'Accounting Judgment'!$F$9) | C27: 20040 | D27: 29201 | E27: 40790 | F27: 55360 | G27: ⚠ Review: Explicit residual balance-sheet concept identifies side/horizon but not economic nature — operating vs financial judgment
A28: Accumulated other comprehensive loss | B28: Equity | C28: -252584 | D28: -264256 | E28: -424441 | F28: -230690
A29: Additional paid-in capital | B29: Equity | C29: 474645 | D29: 575369 | E29: 638190 | F29: 669392
A30: Common stock | B30: Equity | C30: 611 | D30: 606 | E30: 581 | F30: 557
A31: Retained earnings | B31: Equity | C31: 2926127 | D31: 3920362 | E31: 4109717 | F31: 4522581
A33: CONDENSED INCOME STATEMENT | B33: 44955 | C33: 45319 | D33: 45690 | E33: 46054
A34: Revenue | B34: ='Income Statement'!B19 | C34: ='Income Statement'!C19 | D34: ='Income Statement'!D19 | E34: ='Income Statement'!E19
A35: Net Income | B35: ='Income Statement'!B18 | C35: ='Income Statement'!C18 | D35: ='Income Statement'!D18 | E35: ='Income Statement'!E18
A36: Pretax Income | B36: ='Income Statement'!B15 | C36: ='Income Statement'!C15 | D36: ='Income Statement'!D15 | E36: ='Income Statement'!E15
A37: Tax Expense | B37: ='Income Statement'!B17 | C37: ='Income Statement'!C17 | D37: ='Income Statement'!D17 | E37: ='Income Statement'!E17
A38: Effective Tax Rate | B38: =IF(B36=0,NA(),-B37/B36) | C38: =IF(C36=0,NA(),-C37/C36) | D38: =IF(D36=0,NA(),-D37/D36) | E38: =IF(E36=0,NA(),-E37/E36)
A39: Net Interest | B39: Source unavailable | C39: Source unavailable | D39: Source unavailable | E39: Source unavailable
A40: Net Interest After Tax | B40: Source unavailable | C40: Source unavailable | D40: Source unavailable | E40: Source unavailable
A41: NOPAT | B41: Source unavailable | C41: Source unavailable | D41: Source unavailable | E41: Source unavailable
A43: CONDENSED BALANCE SHEET
A44: Operating Working Capital Assets | B44: =SUMIF($B$6:$B$31,"Operating Working Capital Asset",C$6:C$31) | C44: =SUMIF($B$6:$B$31,"Operating Working Capital Asset",D$6:D$31) | D44: =SUMIF($B$6:$B$31,"Operating Working Capital Asset",E$6:E$31) | E44: =SUMIF($B$6:$B$31,"Operating Working Capital Asset",F$6:F$31)
A45: Operating Working Capital Liabilities | B45: =SUMIF($B$6:$B$31,"Operating Working Capital Liability",C$6:C$31) | C45: =SUMIF($B$6:$B$31,"Operating Working Capital Liability",D$6:D$31) | D45: =SUMIF($B$6:$B$31,"Operating Working Capital Liability",E$6:E$31) | E45: =SUMIF($B$6:$B$31,"Operating Working Capital Liability",F$6:F$31)
A46: NOWC | B46: =B44-B45 | C46: =C44-C45 | D46: =D44-D45 | E46: =E44-E45
A47: Operating Long-Term Assets | B47: =SUMIF($B$6:$B$31,"Operating Long-Term Asset",C$6:C$31) | C47: =SUMIF($B$6:$B$31,"Operating Long-Term Asset",D$6:D$31) | D47: =SUMIF($B$6:$B$31,"Operating Long-Term Asset",E$6:E$31) | E47: =SUMIF($B$6:$B$31,"Operating Long-Term Asset",F$6:F$31)
A48: Operating Long-Term Liabilities | B48: =SUMIF($B$6:$B$31,"Operating Long-Term Liability",C$6:C$31) | C48: =SUMIF($B$6:$B$31,"Operating Long-Term Liability",D$6:D$31) | D48: =SUMIF($B$6:$B$31,"Operating Long-Term Liability",E$6:E$31) | E48: =SUMIF($B$6:$B$31,"Operating Long-Term Liability",F$6:F$31)
A49: NOLA | B49: =B47-B48 | C49: =C47-C48 | D49: =D47-D48 | E49: =E47-E48
A50: NOA | B50: =B46+B49 | C50: =C46+C49 | D50: =D46+D49 | E50: =E46+E49
A51: Financial Assets | B51: =SUMIF($B$6:$B$31,"Financial Asset",C$6:C$31) | C51: =SUMIF($B$6:$B$31,"Financial Asset",D$6:D$31) | D51: =SUMIF($B$6:$B$31,"Financial Asset",E$6:E$31) | E51: =SUMIF($B$6:$B$31,"Financial Asset",F$6:F$31)
A52: Financial Liabilities | B52: =SUMIF($B$6:$B$31,"Financial Liability",C$6:C$31) | C52: =SUMIF($B$6:$B$31,"Financial Liability",D$6:D$31) | D52: =SUMIF($B$6:$B$31,"Financial Liability",E$6:E$31) | E52: =SUMIF($B$6:$B$31,"Financial Liability",F$6:F$31)
A53: Net Debt | B53: =B52-B51 | C53: =C52-C51 | D53: =D52-D51 | E53: =E52-E51
A54: Equity (NOA - Net Debt) | B54: =B50-B53 | C54: =C50-C53 | D54: =D50-D53 | E54: =E50-E53
A55: Reported Equity | B55: ='Balance Sheet'!B35 | C55: ='Balance Sheet'!C35 | D55: ='Balance Sheet'!D35 | E55: ='Balance Sheet'!E35
A56: Total Capital | B56: =B53+B54 | C56: =C53+C54 | D56: =D53+D54 | E56: =E53+E54
A57: CHECK | B57: =IF(ABS(B54-B55)<1,"OK","CHECK") | C57: =IF(ABS(C54-C55)<1,"OK","CHECK") | D57: =IF(ABS(D54-D55)<1,"OK","CHECK") | E57: =IF(ABS(E54-E55)<1,"OK","CHECK")

Sheet ALT DuPont
A1: lululemon athletica inc. — DuPont Decomposition
A2: ROE = RNOA + FLEV × Spread
A4: Metric | B4: 44955 | C4: 45319 | D4: 45690 | E4: 46054
A5: Sales Growth | B5: N/A | C5: =IF('Condensed Financials'!B34=0,NA(),'Condensed Financials'!C34/'Condensed Financials'!B34-1) | D5: =IF('Condensed Financials'!C34=0,NA(),'Condensed Financials'!D34/'Condensed Financials'!C34-1) | E5: =IF('Condensed Financials'!D34=0,NA(),'Condensed Financials'!E34/'Condensed Financials'!D34-1)
A6: NOPAT Margin | B6: Source unavailable | C6: Source unavailable | D6: Source unavailable | E6: Source unavailable
A7: RNOA | B7: N/A | C7: Source unavailable | D7: Source unavailable | E7: Source unavailable
A8: After-tax CoD | B8: N/A | C8: Source unavailable | D8: Source unavailable | E8: Source unavailable
A9: Spread | B9: N/A | C9: Source unavailable | D9: Source unavailable | E9: Source unavailable
A10: FLEV | B10: N/A | C10: =IF((('Condensed Financials'!C54+'Condensed Financials'!B54)/2)=0,NA(),(('Condensed Financials'!C53+'Condensed Financials'!B53)/2)/(('Condensed Financials'!C54+'Condensed Financials'!B54)/2)) | D10: =IF((('Condensed Financials'!D54+'Condensed Financials'!C54)/2)=0,NA(),(('Condensed Financials'!D53+'Condensed Financials'!C53)/2)/(('Condensed Financials'!D54+'Condensed Financials'!C54)/2)) | E10: =IF((('Condensed Financials'!E54+'Condensed Financials'!D54)/2)=0,NA(),(('Condensed Financials'!E53+'Condensed Financials'!D53)/2)/(('Condensed Financials'!E54+'Condensed Financials'!D54)/2))
A11: ROE (decomposed) | B11: N/A | C11: Source unavailable | D11: Source unavailable | E11: Source unavailable
A12: Actual ROE | B12: N/A | C12: =IF((('Condensed Financials'!C54+'Condensed Financials'!B54)/2)=0,NA(),'Condensed Financials'!C35/(('Condensed Financials'!C54+'Condensed Financials'!B54)/2)) | D12: =IF((('Condensed Financials'!D54+'Condensed Financials'!C54)/2)=0,NA(),'Condensed Financials'!D35/(('Condensed Financials'!D54+'Condensed Financials'!C54)/2)) | E12: =IF((('Condensed Financials'!E54+'Condensed Financials'!D54)/2)=0,NA(),'Condensed Financials'!E35/(('Condensed Financials'!E54+'Condensed Financials'!D54)/2))
A14: RNOA DRIVER DECOMPOSITION
A15: Average NOA | B15: N/A | C15: =('Condensed Financials'!B50+'Condensed Financials'!C50)/2 | D15: =('Condensed Financials'!C50+'Condensed Financials'!D50)/2 | E15: =('Condensed Financials'!D50+'Condensed Financials'!E50)/2
A16: NOA Turnover | B16: N/A | C16: =IF(C15=0,NA(),'Condensed Financials'!C34/C15) | D16: =IF(D15=0,NA(),'Condensed Financials'!D34/D15) | E16: =IF(E15=0,NA(),'Condensed Financials'!E34/E15)
A17: NOA Intensity | B17: N/A | C17: =IF('Condensed Financials'!C34=0,NA(),C15/'Condensed Financials'!C34) | D17: =IF('Condensed Financials'!D34=0,NA(),D15/'Condensed Financials'!D34) | E17: =IF('Condensed Financials'!E34=0,NA(),E15/'Condensed Financials'!E34)
A18: RNOA from Margin × Turnover | B18: N/A | C18: Source unavailable | D18: Source unavailable | E18: Source unavailable
A19: RNOA DRIVER CHECK | B19: N/A | C19: Source unavailable | D19: Source unavailable | E19: Source unavailable
A21: RNOA CHANGE ATTRIBUTION
A22: Change in NOPAT Margin | B22: N/A | C22: N/A | D22: Source unavailable | E22: Source unavailable
A23: Change in NOA Turnover | B23: N/A | C23: N/A | D23: =D16-C16 | E23: =E16-D16
A24: Direct Change in RNOA | B24: N/A | C24: N/A | D24: Source unavailable | E24: Source unavailable
A25: Margin Effect on RNOA Change | B25: N/A | C25: N/A | D25: Source unavailable | E25: Source unavailable
A26: Turnover Effect on RNOA Change | B26: N/A | C26: N/A | D26: Source unavailable | E26: Source unavailable
A27: RNOA Change from Drivers | B27: N/A | C27: N/A | D27: Source unavailable | E27: Source unavailable
A28: RNOA CHANGE DRIVER CHECK | B28: N/A | C28: N/A | D28: Source unavailable | E28: Source unavailable
A30: ROE OPERATING / FINANCING ATTRIBUTION
A31: Financing Contribution to ROE | B31: N/A | C31: Source unavailable | D31: Source unavailable | E31: Source unavailable
A32: ROE LEVEL ATTRIBUTION CHECK | B32: N/A | C32: Source unavailable | D32: Source unavailable | E32: Source unavailable
A34: ROE CHANGE ATTRIBUTION
A35: Direct Change in Decomposed ROE | B35: N/A | C35: N/A | D35: Source unavailable | E35: Source unavailable
A36: Operating Effect on Change in ROE | B36: N/A | C36: N/A | D36: Source unavailable | E36: Source unavailable
A37: Leverage Effect on Change in ROE | B37: N/A | C37: N/A | D37: Source unavailable | E37: Source unavailable
A38: Spread Effect on Change in ROE | B38: N/A | C38: N/A | D38: Source unavailable | E38: Source unavailable
A39: Financing Effect on Change in ROE | B39: N/A | C39: N/A | D39: Source unavailable | E39: Source unavailable
A40: Change in ROE from Drivers | B40: N/A | C40: N/A | D40: Source unavailable | E40: Source unavailable
A41: ROE CHANGE ATTRIBUTION CHECK | B41: N/A | C41: N/A | D41: Source unavailable | E41: Source unavailable
A43: FIXED-ASSET INTENSITY CONTEXT
A44: Property, Plant & Equipment | B44: ='Balance Sheet'!B25 | C44: ='Balance Sheet'!C25 | D44: ='Balance Sheet'!D25 | E44: ='Balance Sheet'!E25
A45: Depreciation & Amortisation | B45: ='Cash Flow Statement'!B23 | C45: ='Cash Flow Statement'!C23 | D45: ='Cash Flow Statement'!D23 | E45: ='Cash Flow Statement'!E23
A46: Average PP&E | B46: N/A | C46: =(B44+C44)/2 | D46: =(C44+D44)/2 | E46: =(D44+E44)/2
A47: PP&E Turnover | B47: N/A | C47: =IF(C46=0,NA(),'Condensed Financials'!C34/C46) | D47: =IF(D46=0,NA(),'Condensed Financials'!D34/D46) | E47: =IF(E46=0,NA(),'Condensed Financials'!E34/E46)
A48: PP&E Intensity | B48: N/A | C48: =IF('Condensed Financials'!C34=0,NA(),C46/'Condensed Financials'!C34) | D48: =IF('Condensed Financials'!D34=0,NA(),D46/'Condensed Financials'!D34) | E48: =IF('Condensed Financials'!E34=0,NA(),E46/'Condensed Financials'!E34)
A49: Change in PP&E | B49: N/A | C49: =C44-B44 | D49: =D44-C44 | E49: =E44-D44
A50: D&A / Revenue | B50: =IF('Condensed Financials'!B34=0,NA(),B45/'Condensed Financials'!B34) | C50: =IF('Condensed Financials'!C34=0,NA(),C45/'Condensed Financials'!C34) | D50: =IF('Condensed Financials'!D34=0,NA(),D45/'Condensed Financials'!D34) | E50: =IF('Condensed Financials'!E34=0,NA(),E45/'Condensed Financials'!E34)
A51: D&A / Average PP&E | B51: N/A | C51: =IF(C46=0,NA(),C45/C46) | D51: =IF(D46=0,NA(),D45/D46) | E51: =IF(E46=0,NA(),E45/E46)
A52: FIXED-ASSET INTENSITY CHECK | B52: N/A | C52: =IF(OR(ISNA(C47),ISNA(C48)),"N/A",IF(ABS(C47*C48-1)<0.0000001,"OK","CHECK")) | D52: =IF(OR(ISNA(D47),ISNA(D48)),"N/A",IF(ABS(D47*D48-1)<0.0000001,"OK","CHECK")) | E52: =IF(OR(ISNA(E47),ISNA(E48)),"N/A",IF(ABS(E47*E48-1)<0.0000001,"OK","CHECK"))
A54: LEASE LIABILITY CONTEXT
A55: Lease Liability | B55: ='Balance Sheet'!B17+'Balance Sheet'!B29 | C55: ='Balance Sheet'!C17+'Balance Sheet'!C29 | D55: ='Balance Sheet'!D17+'Balance Sheet'!D29 | E55: ='Balance Sheet'!E17+'Balance Sheet'!E29
A56: Lease Liability / Revenue | B56: =IF('Condensed Financials'!B34=0,NA(),B55/'Condensed Financials'!B34) | C56: =IF('Condensed Financials'!C34=0,NA(),C55/'Condensed Financials'!C34) | D56: =IF('Condensed Financials'!D34=0,NA(),D55/'Condensed Financials'!D34) | E56: =IF('Condensed Financials'!E34=0,NA(),E55/'Condensed Financials'!E34)
A57: Change in Lease Liability | B57: N/A | C57: =C55-B55 | D57: =D55-C55 | E57: =E55-D55
A58: Lease Liability Growth | B58: N/A | C58: =IF(B55=0,NA(),C55/B55-1) | D58: =IF(C55=0,NA(),D55/C55-1) | E58: =IF(D55=0,NA(),E55/D55-1)
A60: PP&E CAPEX CONTEXT
A61: Payments for Property, Plant & Equipment (reported) | B61: ='Cash Flow Statement'!B15 | C61: ='Cash Flow Statement'!C15 | D61: ='Cash Flow Statement'!D15 | E61: ='Cash Flow Statement'!E15
A62: PP&E Capex (−reported) | B62: =-B61 | C62: =-C61 | D62: =-D61 | E62: =-E61
A63: PP&E Capex / Revenue | B63: =IF('Condensed Financials'!B34=0,NA(),B62/'Condensed Financials'!B34) | C63: =IF('Condensed Financials'!C34=0,NA(),C62/'Condensed Financials'!C34) | D63: =IF('Condensed Financials'!D34=0,NA(),D62/'Condensed Financials'!D34) | E63: =IF('Condensed Financials'!E34=0,NA(),E62/'Condensed Financials'!E34)
A65: GOODWILL & INTANGIBLES CONTEXT
A66: Goodwill | B66: ='Balance Sheet'!B22 | C66: ='Balance Sheet'!C22 | D66: ='Balance Sheet'!D22 | E66: ='Balance Sheet'!E22
A67: Change in Goodwill | C67: =C66-B66 | D67: =D66-C66 | E67: =E66-D66
A68: Goodwill Growth | C68: =IF(B66=0,NA(),C66/B66-1) | D68: =IF(C66=0,NA(),D66/C66-1) | E68: =IF(D66=0,NA(),E66/D66-1)
A69: Average Goodwill | C69: =(B66+C66)/2 | D69: =(C66+D66)/2 | E69: =(D66+E66)/2
A70: Average Goodwill / Revenue | C70: =IF('Condensed Financials'!C34=0,NA(),C69/'Condensed Financials'!C34) | D70: =IF('Condensed Financials'!D34=0,NA(),D69/'Condensed Financials'!D34) | E70: =IF('Condensed Financials'!E34=0,NA(),E69/'Condensed Financials'!E34)
A71: Intangible Assets | B71: ='Balance Sheet'!B23 | C71: ='Balance Sheet'!C23 | D71: ='Balance Sheet'!D23 | E71: ='Balance Sheet'!E23
A72: Change in Intangible Assets | C72: =C71-B71 | D72: =D71-C71 | E72: =E71-D71
A73: Intangible Assets Growth | C73: =IF(B71=0,NA(),C71/B71-1) | D73: =IF(C71=0,NA(),D71/C71-1) | E73: =IF(D71=0,NA(),E71/D71-1)
A74: Average Intangible Assets | C74: =(B71+C71)/2 | D74: =(C71+D71)/2 | E74: =(D71+E71)/2
A75: Average Intangible Assets / Revenue | C75: =IF('Condensed Financials'!C34=0,NA(),C74/'Condensed Financials'!C34) | D75: =IF('Condensed Financials'!D34=0,NA(),D74/'Condensed Financials'!D34) | E75: =IF('Condensed Financials'!E34=0,NA(),E74/'Condensed Financials'!E34)
A76: Goodwill & Intangibles | B76: =B66+B71 | C76: =C66+C71 | D76: =D66+D71 | E76: =E66+E71
A77: Change in Goodwill & Intangibles | C77: =C76-B76 | D77: =D76-C76 | E77: =E76-D76
A78: Goodwill & Intangibles Growth | C78: =IF(B76=0,NA(),C76/B76-1) | D78: =IF(C76=0,NA(),D76/C76-1) | E78: =IF(D76=0,NA(),E76/D76-1)
A79: Average Goodwill & Intangibles | C79: =(B76+C76)/2 | D79: =(C76+D76)/2 | E79: =(D76+E76)/2
A80: Average Goodwill & Intangibles / Revenue | C80: =IF('Condensed Financials'!C34=0,NA(),C79/'Condensed Financials'!C34) | D80: =IF('Condensed Financials'!D34=0,NA(),D79/'Condensed Financials'!D34) | E80: =IF('Condensed Financials'!E34=0,NA(),E79/'Condensed Financials'!E34)

Sheet Accounting Judgment
A1: Accounting Judgment
A2: The supplied treatment is the model's reference treatment, not a universal accounting truth. Compare it with the listed alternative(s), choose the treatment you would defend, and explain the economic consequence.
A3: Choose a treatment in column F only. That choice drives the matching Condensed Financials classification and downstream historical schedules; leaving F blank uses the supplied reference treatment. Columns D:E are display context and must not be edited. Enter your rationale and economic consequence in G:H. Formula Check grades formula cells against the treatment currently selected in F and validates that the generated classification links remain intact; it does not grade the judgment response itself. Do not edit the linked Condensed Financials classification cell directly.
A4: Order | B4: Line item | C4: Topic | D4: Supplied reference treatment | E4: Alternative(s) to evaluate | F4: Treatment to defend | G4: Rationale | H4: Economic consequence
A5: 1 | B5: Current lease liabilities | C5: Lease liability operating vs financing | D5: Operating Long-Term Liability | E5: Financial Liability | F5: Operating Long-Term Liability | G5: The reference model keeps the liability in operating long-term liabilities under its current lease convention. Treating it as a financial liability is also defensible when the lease obligation is viewed as debt-like financing. | H5: Operating-liability treatment lowers NOLA/NOA; financial-liability treatment raises Net Debt by the same balance. Implied equity is unchanged from this classification switch alone, but RNOA versus FLEV/Spread interpretation changes.
A6: 2 | B6: Other current liabilities | C6: Other current liability: operating vs financial | D6: Operating Working Capital Liability | E6: Financial Liability | F6: Operating Working Capital Liability | G6: The residual current-liability concept proves balance-sheet side and horizon but not whether the balance is an operating working-capital liability or a financial liability in economic substance. | H6: Operating-WC-liability treatment lowers NOWC/NOA; financial-liability treatment raises Net Debt by the same balance. Implied equity is unchanged by the classification switch alone.
A7: 3 | B7: Other non-current assets | C7: Other non-current asset: operating vs financial | D7: Operating Long-Term Asset | E7: Financial Asset | F7: Operating Long-Term Asset | G7: The residual non-current-asset concept proves balance-sheet side and horizon but not whether the balance is an operating long-term asset or a financial asset in economic substance. | H7: Operating-LT treatment raises NOLA/NOA; financial-asset treatment lowers Net Debt by the same balance. Implied equity is unchanged by the classification switch alone.
A8: 4 | B8: Non-current lease liabilities | C8: Lease liability operating vs financing | D8: Operating Long-Term Liability | E8: Financial Liability | F8: Operating Long-Term Liability | G8: The reference model keeps the liability in operating long-term liabilities under its current lease convention. Treating it as a financial liability is also defensible when the lease obligation is viewed as debt-like financing. | H8: Operating-liability treatment lowers NOLA/NOA; financial-liability treatment raises Net Debt by the same balance. Implied equity is unchanged from this classification switch alone, but RNOA versus FLEV/Spread interpretation changes.
A9: 5 | B9: Other non-current liabilities | C9: Other non-current liability: operating vs financial | D9: Operating Long-Term Liability | E9: Financial Liability | F9: Operating Long-Term Liability | G9: The residual non-current-liability concept proves balance-sheet side and horizon but not whether the balance is an operating long-term liability or a financial liability in economic substance. | H9: Operating-LT-liability treatment lowers NOLA/NOA; financial-liability treatment raises Net Debt by the same balance. Implied equity is unchanged by the classification switch alone.

Sheet Earnings Quality
A1: lululemon athletica inc. — Earnings Quality
A2: Historical cash-conversion and accrual diagnostics. These are mechanical diagnostics, not an automatic quality score.
A4: Metric | B4: 44955 | C4: 45319 | D4: 45690 | E4: 46054
A5: Operating Cash Flow | B5: ='Cash Flow Statement'!B27 | C5: ='Cash Flow Statement'!C27 | D5: ='Cash Flow Statement'!D27 | E5: ='Cash Flow Statement'!E27
A6: Reported Net Income | B6: ='Condensed Financials'!B35 | C6: ='Condensed Financials'!C35 | D6: ='Condensed Financials'!D35 | E6: ='Condensed Financials'!E35
A7: Cash Conversion Ratio | B7: =IF(B6=0,NA(),B5/B6) | C7: =IF(C6=0,NA(),C5/C6) | D7: =IF(D6=0,NA(),D5/D6) | E7: =IF(E6=0,NA(),E5/E6)
A8: Total Accruals (Net Income - CFO) | B8: =B6-B5 | C8: =C6-C5 | D8: =D6-D5 | E8: =E6-E5
A10: Total Assets | B10: ='Balance Sheet'!B36 | C10: ='Balance Sheet'!C36 | D10: ='Balance Sheet'!D36 | E10: ='Balance Sheet'!E36
A11: Average Total Assets | C11: =(B10+C10)/2 | D11: =(C10+D10)/2 | E11: =(D10+E10)/2
A12: Accrual Ratio | C12: =IF(C11=0,NA(),C8/C11) | D12: =IF(D11=0,NA(),D8/D11) | E12: =IF(E11=0,NA(),E8/E11)
A14: EARNINGS QUALITY TREND DIAGNOSTICS
A15: Change in Operating Cash Flow | B15: N/A | C15: =C5-B5 | D15: =D5-C5 | E15: =E5-D5
A16: Change in Cash Conversion Ratio | B16: N/A | C16: =C7-B7 | D16: =D7-C7 | E16: =E7-D7
A17: Change in Total Accruals | B17: N/A | C17: =C8-B8 | D17: =D8-C8 | E17: =E8-D8
A18: Change in Accrual Ratio | B18: N/A | C18: N/A | D18: =D12-C12 | E18: =E12-D12
A19: EARNINGS QUALITY CHANGE CHECK | B19: N/A | C19: =IF(ABS(C17-((C6-B6)-C15))<0.01,"OK","CHECK") | D19: =IF(ABS(D17-((D6-C6)-D15))<0.01,"OK","CHECK") | E19: =IF(ABS(E17-((E6-D6)-E15))<0.01,"OK","CHECK")

Sheet Working Capital Analysis
A1: Working Capital Analysis
A2: Relate classified operating working capital to Revenue and identify how much incremental NOWC accompanies changes in sales.
A3: These are diagnostics, not automatic judgments. Positive Change in NOWC is an operating cash use; negative Change in NOWC is a release. Annual data alone does not prove seasonality or deterioration.
A5: Metric | B5: 44955 | C5: 45319 | D5: 45690 | E5: 46054
A6: Revenue | B6: ='Condensed Financials'!B34 | C6: ='Condensed Financials'!C34 | D6: ='Condensed Financials'!D34 | E6: ='Condensed Financials'!E34
A7: Operating Working Capital Assets | B7: ='Condensed Financials'!B44 | C7: ='Condensed Financials'!C44 | D7: ='Condensed Financials'!D44 | E7: ='Condensed Financials'!E44
A8: Operating Working Capital Liabilities | B8: ='Condensed Financials'!B45 | C8: ='Condensed Financials'!C45 | D8: ='Condensed Financials'!D45 | E8: ='Condensed Financials'!E45
A9: NOWC | B9: ='Condensed Financials'!B46 | C9: ='Condensed Financials'!C46 | D9: ='Condensed Financials'!D46 | E9: ='Condensed Financials'!E46
A11: OWCA / Revenue | B11: =IF(B6=0,NA(),B7/B6) | C11: =IF(C6=0,NA(),C7/C6) | D11: =IF(D6=0,NA(),D7/D6) | E11: =IF(E6=0,NA(),E7/E6)
A12: OWCL / Revenue | B12: =IF(B6=0,NA(),B8/B6) | C12: =IF(C6=0,NA(),C8/C6) | D12: =IF(D6=0,NA(),D8/D6) | E12: =IF(E6=0,NA(),E8/E6)
A13: NOWC / Revenue | B13: =IF(B6=0,NA(),B9/B6) | C13: =IF(C6=0,NA(),C9/C6) | D13: =IF(D6=0,NA(),D9/D6) | E13: =IF(E6=0,NA(),E9/E6)
A14: Change in Revenue | B14: N/A | C14: =C6-B6 | D14: =D6-C6 | E14: =E6-D6
A15: Change in NOWC | B15: N/A | C15: =C9-B9 | D15: =D9-C9 | E15: =E9-D9
A16: Incremental NOWC / Change in Revenue | B16: N/A | C16: =IF(C14=0,NA(),C15/C14) | D16: =IF(D14=0,NA(),D15/D14) | E16: =IF(E14=0,NA(),E15/E14)
A18: WORKING-CAPITAL DRIVER DECOMPOSITION
A19: Change in OWCA | B19: N/A | C19: =C7-B7 | D19: =D7-C7 | E19: =E7-D7
A20: Change in OWCL | B20: N/A | C20: =C8-B8 | D20: =D8-C8 | E20: =E8-D8
A21: Change in NOWC from Components | B21: N/A | C21: =C19-C20 | D21: =D19-D20 | E21: =E19-E20
A22: Incremental OWCA / Change in Revenue | B22: N/A | C22: =IF(C14=0,NA(),C19/C14) | D22: =IF(D14=0,NA(),D19/D14) | E22: =IF(E14=0,NA(),E19/E14)
A23: Incremental OWCL / Change in Revenue | B23: N/A | C23: =IF(C14=0,NA(),C20/C14) | D23: =IF(D14=0,NA(),D20/D14) | E23: =IF(E14=0,NA(),E20/E14)
A24: DRIVER DECOMPOSITION CHECK | B24: N/A | C24: =IF(ABS(C21-C15)<0.01,"OK","CHECK") | D24: =IF(ABS(D21-D15)<0.01,"OK","CHECK") | E24: =IF(ABS(E21-E15)<0.01,"OK","CHECK")

Sheet Per Share Analysis
A1: lululemon athletica inc. — Per Share Analysis
A2: Historical per-share diagnostics using supplied diluted weighted-average shares. Share counts are source inputs, not practice cells.
A4: Metric | B4: 44955 | C4: 45319 | D4: 45690 | E4: 46054
A5: Reported Net Income | B5: ='Condensed Financials'!B35 | C5: ='Condensed Financials'!C35 | D5: ='Condensed Financials'!D35 | E5: ='Condensed Financials'!E35
A6: NOPAT | B6: Source unavailable | C6: Source unavailable | D6: Source unavailable | E6: Source unavailable
A7: Diluted Weighted-Average Shares | B7: 128017 | C7: 127060 | D7: 123935 | E7: 119068
A8: Share Basis: Reported basis
A9: Diluted EPS (Comparable Basis) | B9: =IF(B7<=0,NA(),B5/B7) | C9: =IF(C7<=0,NA(),C5/C7) | D9: =IF(D7<=0,NA(),D5/D7) | E9: =IF(E7<=0,NA(),E5/E7)
A10: NOPAT per Diluted Share | B10: Source unavailable | C10: Source unavailable | D10: Source unavailable | E10: Source unavailable
A12: Change in Diluted EPS | B12: N/A | C12: =C9-B9 | D12: =D9-C9 | E12: =E9-D9
A13: Change in Diluted Weighted-Average Shares | B13: N/A | C13: =C7-B7 | D13: =D7-C7 | E13: =E7-D7
A15: DILUTED EPS CHANGE ATTRIBUTION
A16: Change in Per-Share Earnings Numerator | B16: N/A | C16: =C5-B5 | D16: =D5-C5 | E16: =E5-D5
A17: Earnings Effect on Change in Diluted EPS | B17: N/A | C17: =C16*((1/C7+1/B7)/2) | D17: =D16*((1/D7+1/C7)/2) | E17: =E16*((1/E7+1/D7)/2)
A18: Share-Count Effect on Change in Diluted EPS | B18: N/A | C18: =((1/C7)-(1/B7))*((C5+B5)/2) | D18: =((1/D7)-(1/C7))*((D5+C5)/2) | E18: =((1/E7)-(1/D7))*((E5+D5)/2)
A19: Diluted EPS Change from Drivers | B19: N/A | C19: =C17+C18 | D19: =D17+D18 | E19: =E17+E18
A20: DILUTED EPS CHANGE ATTRIBUTION CHECK | B20: N/A | C20: =IF(ABS(C19-C12)<0.0000001,"OK","CHECK") | D20: =IF(ABS(D19-D12)<0.0000001,"OK","CHECK") | E20: =IF(ABS(E19-E12)<0.0000001,"OK","CHECK")

Sheet Model_Bear
A1: Deferred from historical-only v1

Sheet Model_Base
A1: Deferred from historical-only v1

Sheet Model_Bull
A1: Deferred from historical-only v1

Sheet Scenario_Summary
A1: Deferred from historical-only v1

Sheet _ComponentMap
A1: id | B1: order | C1: title | D1: short_hint | E1: semantic_key | F1: category | G1: tab | H1: cell | I1: formula | J1: expected_value | K1: tolerance | L1: depends_on | M1: hints | N1: related_cells | O1: status | P1: family_id | Q1: family_order | R1: period_index | S1: period_end
A2: revenue_link__20230129 | B2: 1 | C2: Revenue historical source link | D2: Link Revenue from the Income Statement into Condensed Financials. | E2: condensed.revenue_link.2023-01-29 | F2: accounting | G2: Condensed Financials | H2: B34 | I2: ='Income Statement'!B19 | J2: 8110518 | K2: 0.01 | M2: Pull the Revenue line from the Income Statement for the same fiscal period. | O2: pending | P2: revenue_link | Q2: 1 | R2: 0 | S2: 2023-01-29
A3: revenue_link__20240128 | B3: 2 | C3: Revenue historical source link | D3: Link Revenue from the Income Statement into Condensed Financials. | E3: condensed.revenue_link.2024-01-28 | F3: accounting | G3: Condensed Financials | H3: C34 | I3: ='Income Statement'!C19 | J3: 9619278 | K3: 0.01 | M3: Pull the Revenue line from the Income Statement for the same fiscal period. | O3: pending | P3: revenue_link | Q3: 1 | R3: 1 | S3: 2024-01-28
A4: revenue_link__20250202 | B4: 3 | C4: Revenue historical source link | D4: Link Revenue from the Income Statement into Condensed Financials. | E4: condensed.revenue_link.2025-02-02 | F4: accounting | G4: Condensed Financials | H4: D34 | I4: ='Income Statement'!D19 | J4: 10588126 | K4: 0.01 | M4: Pull the Revenue line from the Income Statement for the same fiscal period. | O4: pending | P4: revenue_link | Q4: 1 | R4: 2 | S4: 2025-02-02
A5: revenue_link__20260201 | B5: 4 | C5: Revenue historical source link | D5: Link Revenue from the Income Statement into Condensed Financials. | E5: condensed.revenue_link.2026-02-01 | F5: accounting | G5: Condensed Financials | H5: E34 | I5: ='Income Statement'!E19 | J5: 11102600 | K5: 0.01 | M5: Pull the Revenue line from the Income Statement for the same fiscal period. | O5: pending | P5: revenue_link | Q5: 1 | R5: 3 | S5: 2026-02-01
A6: net_income_link__20230129 | B6: 5 | C6: Net Income historical source link | D6: Link Net Income from the Income Statement into Condensed Financials. | E6: condensed.net_income_link.2023-01-29 | F6: accounting | G6: Condensed Financials | H6: B35 | I6: ='Income Statement'!B18 | J6: 854800 | K6: 0.01 | M6: Pull Net Income from the Income Statement for the same fiscal period. | O6: pending | P6: net_income_link | Q6: 2 | R6: 0 | S6: 2023-01-29
A7: net_income_link__20240128 | B7: 6 | C7: Net Income historical source link | D7: Link Net Income from the Income Statement into Condensed Financials. | E7: condensed.net_income_link.2024-01-28 | F7: accounting | G7: Condensed Financials | H7: C35 | I7: ='Income Statement'!C18 | J7: 1550190 | K7: 0.01 | M7: Pull Net Income from the Income Statement for the same fiscal period. | O7: pending | P7: net_income_link | Q7: 2 | R7: 1 | S7: 2024-01-28
A8: net_income_link__20250202 | B8: 7 | C8: Net Income historical source link | D8: Link Net Income from the Income Statement into Condensed Financials. | E8: condensed.net_income_link.2025-02-02 | F8: accounting | G8: Condensed Financials | H8: D35 | I8: ='Income Statement'!D18 | J8: 1814616 | K8: 0.01 | M8: Pull Net Income from the Income Statement for the same fiscal period. | O8: pending | P8: net_income_link | Q8: 2 | R8: 2 | S8: 2025-02-02
A9: net_income_link__20260201 | B9: 8 | C9: Net Income historical source link | D9: Link Net Income from the Income Statement into Condensed Financials. | E9: condensed.net_income_link.2026-02-01 | F9: accounting | G9: Condensed Financials | H9: E35 | I9: ='Income Statement'!E18 | J9: 1579183 | K9: 0.01 | M9: Pull Net Income from the Income Statement for the same fiscal period. | O9: pending | P9: net_income_link | Q9: 2 | R9: 3 | S9: 2026-02-01
A10: effective_tax_rate_fy__20230129 | B10: 9 | C10: Effective tax rate | D10: Relate tax expense to pretax income using the model's sign convention. | E10: condensed.effective_tax_rate.2023-01-29 | F10: accounting | G10: Condensed Financials | H10: B38 | I10: =IF(B36=0,NA(),-B37/B36) | J10: -0.35853324 | K10: 0.01 | M10: Effective tax rate uses pretax income in the denominator.|Preserve the model's sign convention for tax expense.|A zero Pretax Income makes Effective Tax Rate undefined (#N/A). | O10: pending | P10: effective_tax_rate_fy | Q10: 3 | R10: 0 | S10: 2023-01-29
A11: effective_tax_rate_fy__20240128 | B11: 10 | C11: Effective tax rate | D11: Relate tax expense to pretax income using the model's sign convention. | E11: condensed.effective_tax_rate.2024-01-28 | F11: accounting | G11: Condensed Financials | H11: C38 | I11: =IF(C36=0,NA(),-C37/C36) | J11: -0.28750974 | K11: 0.01 | M11: Effective tax rate uses pretax income in the denominator.|Preserve the model's sign convention for tax expense.|A zero Pretax Income makes Effective Tax Rate undefined (#N/A). | O11: pending | P11: effective_tax_rate_fy | Q11: 3 | R11: 1 | S11: 2024-01-28
A12: effective_tax_rate_fy__20250202 | B12: 11 | C12: Effective tax rate | D12: Relate tax expense to pretax income using the model's sign convention. | E12: condensed.effective_tax_rate.2025-02-02 | F12: accounting | G12: Condensed Financials | H12: D38 | I12: =IF(D36=0,NA(),-D37/D36) | J12: -0.29558938 | K12: 0.01 | M12: Effective tax rate uses pretax income in the denominator.|Preserve the model's sign convention for tax expense.|A zero Pretax Income makes Effective Tax Rate undefined (#N/A). | O12: pending | P12: effective_tax_rate_fy | Q12: 3 | R12: 2 | S12: 2025-02-02
A13: effective_tax_rate_fy__20260201 | B13: 12 | C13: Effective tax rate | D13: Relate tax expense to pretax income using the model's sign convention. | E13: condensed.effective_tax_rate.2026-02-01 | F13: accounting | G13: Condensed Financials | H13: E38 | I13: =IF(E36=0,NA(),-E37/E36) | J13: -0.29468232 | K13: 0.01 | M13: Effective tax rate uses pretax income in the denominator.|Preserve the model's sign convention for tax expense.|A zero Pretax Income makes Effective Tax Rate undefined (#N/A). | O13: pending | P13: effective_tax_rate_fy | Q13: 3 | R13: 3 | S13: 2026-02-01
A14: owca_agg__20230129 | B14: 25 | C14: Operating working capital assets | D14: Aggregate the classified balance-sheet detail with the classification column. | E14: condensed.owca.2023-01-29 | F14: accounting | G14: Condensed Financials | H14: B44 | I14: =SUMIF($B$6:$B$31,"Operating Working Capital Asset",C$6:C$31) | J14: 2004586 | K14: 0.01 | M14: Use SUMIF over the classification column for Operating Working Capital Asset. | O14: pending | P14: owca_agg | Q14: 7 | R14: 0 | S14: 2023-01-29
A15: owca_agg__20240128 | B15: 26 | C15: Operating working capital assets | D15: Aggregate the classified balance-sheet detail with the classification column. | E15: condensed.owca.2024-01-28 | F15: accounting | G15: Condensed Financials | H15: C44 | I15: =SUMIF($B$6:$B$31,"Operating Working Capital Asset",D$6:D$31) | J15: 1816606 | K15: 0.01 | M15: Use SUMIF over the classification column for Operating Working Capital Asset. | O15: pending | P15: owca_agg | Q15: 7 | R15: 1 | S15: 2024-01-28
A16: owca_agg__20250202 | B16: 27 | C16: Operating working capital assets | D16: Aggregate the classified balance-sheet detail with the classification column. | E16: condensed.owca.2025-02-02 | F16: accounting | G16: Condensed Financials | H16: D44 | I16: =SUMIF($B$6:$B$31,"Operating Working Capital Asset",E$6:E$31) | J16: 1995966 | K16: 0.01 | M16: Use SUMIF over the classification column for Operating Working Capital Asset. | O16: pending | P16: owca_agg | Q16: 7 | R16: 2 | S16: 2025-02-02
A17: owca_agg__20260201 | B17: 28 | C17: Operating working capital assets | D17: Aggregate the classified balance-sheet detail with the classification column. | E17: condensed.owca.2026-02-01 | F17: accounting | G17: Condensed Financials | H17: E44 | I17: =SUMIF($B$6:$B$31,"Operating Working Capital Asset",F$6:F$31) | J17: 2455499 | K17: 0.01 | M17: Use SUMIF over the classification column for Operating Working Capital Asset. | O17: pending | P17: owca_agg | Q17: 7 | R17: 3 | S17: 2026-02-01
A18: owcl_agg__20230129 | B18: 29 | C18: Operating working capital liabilities | D18: Aggregate the classified balance-sheet detail with the classification column. | E18: condensed.owcl.2023-01-29 | F18: accounting | G18: Condensed Financials | H18: B45 | I18: =SUMIF($B$6:$B$31,"Operating Working Capital Liability",C$6:C$31) | J18: 1312781 | K18: 0.01 | M18: Use SUMIF over the classification column for Operating Working Capital Liability. | O18: pending | P18: owcl_agg | Q18: 8 | R18: 0 | S18: 2023-01-29
A19: owcl_agg__20240128 | B19: 30 | C19: Operating working capital liabilities | D19: Aggregate the classified balance-sheet detail with the classification column. | E19: condensed.owcl.2024-01-28 | F19: accounting | G19: Condensed Financials | H19: C45 | I19: =SUMIF($B$6:$B$31,"Operating Working Capital Liability",D$6:D$31) | J19: 1397855 | K19: 0.01 | M19: Use SUMIF over the classification column for Operating Working Capital Liability. | O19: pending | P19: owcl_agg | Q19: 8 | R19: 1 | S19: 2024-01-28
A20: owcl_agg__20250202 | B20: 31 | C20: Operating working capital liabilities | D20: Aggregate the classified balance-sheet detail with the classification column. | E20: condensed.owcl.2025-02-02 | F20: accounting | G20: Condensed Financials | H20: D45 | I20: =SUMIF($B$6:$B$31,"Operating Working Capital Liability",E$6:E$31) | J20: 1564476 | K20: 0.01 | M20: Use SUMIF over the classification column for Operating Working Capital Liability. | O20: pending | P20: owcl_agg | Q20: 8 | R20: 2 | S20: 2025-02-02
A21: owcl_agg__20260201 | B21: 32 | C21: Operating working capital liabilities | D21: Aggregate the classified balance-sheet detail with the classification column. | E21: condensed.owcl.2026-02-01 | F21: accounting | G21: Condensed Financials | H21: E45 | I21: =SUMIF($B$6:$B$31,"Operating Working Capital Liability",F$6:F$31) | J21: 1588824 | K21: 0.01 | M21: Use SUMIF over the classification column for Operating Working Capital Liability. | O21: pending | P21: owcl_agg | Q21: 8 | R21: 3 | S21: 2026-02-01
A22: nowc_agg__20230129 | B22: 33 | C22: Net Operating Working Capital (NOWC) | D22: Sum operating WC assets minus operating WC liabilities. | E22: condensed.nowc.2023-01-29 | F22: accounting | G22: Condensed Financials | H22: B46 | I22: =B44-B45 | J22: 691805 | K22: 0.01 | L22: owca_agg__20230129,owcl_agg__20230129 | M22: Use SUMIF over the classification column for 'Operating Working Capital Asset'.|Subtract SUMIF for 'Operating Working Capital Liability'.|NOWC = Op. WC Assets − Op. WC Liabilities. | O22: pending | P22: nowc_agg | Q22: 9 | R22: 0 | S22: 2023-01-29
A23: nowc_agg__20240128 | B23: 34 | C23: Net Operating Working Capital (NOWC) | D23: Sum operating WC assets minus operating WC liabilities. | E23: condensed.nowc.2024-01-28 | F23: accounting | G23: Condensed Financials | H23: C46 | I23: =C44-C45 | J23: 418751 | K23: 0.01 | L23: owca_agg__20240128,owcl_agg__20240128 | M23: Use SUMIF over the classification column for 'Operating Working Capital Asset'.|Subtract SUMIF for 'Operating Working Capital Liability'.|NOWC = Op. WC Assets − Op. WC Liabilities. | O23: pending | P23: nowc_agg | Q23: 9 | R23: 1 | S23: 2024-01-28
A24: nowc_agg__20250202 | B24: 35 | C24: Net Operating Working Capital (NOWC) | D24: Sum operating WC assets minus operating WC liabilities. | E24: condensed.nowc.2025-02-02 | F24: accounting | G24: Condensed Financials | H24: D46 | I24: =D44-D45 | J24: 431490 | K24: 0.01 | L24: owca_agg__20250202,owcl_agg__20250202 | M24: Use SUMIF over the classification column for 'Operating Working Capital Asset'.|Subtract SUMIF for 'Operating Working Capital Liability'.|NOWC = Op. WC Assets − Op. WC Liabilities. | O24: pending | P24: nowc_agg | Q24: 9 | R24: 2 | S24: 2025-02-02
A25: nowc_agg__20260201 | B25: 36 | C25: Net Operating Working Capital (NOWC) | D25: Sum operating WC assets minus operating WC liabilities. | E25: condensed.nowc.2026-02-01 | F25: accounting | G25: Condensed Financials | H25: E46 | I25: =E44-E45 | J25: 866675 | K25: 0.01 | L25: owca_agg__20260201,owcl_agg__20260201 | M25: Use SUMIF over the classification column for 'Operating Working Capital Asset'.|Subtract SUMIF for 'Operating Working Capital Liability'.|NOWC = Op. WC Assets − Op. WC Liabilities. | O25: pending | P25: nowc_agg | Q25: 9 | R25: 3 | S25: 2026-02-01
A26: olta_agg__20230129 | B26: 37 | C26: Operating long-term assets | D26: Aggregate the classified balance-sheet detail with the classification column. | E26: condensed.olta.2023-01-29 | F26: accounting | G26: Condensed Financials | H26: B47 | I26: =SUMIF($B$6:$B$31,"Operating Long-Term Asset",C$6:C$31) | J26: 2447585 | K26: 0.01 | M26: Use SUMIF over the classification column for Operating Long-Term Asset. | O26: pending | P26: olta_agg | Q26: 10 | R26: 0 | S26: 2023-01-29
A27: olta_agg__20240128 | B27: 38 | C27: Operating long-term assets | D27: Aggregate the classified balance-sheet detail with the classification column. | E27: condensed.olta.2024-01-28 | F27: accounting | G27: Condensed Financials | H27: C47 | I27: =SUMIF($B$6:$B$31,"Operating Long-Term Asset",D$6:D$31) | J27: 3031364 | K27: 0.01 | M27: Use SUMIF over the classification column for Operating Long-Term Asset. | O27: pending | P27: olta_agg | Q27: 10 | R27: 1 | S27: 2024-01-28
A28: olta_agg__20250202 | B28: 39 | C28: Operating long-term assets | D28: Aggregate the classified balance-sheet detail with the classification column. | E28: condensed.olta.2025-02-02 | F28: accounting | G28: Condensed Financials | H28: D47 | I28: =SUMIF($B$6:$B$31,"Operating Long-Term Asset",E$6:E$31) | J28: 3622990 | K28: 0.01 | M28: Use SUMIF over the classification column for Operating Long-Term Asset. | O28: pending | P28: olta_agg | Q28: 10 | R28: 2 | S28: 2025-02-02
A29: olta_agg__20260201 | B29: 40 | C29: Operating long-term assets | D29: Aggregate the classified balance-sheet detail with the classification column. | E29: condensed.olta.2026-02-01 | F29: accounting | G29: Condensed Financials | H29: E47 | I29: =SUMIF($B$6:$B$31,"Operating Long-Term Asset",F$6:F$31) | J29: 4194042 | K29: 0.01 | M29: Use SUMIF over the classification column for Operating Long-Term Asset. | O29: pending | P29: olta_agg | Q29: 10 | R29: 3 | S29: 2026-02-01
A30: oltl_agg__20230129 | B30: 41 | C30: Operating long-term liabilities | D30: Aggregate the classified balance-sheet detail with the classification column. | E30: condensed.oltl.2023-01-29 | F30: accounting | G30: Condensed Financials | H30: B48 | I30: =SUMIF($B$6:$B$31,"Operating Long-Term Liability",C$6:C$31) | J30: 1145458 | K30: 0.01 | M30: Use SUMIF over the classification column for Operating Long-Term Liability. | O30: pending | P30: oltl_agg | Q30: 11 | R30: 0 | S30: 2023-01-29
A31: oltl_agg__20240128 | B31: 42 | C31: Operating long-term liabilities | D31: Aggregate the classified balance-sheet detail with the classification column. | E31: condensed.oltl.2024-01-28 | F31: accounting | G31: Condensed Financials | H31: C48 | I31: =SUMIF($B$6:$B$31,"Operating Long-Term Liability",D$6:D$31) | J31: 1462005 | K31: 0.01 | M31: Use SUMIF over the classification column for Operating Long-Term Liability. | O31: pending | P31: oltl_agg | Q31: 11 | R31: 1 | S31: 2024-01-28
A32: oltl_agg__20250202 | B32: 43 | C32: Operating long-term liabilities | D32: Aggregate the classified balance-sheet detail with the classification column. | E32: condensed.oltl.2025-02-02 | F32: accounting | G32: Condensed Financials | H32: D48 | I32: =SUMIF($B$6:$B$31,"Operating Long-Term Liability",E$6:E$31) | J32: 1714769 | K32: 0.01 | M32: Use SUMIF over the classification column for Operating Long-Term Liability. | O32: pending | P32: oltl_agg | Q32: 11 | R32: 2 | S32: 2025-02-02
A33: oltl_agg__20260201 | B33: 44 | C33: Operating long-term liabilities | D33: Aggregate the classified balance-sheet detail with the classification column. | E33: condensed.oltl.2026-02-01 | F33: accounting | G33: Condensed Financials | H33: E48 | I33: =SUMIF($B$6:$B$31,"Operating Long-Term Liability",F$6:F$31) | J33: 1906079 | K33: 0.01 | M33: Use SUMIF over the classification column for Operating Long-Term Liability. | O33: pending | P33: oltl_agg | Q33: 11 | R33: 3 | S33: 2026-02-01
A34: nola_agg__20230129 | B34: 45 | C34: Net operating long-term assets (NOLA) | D34: Operating long-term assets less operating long-term liabilities. | E34: condensed.nola.2023-01-29 | F34: accounting | G34: Condensed Financials | H34: B49 | I34: =B47-B48 | J34: 1302127 | K34: 0.01 | L34: olta_agg__20230129,oltl_agg__20230129 | M34: NOLA = Operating LT Assets − Operating LT Liabilities. | O34: pending | P34: nola_agg | Q34: 12 | R34: 0 | S34: 2023-01-29
A35: nola_agg__20240128 | B35: 46 | C35: Net operating long-term assets (NOLA) | D35: Operating long-term assets less operating long-term liabilities. | E35: condensed.nola.2024-01-28 | F35: accounting | G35: Condensed Financials | H35: C49 | I35: =C47-C48 | J35: 1569359 | K35: 0.01 | L35: olta_agg__20240128,oltl_agg__20240128 | M35: NOLA = Operating LT Assets − Operating LT Liabilities. | O35: pending | P35: nola_agg | Q35: 12 | R35: 1 | S35: 2024-01-28
A36: nola_agg__20250202 | B36: 47 | C36: Net operating long-term assets (NOLA) | D36: Operating long-term assets less operating long-term liabilities. | E36: condensed.nola.2025-02-02 | F36: accounting | G36: Condensed Financials | H36: D49 | I36: =D47-D48 | J36: 1908221 | K36: 0.01 | L36: olta_agg__20250202,oltl_agg__20250202 | M36: NOLA = Operating LT Assets − Operating LT Liabilities. | O36: pending | P36: nola_agg | Q36: 12 | R36: 2 | S36: 2025-02-02
A37: nola_agg__20260201 | B37: 48 | C37: Net operating long-term assets (NOLA) | D37: Operating long-term assets less operating long-term liabilities. | E37: condensed.nola.2026-02-01 | F37: accounting | G37: Condensed Financials | H37: E49 | I37: =E47-E48 | J37: 2287963 | K37: 0.01 | L37: olta_agg__20260201,oltl_agg__20260201 | M37: NOLA = Operating LT Assets − Operating LT Liabilities. | O37: pending | P37: nola_agg | Q37: 12 | R37: 3 | S37: 2026-02-01
A38: noa_agg__20230129 | B38: 49 | C38: Net Operating Assets (NOA) | D38: NOWC plus net operating long-term assets. | E38: condensed.noa.2023-01-29 | F38: accounting | G38: Condensed Financials | H38: B50 | I38: =B46+B49 | J38: 1993932 | K38: 0.01 | L38: nowc_agg__20230129,nola_agg__20230129 | M38: Net Operating LT Assets = Op. LT Assets − Op. LT Liabilities (SUMIF).|NOA = NOWC + Net Operating LT Assets. | O38: pending | P38: noa_agg | Q38: 13 | R38: 0 | S38: 2023-01-29
A39: noa_agg__20240128 | B39: 50 | C39: Net Operating Assets (NOA) | D39: NOWC plus net operating long-term assets. | E39: condensed.noa.2024-01-28 | F39: accounting | G39: Condensed Financials | H39: C50 | I39: =C46+C49 | J39: 1988110 | K39: 0.01 | L39: nowc_agg__20240128,nola_agg__20240128 | M39: Net Operating LT Assets = Op. LT Assets − Op. LT Liabilities (SUMIF).|NOA = NOWC + Net Operating LT Assets. | O39: pending | P39: noa_agg | Q39: 13 | R39: 1 | S39: 2024-01-28
A40: noa_agg__20250202 | B40: 51 | C40: Net Operating Assets (NOA) | D40: NOWC plus net operating long-term assets. | E40: condensed.noa.2025-02-02 | F40: accounting | G40: Condensed Financials | H40: D50 | I40: =D46+D49 | J40: 2339711 | K40: 0.01 | L40: nowc_agg__20250202,nola_agg__20250202 | M40: Net Operating LT Assets = Op. LT Assets − Op. LT Liabilities (SUMIF).|NOA = NOWC + Net Operating LT Assets. | O40: pending | P40: noa_agg | Q40: 13 | R40: 2 | S40: 2025-02-02
A41: noa_agg__20260201 | B41: 52 | C41: Net Operating Assets (NOA) | D41: NOWC plus net operating long-term assets. | E41: condensed.noa.2026-02-01 | F41: accounting | G41: Condensed Financials | H41: E50 | I41: =E46+E49 | J41: 3154638 | K41: 0.01 | L41: nowc_agg__20260201,nola_agg__20260201 | M41: Net Operating LT Assets = Op. LT Assets − Op. LT Liabilities (SUMIF).|NOA = NOWC + Net Operating LT Assets. | O41: pending | P41: noa_agg | Q41: 13 | R41: 3 | S41: 2026-02-01
A42: financial_assets_agg__20230129 | B42: 53 | C42: Financial assets | D42: Aggregate the classified balance-sheet detail with the classification column. | E42: condensed.financial_assets.2023-01-29 | F42: accounting | G42: Condensed Financials | H42: B51 | I42: =SUMIF($B$6:$B$31,"Financial Asset",C$6:C$31) | J42: 1154867 | K42: 0.01 | M42: Use SUMIF over the classification column for Financial Asset. | O42: pending | P42: financial_assets_agg | Q42: 14 | R42: 0 | S42: 2023-01-29
A43: financial_assets_agg__20240128 | B43: 54 | C43: Financial assets | D43: Aggregate the classified balance-sheet detail with the classification column. | E43: condensed.financial_assets.2024-01-28 | F43: accounting | G43: Condensed Financials | H43: C51 | I43: =SUMIF($B$6:$B$31,"Financial Asset",D$6:D$31) | J43: 2243971 | K43: 0.01 | M43: Use SUMIF over the classification column for Financial Asset. | O43: pending | P43: financial_assets_agg | Q43: 14 | R43: 1 | S43: 2024-01-28
A44: financial_assets_agg__20250202 | B44: 55 | C44: Financial assets | D44: Aggregate the classified balance-sheet detail with the classification column. | E44: condensed.financial_assets.2025-02-02 | F44: accounting | G44: Condensed Financials | H44: D51 | I44: =SUMIF($B$6:$B$31,"Financial Asset",E$6:E$31) | J44: 1984336 | K44: 0.01 | M44: Use SUMIF over the classification column for Financial Asset. | O44: pending | P44: financial_assets_agg | Q44: 14 | R44: 2 | S44: 2025-02-02
A45: financial_assets_agg__20260201 | B45: 56 | C45: Financial assets | D45: Aggregate the classified balance-sheet detail with the classification column. | E45: condensed.financial_assets.2026-02-01 | F45: accounting | G45: Condensed Financials | H45: E51 | I45: =SUMIF($B$6:$B$31,"Financial Asset",F$6:F$31) | J45: 1807202 | K45: 0.01 | M45: Use SUMIF over the classification column for Financial Asset. | O45: pending | P45: financial_assets_agg | Q45: 14 | R45: 3 | S45: 2026-02-01
A46: financial_liabilities_agg__20230129 | B46: 57 | C46: Financial liabilities | D46: Aggregate the classified balance-sheet detail with the classification column. | E46: condensed.financial_liabilities.2023-01-29 | F46: accounting | G46: Condensed Financials | H46: B52 | I46: =SUMIF($B$6:$B$31,"Financial Liability",C$6:C$31) | J46: 0 | K46: 0.01 | M46: Use SUMIF over the classification column for Financial Liability. | O46: pending | P46: financial_liabilities_agg | Q46: 15 | R46: 0 | S46: 2023-01-29
A47: financial_liabilities_agg__20240128 | B47: 58 | C47: Financial liabilities | D47: Aggregate the classified balance-sheet detail with the classification column. | E47: condensed.financial_liabilities.2024-01-28 | F47: accounting | G47: Condensed Financials | H47: C52 | I47: =SUMIF($B$6:$B$31,"Financial Liability",D$6:D$31) | J47: 0 | K47: 0.01 | M47: Use SUMIF over the classification column for Financial Liability. | O47: pending | P47: financial_liabilities_agg | Q47: 15 | R47: 1 | S47: 2024-01-28
A48: financial_liabilities_agg__20250202 | B48: 59 | C48: Financial liabilities | D48: Aggregate the classified balance-sheet detail with the classification column. | E48: condensed.financial_liabilities.2025-02-02 | F48: accounting | G48: Condensed Financials | H48: D52 | I48: =SUMIF($B$6:$B$31,"Financial Liability",E$6:E$31) | J48: 0 | K48: 0.01 | M48: Use SUMIF over the classification column for Financial Liability. | O48: pending | P48: financial_liabilities_agg | Q48: 15 | R48: 2 | S48: 2025-02-02
A49: financial_liabilities_agg__20260201 | B49: 60 | C49: Financial liabilities | D49: Aggregate the classified balance-sheet detail with the classification column. | E49: condensed.financial_liabilities.2026-02-01 | F49: accounting | G49: Condensed Financials | H49: E52 | I49: =SUMIF($B$6:$B$31,"Financial Liability",F$6:F$31) | J49: 0 | K49: 0.01 | M49: Use SUMIF over the classification column for Financial Liability. | O49: pending | P49: financial_liabilities_agg | Q49: 15 | R49: 3 | S49: 2026-02-01
A50: net_debt__20230129 | B50: 61 | C50: Net Debt | D50: Financial liabilities minus financial assets. | E50: condensed.net_debt.2023-01-29 | F50: accounting | G50: Condensed Financials | H50: B53 | I50: =B52-B51 | J50: -1154867 | K50: 0.01 | L50: financial_assets_agg__20230129,financial_liabilities_agg__20230129 | M50: Net Debt = SUMIF(Financial Liability) − SUMIF(Financial Asset).|Positive net debt means the firm carries net financial obligations. | O50: pending | P50: net_debt | Q50: 16 | R50: 0 | S50: 2023-01-29
A51: net_debt__20240128 | B51: 62 | C51: Net Debt | D51: Financial liabilities minus financial assets. | E51: condensed.net_debt.2024-01-28 | F51: accounting | G51: Condensed Financials | H51: C53 | I51: =C52-C51 | J51: -2243971 | K51: 0.01 | L51: financial_assets_agg__20240128,financial_liabilities_agg__20240128 | M51: Net Debt = SUMIF(Financial Liability) − SUMIF(Financial Asset).|Positive net debt means the firm carries net financial obligations. | O51: pending | P51: net_debt | Q51: 16 | R51: 1 | S51: 2024-01-28
A52: net_debt__20250202 | B52: 63 | C52: Net Debt | D52: Financial liabilities minus financial assets. | E52: condensed.net_debt.2025-02-02 | F52: accounting | G52: Condensed Financials | H52: D53 | I52: =D52-D51 | J52: -1984336 | K52: 0.01 | L52: financial_assets_agg__20250202,financial_liabilities_agg__20250202 | M52: Net Debt = SUMIF(Financial Liability) − SUMIF(Financial Asset).|Positive net debt means the firm carries net financial obligations. | O52: pending | P52: net_debt | Q52: 16 | R52: 2 | S52: 2025-02-02
A53: net_debt__20260201 | B53: 64 | C53: Net Debt | D53: Financial liabilities minus financial assets. | E53: condensed.net_debt.2026-02-01 | F53: accounting | G53: Condensed Financials | H53: E53 | I53: =E52-E51 | J53: -1807202 | K53: 0.01 | L53: financial_assets_agg__20260201,financial_liabilities_agg__20260201 | M53: Net Debt = SUMIF(Financial Liability) − SUMIF(Financial Asset).|Positive net debt means the firm carries net financial obligations. | O53: pending | P53: net_debt | Q53: 16 | R53: 3 | S53: 2026-02-01
A54: equity_reformulated_fy__20230129 | B54: 65 | C54: Reformulated equity | D54: Use the operating/financing identity linking NOA, Net Debt, and Equity. | E54: condensed.equity.2023-01-29 | F54: accounting | G54: Condensed Financials | H54: B54 | I54: =B50-B53 | J54: 3148799 | K54: 0.01 | L54: noa_agg__20230129,net_debt__20230129 | M54: Reformulated Equity = NOA − Net Debt.|This identity must reconcile to reported equity within tolerance. | O54: pending | P54: equity_reformulated_fy | Q54: 17 | R54: 0 | S54: 2023-01-29
A55: equity_reformulated_fy__20240128 | B55: 66 | C55: Reformulated equity | D55: Use the operating/financing identity linking NOA, Net Debt, and Equity. | E55: condensed.equity.2024-01-28 | F55: accounting | G55: Condensed Financials | H55: C54 | I55: =C50-C53 | J55: 4232081 | K55: 0.01 | L55: noa_agg__20240128,net_debt__20240128 | M55: Reformulated Equity = NOA − Net Debt.|This identity must reconcile to reported equity within tolerance. | O55: pending | P55: equity_reformulated_fy | Q55: 17 | R55: 1 | S55: 2024-01-28
A56: operating_cash_flow_link__20230129 | B56: 66 | C56: Operating cash flow historical source link | D56: Link net cash from operating activities for the same fiscal period. | E56: quality.operating_cash_flow.2023-01-29 | F56: earnings_quality | G56: Earnings Quality | H56: B5 | I56: ='Cash Flow Statement'!B27 | J56: 966463 | K56: 0.01 | M56: Pull final net cash from operating activities for the same period. | O56: pending | P56: operating_cash_flow_link | Q56: 30 | R56: 0 | S56: 2023-01-29
A57: equity_reformulated_fy__20250202 | B57: 67 | C57: Reformulated equity | D57: Use the operating/financing identity linking NOA, Net Debt, and Equity. | E57: condensed.equity.2025-02-02 | F57: accounting | G57: Condensed Financials | H57: D54 | I57: =D50-D53 | J57: 4324047 | K57: 0.01 | L57: noa_agg__20250202,net_debt__20250202 | M57: Reformulated Equity = NOA − Net Debt.|This identity must reconcile to reported equity within tolerance. | O57: pending | P57: equity_reformulated_fy | Q57: 17 | R57: 2 | S57: 2025-02-02
A58: operating_cash_flow_link__20240128 | B58: 67 | C58: Operating cash flow historical source link | D58: Link net cash from operating activities for the same fiscal period. | E58: quality.operating_cash_flow.2024-01-28 | F58: earnings_quality | G58: Earnings Quality | H58: C5 | I58: ='Cash Flow Statement'!C27 | J58: 2296164 | K58: 0.01 | M58: Pull final net cash from operating activities for the same period. | O58: pending | P58: operating_cash_flow_link | Q58: 30 | R58: 1 | S58: 2024-01-28
A59: equity_reformulated_fy__20260201 | B59: 68 | C59: Reformulated equity | D59: Use the operating/financing identity linking NOA, Net Debt, and Equity. | E59: condensed.equity.2026-02-01 | F59: accounting | G59: Condensed Financials | H59: E54 | I59: =E50-E53 | J59: 4961840 | K59: 0.01 | L59: noa_agg__20260201,net_debt__20260201 | M59: Reformulated Equity = NOA − Net Debt.|This identity must reconcile to reported equity within tolerance. | O59: pending | P59: equity_reformulated_fy | Q59: 17 | R59: 3 | S59: 2026-02-01
A60: operating_cash_flow_link__20250202 | B60: 68 | C60: Operating cash flow historical source link | D60: Link net cash from operating activities for the same fiscal period. | E60: quality.operating_cash_flow.2025-02-02 | F60: earnings_quality | G60: Earnings Quality | H60: D5 | I60: ='Cash Flow Statement'!D27 | J60: 2272713 | K60: 0.01 | M60: Pull final net cash from operating activities for the same period. | O60: pending | P60: operating_cash_flow_link | Q60: 30 | R60: 2 | S60: 2025-02-02
A61: sales_growth__20240128 | B61: 69 | C61: Sales Growth | D61: Current Revenue relative to the immediately preceding fiscal year. | E61: dupont.sales_growth.2024-01-28 | F61: dupont | G61: ALT DuPont | H61: C5 | I61: =IF('Condensed Financials'!B34=0,NA(),'Condensed Financials'!C34/'Condensed Financials'!B34-1) | J61: 0.18602511 | K61: 0.01 | L61: revenue_link__20240128,revenue_link__20230129 | M61: Sales Growth = Current Revenue / Prior Revenue − 1.|A zero denominator makes this ratio undefined (#N/A), not 0%. | O61: pending | P61: sales_growth | Q61: 18 | R61: 1 | S61: 2024-01-28
A62: operating_cash_flow_link__20260201 | B62: 69 | C62: Operating cash flow historical source link | D62: Link net cash from operating activities for the same fiscal period. | E62: quality.operating_cash_flow.2026-02-01 | F62: earnings_quality | G62: Earnings Quality | H62: E5 | I62: ='Cash Flow Statement'!E27 | J62: 1602477 | K62: 0.01 | M62: Pull final net cash from operating activities for the same period. | O62: pending | P62: operating_cash_flow_link | Q62: 30 | R62: 3 | S62: 2026-02-01
A63: sales_growth__20250202 | B63: 70 | C63: Sales Growth | D63: Current Revenue relative to the immediately preceding fiscal year. | E63: dupont.sales_growth.2025-02-02 | F63: dupont | G63: ALT DuPont | H63: D5 | I63: =IF('Condensed Financials'!C34=0,NA(),'Condensed Financials'!D34/'Condensed Financials'!C34-1) | J63: 0.10071941 | K63: 0.01 | L63: revenue_link__20250202,revenue_link__20240128 | M63: Sales Growth = Current Revenue / Prior Revenue − 1.|A zero denominator makes this ratio undefined (#N/A), not 0%. | O63: pending | P63: sales_growth | Q63: 18 | R63: 2 | S63: 2025-02-02
A64: cash_conversion_ratio__20230129 | B64: 70 | C64: Cash conversion ratio | D64: Compare operating cash flow with reported Net Income. | E64: quality.cash_conversion_ratio.2023-01-29 | F64: earnings_quality | G64: Earnings Quality | H64: B7 | I64: =IF(B6=0,NA(),B5/B6) | J64: 1.1306306 | K64: 0.01 | L64: operating_cash_flow_link__20230129,net_income_link__20230129 | M64: Cash conversion = CFO / Reported Net Income. | O64: pending | P64: cash_conversion_ratio | Q64: 31 | R64: 0 | S64: 2023-01-29
A65: sales_growth__20260201 | B65: 71 | C65: Sales Growth | D65: Current Revenue relative to the immediately preceding fiscal year. | E65: dupont.sales_growth.2026-02-01 | F65: dupont | G65: ALT DuPont | H65: E5 | I65: =IF('Condensed Financials'!D34=0,NA(),'Condensed Financials'!E34/'Condensed Financials'!D34-1) | J65: 0.048589713 | K65: 0.01 | L65: revenue_link__20260201,revenue_link__20250202 | M65: Sales Growth = Current Revenue / Prior Revenue − 1.|A zero denominator makes this ratio undefined (#N/A), not 0%. | O65: pending | P65: sales_growth | Q65: 18 | R65: 3 | S65: 2026-02-01
A66: cash_conversion_ratio__20240128 | B66: 71 | C66: Cash conversion ratio | D66: Compare operating cash flow with reported Net Income. | E66: quality.cash_conversion_ratio.2024-01-28 | F66: earnings_quality | G66: Earnings Quality | H66: C7 | I66: =IF(C6=0,NA(),C5/C6) | J66: 1.4812146 | K66: 0.01 | L66: operating_cash_flow_link__20240128,net_income_link__20240128 | M66: Cash conversion = CFO / Reported Net Income. | O66: pending | P66: cash_conversion_ratio | Q66: 31 | R66: 1 | S66: 2024-01-28
A67: cash_conversion_ratio__20250202 | B67: 72 | C67: Cash conversion ratio | D67: Compare operating cash flow with reported Net Income. | E67: quality.cash_conversion_ratio.2025-02-02 | F67: earnings_quality | G67: Earnings Quality | H67: D7 | I67: =IF(D6=0,NA(),D5/D6) | J67: 1.2524485 | K67: 0.01 | L67: operating_cash_flow_link__20250202,net_income_link__20250202 | M67: Cash conversion = CFO / Reported Net Income. | O67: pending | P67: cash_conversion_ratio | Q67: 31 | R67: 2 | S67: 2025-02-02
A68: cash_conversion_ratio__20260201 | B68: 73 | C68: Cash conversion ratio | D68: Compare operating cash flow with reported Net Income. | E68: quality.cash_conversion_ratio.2026-02-01 | F68: earnings_quality | G68: Earnings Quality | H68: E7 | I68: =IF(E6=0,NA(),E5/E6) | J68: 1.0147507 | K68: 0.01 | L68: operating_cash_flow_link__20260201,net_income_link__20260201 | M68: Cash conversion = CFO / Reported Net Income. | O68: pending | P68: cash_conversion_ratio | Q68: 31 | R68: 3 | S68: 2026-02-01
A69: total_accruals__20230129 | B69: 74 | C69: Total accruals | D69: Reported Net Income minus operating cash flow. | E69: quality.total_accruals.2023-01-29 | F69: earnings_quality | G69: Earnings Quality | H69: B8 | I69: =B6-B5 | J69: -111663 | K69: 0.01 | L69: operating_cash_flow_link__20230129,net_income_link__20230129 | M69: Total accruals = Reported Net Income − CFO. | O69: pending | P69: total_accruals | Q69: 32 | R69: 0 | S69: 2023-01-29
A70: total_accruals__20240128 | B70: 75 | C70: Total accruals | D70: Reported Net Income minus operating cash flow. | E70: quality.total_accruals.2024-01-28 | F70: earnings_quality | G70: Earnings Quality | H70: C8 | I70: =C6-C5 | J70: -745974 | K70: 0.01 | L70: operating_cash_flow_link__20240128,net_income_link__20240128 | M70: Total accruals = Reported Net Income − CFO. | O70: pending | P70: total_accruals | Q70: 32 | R70: 1 | S70: 2024-01-28
A71: total_accruals__20250202 | B71: 76 | C71: Total accruals | D71: Reported Net Income minus operating cash flow. | E71: quality.total_accruals.2025-02-02 | F71: earnings_quality | G71: Earnings Quality | H71: D8 | I71: =D6-D5 | J71: -458097 | K71: 0.01 | L71: operating_cash_flow_link__20250202,net_income_link__20250202 | M71: Total accruals = Reported Net Income − CFO. | O71: pending | P71: total_accruals | Q71: 32 | R71: 2 | S71: 2025-02-02
A72: total_accruals__20260201 | B72: 77 | C72: Total accruals | D72: Reported Net Income minus operating cash flow. | E72: quality.total_accruals.2026-02-01 | F72: earnings_quality | G72: Earnings Quality | H72: E8 | I72: =E6-E5 | J72: -23294 | K72: 0.01 | L72: operating_cash_flow_link__20260201,net_income_link__20260201 | M72: Total accruals = Reported Net Income − CFO. | O72: pending | P72: total_accruals | Q72: 32 | R72: 3 | S72: 2026-02-01
A73: average_total_assets__20240128 | B73: 78 | C73: Average total assets | D73: Average beginning and ending reported total assets. | E73: quality.average_total_assets.2024-01-28 | F73: earnings_quality | G73: Earnings Quality | H73: C11 | I73: =(B10+C10)/2 | J73: 6349489.5 | K73: 0.01 | M73: Average Total Assets = (Beginning Total Assets + Ending Total Assets) / 2. | O73: pending | P73: average_total_assets | Q73: 33 | R73: 1 | S73: 2024-01-28
A74: average_total_assets__20250202 | B74: 79 | C74: Average total assets | D74: Average beginning and ending reported total assets. | E74: quality.average_total_assets.2025-02-02 | F74: earnings_quality | G74: Earnings Quality | H74: D11 | I74: =(C10+D10)/2 | J74: 7347616.5 | K74: 0.01 | M74: Average Total Assets = (Beginning Total Assets + Ending Total Assets) / 2. | O74: pending | P74: average_total_assets | Q74: 33 | R74: 2 | S74: 2025-02-02
A75: average_total_assets__20260201 | B75: 80 | C75: Average total assets | D75: Average beginning and ending reported total assets. | E75: quality.average_total_assets.2026-02-01 | F75: earnings_quality | G75: Earnings Quality | H75: E11 | I75: =(D10+E10)/2 | J75: 8030017.5 | K75: 0.01 | M75: Average Total Assets = (Beginning Total Assets + Ending Total Assets) / 2. | O75: pending | P75: average_total_assets | Q75: 33 | R75: 3 | S75: 2026-02-01
A76: accrual_ratio__20240128 | B76: 81 | C76: Accrual ratio | D76: Scale total accruals by average total assets. | E76: quality.accrual_ratio.2024-01-28 | F76: earnings_quality | G76: Earnings Quality | H76: C12 | I76: =IF(C11=0,NA(),C8/C11) | J76: -0.11748567 | K76: 0.01 | L76: total_accruals__20240128,average_total_assets__20240128 | M76: Accrual ratio = Total Accruals / Average Total Assets. | O76: pending | P76: accrual_ratio | Q76: 34 | R76: 1 | S76: 2024-01-28
A77: accrual_ratio__20250202 | B77: 82 | C77: Accrual ratio | D77: Scale total accruals by average total assets. | E77: quality.accrual_ratio.2025-02-02 | F77: earnings_quality | G77: Earnings Quality | H77: D12 | I77: =IF(D11=0,NA(),D8/D11) | J77: -0.06234634 | K77: 0.01 | L77: total_accruals__20250202,average_total_assets__20250202 | M77: Accrual ratio = Total Accruals / Average Total Assets. | O77: pending | P77: accrual_ratio | Q77: 34 | R77: 2 | S77: 2025-02-02
A78: accrual_ratio__20260201 | B78: 83 | C78: Accrual ratio | D78: Scale total accruals by average total assets. | E78: quality.accrual_ratio.2026-02-01 | F78: earnings_quality | G78: Earnings Quality | H78: E12 | I78: =IF(E11=0,NA(),E8/E11) | J78: -0.0029008654 | K78: 0.01 | L78: total_accruals__20260201,average_total_assets__20260201 | M78: Accrual ratio = Total Accruals / Average Total Assets. | O78: pending | P78: accrual_ratio | Q78: 34 | R78: 3 | S78: 2026-02-01
A79: owca_to_revenue__20230129 | B79: 84 | C79: Operating working capital assets / Revenue | D79: OWCA divided by Revenue for the same fiscal period. | E79: working_capital.owca_to_revenue.2023-01-29 | F79: working_capital | G79: Working Capital Analysis | H79: B11 | I79: =IF(B6=0,NA(),B7/B6) | J79: 0.24715881 | K79: 0.01 | M79: Operating Working Capital Assets / Revenue measures operating current assets tied up per sales dollar.|A zero Revenue denominator makes the ratio undefined (#N/A).|A higher ratio is not automatically deterioration; diagnose the underlying operating balances before drawing a conclusion. | O79: pending | P79: owca_to_revenue | Q79: 35 | R79: 0 | S79: 2023-01-29
A80: flev__20240128 | B80: 85 | C80: Financial leverage (FLEV) | D80: Relate average net debt to average reformulated equity. | E80: dupont.flev.2024-01-28 | F80: dupont | G80: ALT DuPont | H80: C10 | I80: =IF((('Condensed Financials'!C54+'Condensed Financials'!B54)/2)=0,NA(),(('Condensed Financials'!C53+'Condensed Financials'!B53)/2)/(('Condensed Financials'!C54+'Condensed Financials'!B54)/2)) | J80: -0.46049224 | K80: 0.01 | L80: net_debt__20240128,equity_reformulated_fy__20240128,net_debt__20230129,equity_reformulated_fy__20230129 | M80: FLEV = Average Net Debt / Average Equity.|A zero denominator makes this ratio undefined (#N/A), not 0%. | O80: pending | P80: flev | Q80: 23 | R80: 1 | S80: 2024-01-28
A81: owca_to_revenue__20240128 | B81: 85 | C81: Operating working capital assets / Revenue | D81: OWCA divided by Revenue for the same fiscal period. | E81: working_capital.owca_to_revenue.2024-01-28 | F81: working_capital | G81: Working Capital Analysis | H81: C11 | I81: =IF(C6=0,NA(),C7/C6) | J81: 0.18885056 | K81: 0.01 | M81: Operating Working Capital Assets / Revenue measures operating current assets tied up per sales dollar.|A zero Revenue denominator makes the ratio undefined (#N/A).|A higher ratio is not automatically deterioration; diagnose the underlying operating balances before drawing a conclusion. | O81: pending | P81: owca_to_revenue | Q81: 35 | R81: 1 | S81: 2024-01-28
A82: flev__20250202 | B82: 86 | C82: Financial leverage (FLEV) | D82: Relate average net debt to average reformulated equity. | E82: dupont.flev.2025-02-02 | F82: dupont | G82: ALT DuPont | H82: D10 | I82: =IF((('Condensed Financials'!D54+'Condensed Financials'!C54)/2)=0,NA(),(('Condensed Financials'!D53+'Condensed Financials'!C53)/2)/(('Condensed Financials'!D54+'Condensed Financials'!C54)/2)) | J82: -0.49418464 | K82: 0.01 | L82: net_debt__20250202,equity_reformulated_fy__20250202,net_debt__20240128,equity_reformulated_fy__20240128 | M82: FLEV = Average Net Debt / Average Equity.|A zero denominator makes this ratio undefined (#N/A), not 0%. | O82: pending | P82: flev | Q82: 23 | R82: 2 | S82: 2025-02-02
A83: owca_to_revenue__20250202 | B83: 86 | C83: Operating working capital assets / Revenue | D83: OWCA divided by Revenue for the same fiscal period. | E83: working_capital.owca_to_revenue.2025-02-02 | F83: working_capital | G83: Working Capital Analysis | H83: D11 | I83: =IF(D6=0,NA(),D7/D6) | J83: 0.18850985 | K83: 0.01 | M83: Operating Working Capital Assets / Revenue measures operating current assets tied up per sales dollar.|A zero Revenue denominator makes the ratio undefined (#N/A).|A higher ratio is not automatically deterioration; diagnose the underlying operating balances before drawing a conclusion. | O83: pending | P83: owca_to_revenue | Q83: 35 | R83: 2 | S83: 2025-02-02
A84: flev__20260201 | B84: 87 | C84: Financial leverage (FLEV) | D84: Relate average net debt to average reformulated equity. | E84: dupont.flev.2026-02-01 | F84: dupont | G84: ALT DuPont | H84: E10 | I84: =IF((('Condensed Financials'!E54+'Condensed Financials'!D54)/2)=0,NA(),(('Condensed Financials'!E53+'Condensed Financials'!D53)/2)/(('Condensed Financials'!E54+'Condensed Financials'!D54)/2)) | J84: -0.40831188 | K84: 0.01 | L84: net_debt__20260201,equity_reformulated_fy__20260201,net_debt__20250202,equity_reformulated_fy__20250202 | M84: FLEV = Average Net Debt / Average Equity.|A zero denominator makes this ratio undefined (#N/A), not 0%. | O84: pending | P84: flev | Q84: 23 | R84: 3 | S84: 2026-02-01
A85: owca_to_revenue__20260201 | B85: 87 | C85: Operating working capital assets / Revenue | D85: OWCA divided by Revenue for the same fiscal period. | E85: working_capital.owca_to_revenue.2026-02-01 | F85: working_capital | G85: Working Capital Analysis | H85: E11 | I85: =IF(E6=0,NA(),E7/E6) | J85: 0.22116432 | K85: 0.01 | M85: Operating Working Capital Assets / Revenue measures operating current assets tied up per sales dollar.|A zero Revenue denominator makes the ratio undefined (#N/A).|A higher ratio is not automatically deterioration; diagnose the underlying operating balances before drawing a conclusion. | O85: pending | P85: owca_to_revenue | Q85: 35 | R85: 3 | S85: 2026-02-01
A86: owcl_to_revenue__20230129 | B86: 88 | C86: Operating working capital liabilities / Revenue | D86: OWCL divided by Revenue for the same fiscal period. | E86: working_capital.owcl_to_revenue.2023-01-29 | F86: working_capital | G86: Working Capital Analysis | H86: B12 | I86: =IF(B6=0,NA(),B8/B6) | J86: 0.16186155 | K86: 0.01 | M86: Operating Working Capital Liabilities / Revenue measures operating current liabilities financing each sales dollar.|A zero Revenue denominator makes the ratio undefined (#N/A).|A higher ratio can finance growth but is not automatically positive; payment behavior and business model matter. | O86: pending | P86: owcl_to_revenue | Q86: 36 | R86: 0 | S86: 2023-01-29
A87: owcl_to_revenue__20240128 | B87: 89 | C87: Operating working capital liabilities / Revenue | D87: OWCL divided by Revenue for the same fiscal period. | E87: working_capital.owcl_to_revenue.2024-01-28 | F87: working_capital | G87: Working Capital Analysis | H87: C12 | I87: =IF(C6=0,NA(),C8/C6) | J87: 0.14531808 | K87: 0.01 | M87: Operating Working Capital Liabilities / Revenue measures operating current liabilities financing each sales dollar.|A zero Revenue denominator makes the ratio undefined (#N/A).|A higher ratio can finance growth but is not automatically positive; payment behavior and business model matter. | O87: pending | P87: owcl_to_revenue | Q87: 36 | R87: 1 | S87: 2024-01-28
A88: owcl_to_revenue__20250202 | B88: 90 | C88: Operating working capital liabilities / Revenue | D88: OWCL divided by Revenue for the same fiscal period. | E88: working_capital.owcl_to_revenue.2025-02-02 | F88: working_capital | G88: Working Capital Analysis | H88: D12 | I88: =IF(D6=0,NA(),D8/D6) | J88: 0.14775759 | K88: 0.01 | M88: Operating Working Capital Liabilities / Revenue measures operating current liabilities financing each sales dollar.|A zero Revenue denominator makes the ratio undefined (#N/A).|A higher ratio can finance growth but is not automatically positive; payment behavior and business model matter. | O88: pending | P88: owcl_to_revenue | Q88: 36 | R88: 2 | S88: 2025-02-02
A89: actual_roe__20240128 | B89: 91 | C89: Actual ROE | D89: Relate net income to average reformulated equity. | E89: dupont.actual_roe.2024-01-28 | F89: dupont | G89: ALT DuPont | H89: C12 | I89: =IF((('Condensed Financials'!C54+'Condensed Financials'!B54)/2)=0,NA(),'Condensed Financials'!C35/(('Condensed Financials'!C54+'Condensed Financials'!B54)/2)) | J89: 0.4200556 | K89: 0.01 | L89: net_income_link__20240128,equity_reformulated_fy__20240128,equity_reformulated_fy__20230129 | M89: Actual ROE = Net Income / Average Equity.|A zero denominator makes this ratio undefined (#N/A), not 0%. | O89: pending | P89: actual_roe | Q89: 25 | R89: 1 | S89: 2024-01-28
A90: owcl_to_revenue__20260201 | B90: 91 | C90: Operating working capital liabilities / Revenue | D90: OWCL divided by Revenue for the same fiscal period. | E90: working_capital.owcl_to_revenue.2026-02-01 | F90: working_capital | G90: Working Capital Analysis | H90: E12 | I90: =IF(E6=0,NA(),E8/E6) | J90: 0.14310378 | K90: 0.01 | M90: Operating Working Capital Liabilities / Revenue measures operating current liabilities financing each sales dollar.|A zero Revenue denominator makes the ratio undefined (#N/A).|A higher ratio can finance growth but is not automatically positive; payment behavior and business model matter. | O90: pending | P90: owcl_to_revenue | Q90: 36 | R90: 3 | S90: 2026-02-01
A91: actual_roe__20250202 | B91: 92 | C91: Actual ROE | D91: Relate net income to average reformulated equity. | E91: dupont.actual_roe.2025-02-02 | F91: dupont | G91: ALT DuPont | H91: D12 | I91: =IF((('Condensed Financials'!D54+'Condensed Financials'!C54)/2)=0,NA(),'Condensed Financials'!D35/(('Condensed Financials'!D54+'Condensed Financials'!C54)/2)) | J91: 0.42416757 | K91: 0.01 | L91: net_income_link__20250202,equity_reformulated_fy__20250202,equity_reformulated_fy__20240128 | M91: Actual ROE = Net Income / Average Equity.|A zero denominator makes this ratio undefined (#N/A), not 0%. | O91: pending | P91: actual_roe | Q91: 25 | R91: 2 | S91: 2025-02-02
A92: nowc_to_revenue__20230129 | B92: 92 | C92: NOWC / Revenue | D92: NOWC divided by Revenue for the same fiscal period. | E92: working_capital.nowc_to_revenue.2023-01-29 | F92: working_capital | G92: Working Capital Analysis | H92: B13 | I92: =IF(B6=0,NA(),B9/B6) | J92: 0.085297265 | K92: 0.01 | M92: NOWC / Revenue measures net operating working capital tied up per sales dollar.|NOWC = OWCA - OWCL.|Rising intensity means more net working capital is tied up per sales dollar, but the cause must be diagnosed rather than labeled automatically. | O92: pending | P92: nowc_to_revenue | Q92: 37 | R92: 0 | S92: 2023-01-29
A93: actual_roe__20260201 | B93: 93 | C93: Actual ROE | D93: Relate net income to average reformulated equity. | E93: dupont.actual_roe.2026-02-01 | F93: dupont | G93: ALT DuPont | H93: E12 | I93: =IF((('Condensed Financials'!E54+'Condensed Financials'!D54)/2)=0,NA(),'Condensed Financials'!E35/(('Condensed Financials'!E54+'Condensed Financials'!D54)/2)) | J93: 0.3401254 | K93: 0.01 | L93: net_income_link__20260201,equity_reformulated_fy__20260201,equity_reformulated_fy__20250202 | M93: Actual ROE = Net Income / Average Equity.|A zero denominator makes this ratio undefined (#N/A), not 0%. | O93: pending | P93: actual_roe | Q93: 25 | R93: 3 | S93: 2026-02-01
A94: nowc_to_revenue__20240128 | B94: 93 | C94: NOWC / Revenue | D94: NOWC divided by Revenue for the same fiscal period. | E94: working_capital.nowc_to_revenue.2024-01-28 | F94: working_capital | G94: Working Capital Analysis | H94: C13 | I94: =IF(C6=0,NA(),C9/C6) | J94: 0.043532477 | K94: 0.01 | M94: NOWC / Revenue measures net operating working capital tied up per sales dollar.|NOWC = OWCA - OWCL.|Rising intensity means more net working capital is tied up per sales dollar, but the cause must be diagnosed rather than labeled automatically. | O94: pending | P94: nowc_to_revenue | Q94: 37 | R94: 1 | S94: 2024-01-28
A95: nowc_to_revenue__20250202 | B95: 94 | C95: NOWC / Revenue | D95: NOWC divided by Revenue for the same fiscal period. | E95: working_capital.nowc_to_revenue.2025-02-02 | F95: working_capital | G95: Working Capital Analysis | H95: D13 | I95: =IF(D6=0,NA(),D9/D6) | J95: 0.040752254 | K95: 0.01 | M95: NOWC / Revenue measures net operating working capital tied up per sales dollar.|NOWC = OWCA - OWCL.|Rising intensity means more net working capital is tied up per sales dollar, but the cause must be diagnosed rather than labeled automatically. | O95: pending | P95: nowc_to_revenue | Q95: 37 | R95: 2 | S95: 2025-02-02
A96: nowc_to_revenue__20260201 | B96: 95 | C96: NOWC / Revenue | D96: NOWC divided by Revenue for the same fiscal period. | E96: working_capital.nowc_to_revenue.2026-02-01 | F96: working_capital | G96: Working Capital Analysis | H96: E13 | I96: =IF(E6=0,NA(),E9/E6) | J96: 0.078060544 | K96: 0.01 | M96: NOWC / Revenue measures net operating working capital tied up per sales dollar.|NOWC = OWCA - OWCL.|Rising intensity means more net working capital is tied up per sales dollar, but the cause must be diagnosed rather than labeled automatically. | O96: pending | P96: nowc_to_revenue | Q96: 37 | R96: 3 | S96: 2026-02-01
A97: revenue_change__20240128 | B97: 96 | C97: Change in Revenue | D97: Absolute year-on-year change in Revenue. | E97: working_capital.revenue_change.2024-01-28 | F97: working_capital | G97: Working Capital Analysis | H97: C14 | I97: =C6-B6 | J97: 1508760 | K97: 0.01 | M97: Use the absolute year-on-year change in Revenue, not the percentage growth rate. | O97: pending | P97: revenue_change | Q97: 38 | R97: 1 | S97: 2024-01-28
A98: revenue_change__20250202 | B98: 97 | C98: Change in Revenue | D98: Absolute year-on-year change in Revenue. | E98: working_capital.revenue_change.2025-02-02 | F98: working_capital | G98: Working Capital Analysis | H98: D14 | I98: =D6-C6 | J98: 968848 | K98: 0.01 | M98: Use the absolute year-on-year change in Revenue, not the percentage growth rate. | O98: pending | P98: revenue_change | Q98: 38 | R98: 2 | S98: 2025-02-02
A99: revenue_change__20260201 | B99: 98 | C99: Change in Revenue | D99: Absolute year-on-year change in Revenue. | E99: working_capital.revenue_change.2026-02-01 | F99: working_capital | G99: Working Capital Analysis | H99: E14 | I99: =E6-D6 | J99: 514474 | K99: 0.01 | M99: Use the absolute year-on-year change in Revenue, not the percentage growth rate. | O99: pending | P99: revenue_change | Q99: 38 | R99: 3 | S99: 2026-02-01
A100: nowc_change__20240128 | B100: 99 | C100: Change in NOWC | D100: Absolute year-on-year change in NOWC. | E100: working_capital.nowc_change.2024-01-28 | F100: working_capital | G100: Working Capital Analysis | H100: C15 | I100: =C9-B9 | J100: -273054 | K100: 0.01 | M100: Positive Change in NOWC means additional operating working capital is tied up; negative Change in NOWC means a release.|Do not call the movement good or bad without examining why it occurred. | O100: pending | P100: nowc_change | Q100: 39 | R100: 1 | S100: 2024-01-28
...

Sheet _CheckContext
A1: BAV_CHECK_CONTEXT_V1
A2: {"base_classification_overrides":{},"judgment_bindings":[{"allowed_treatments":["Operating Long-Term Liability","Financial Liability"],"case_id":"classification::concept=lease_liability_current|label=current lease liabilities","line_identity":"concept=lease_liability_current|label=current lease liabilities","order":1,"override_selector":"identity:concept=lease_liability_current|label=current lease liabilities","reference_treatment":"Operating Long-Term Liability","worksheet_row":5},{"allowed_treatments":["Operating Working Capital Liability","Financial Liability"],"case_id":"classification::concept=other_current_liabilities|label=other current liabilities","line_identity":"concept=other_current_liabilities|label=other current liabilities","order":2,"override_selector":"identity:concept=other_current_liabilities|label=other current liabilities","reference_treatment":"Operating Working Capital Liability","worksheet_row":6},{"allowed_treatments":["Operating Long-Term Asset","Financial Asset"],"case_id":"classification::concept=other_non_current_assets|label=other non-current assets","line_identity":"concept=other_non_current_assets|label=other non-current assets","order":3,"override_selector":"identity:concept=other_non_current_assets|label=other non-current assets","reference_treatment":"Operating Long-Term Asset","worksheet_row":7},{"allowed_treatments":["Operating Long-Term Liability","Financial Liability"],"case_id":"classification::concept=lease_liability_noncurrent|label=non-current lease liabilities","line_identity":"concept=lease_liability_noncurrent|label=non-current lease liabilities","order":4,"override_selector":"identity:concept=lease_liability_noncurrent|label=non-current lease liabilities","reference_treatment":"Operating Long-Term Liability","worksheet_row":8},{"allowed_treatments":["Operating Long-Term Liability","Financial Liability"],"case_id":"classification::concept=other_non_current_liabilities|label=other non-current liabilities","line_identity":"concept=other_non_current_liabilities|label=other non-current liabilities","order":5,"override_selector":"identity:concept=other_non_current_liabilities|label=other non-current liabilities","reference_treatment":"Operating Long-Term Liability","worksheet_row":9}],"modeled_periods":["2023-01-29","2024-01-28","2025-02-02","2026-02-01"],"normalization_bindings":[],"schema_version":2,"source_payload":{"balance_sheet":[{"concept":"accounts_receivable","label":"Accounts receivable, net","values":{"2023-01-29":132906.0,"2024-01-28":124769.0,"2025-02-02":120173.0,"2026-02-01":190657.0}},{"concept":"cash_and_cash_equivalents","label":"Cash and cash equivalents","values":{"2023-01-29":1154867.0,"2024-01-28":2243971.0,"2025-02-02":1984336.0,"2026-02-01":1807202.0}},{"concept":"inventories","label":"Inventories","values":{"2023-01-29":1447367.0,"2024-01-28":1323602.0,"2025-02-02":1442081.0,"2026-02-01":1700753.0}},{"concept":"prepaid_and_receivable_income_taxes","label":"Prepaid and receivable income taxes","values":{"2023-01-29":185641.0,"2024-01-28":183733.0,"2025-02-02":182253.0,"2026-02-01":352469.0}},{"concept":"prepaid_expenses_and_other_current_assets","label":"Prepaid expenses and other current assets","values":{"2023-01-29":238672.0,"2024-01-28":184502.0,"2025-02-02":251459.0,"2026-02-01":211620.0}},{"concept":"total_current_assets","label":"Total current assets","values":{"2023-01-29":3159453.0,"2024-01-28":4060577.0,"2025-02-02":3980302.0,"2026-02-01":4262701.0}},{"concept":"accounts_payable","label":"Accounts payable","values":{"2023-01-29":172732.0,"2024-01-28":348441.0,"2025-02-02":271406.0,"2026-02-01":331421.0}},{"concept":"accrued_compensation_and_related_expenses","label":"Accrued compensation and related expenses","values":{"2023-01-29":248167.0,"2024-01-28":326110.0,"2025-02-02":204543.0,"2026-02-01":187887.0}},{"concept":"accrued_liabilities_and_other","label":"Accrued liabilities and other","values":{"2023-01-29":399223.0,"2024-01-28":348555.0,"2025-02-02":559463.0,"2026-02-01":662982.0}},{"concept":"current_income_taxes_payable","label":"Current income taxes payable","values":{"2023-01-29":174221.0,"2024-01-28":12098.0,"2025-02-02":183126.0,"2026-02-01":43948.0}},{"concept":"lease_liability_current","label":"Current lease liabilities","values":{"2023-01-29":207972.0,"2024-01-28":249270.0,"2025-02-02":275154.0,"2026-02-01":298724.0}},{"concept":"other_current_liabilities","label":"Other current liabilities","values":{"2023-01-29":38405.0,"2024-01-28":40308.0,"2025-02-02":37586.0,"2026-02-01":45954.0}},{"concept":"total_current_liabilities","label":"Total current liabilities","values":{"2023-01-29":1492198.0,"2024-01-28":1631261.0,"2025-02-02":1839630.0,"2026-02-01":1887548.0}},{"concept":"unredeemed_gift_card_liability","label":"Unredeemed gift card liability","values":{"2023-01-29":251478.0,"2024-01-28":306479.0,"2025-02-02":308352.0,"2026-02-01":316632.0}},{"concept":"deferred_tax_asset","label":"Deferred income tax assets","values":{"2023-01-29":6402.0,"2024-01-28":9176.0,"2025-02-02":17085.0,"2026-02-01":24037.0}},{"concept":"goodwill","label":"Goodwill","values":{"2023-01-29":24144.0,"2024-01-28":24083.0,"2025-02-02":159518.0,"2026-02-01":184911.0}},{"concept":"intangible_assets","label":"Intangible assets, net","values":{"2023-01-29":21961.0,"2024-01-28":0.0,"2025-02-02":11673.0,"2026-02-01":6283.0}},{"concept":"other_non_current_assets","label":"Other non-current assets","values":{"2023-01-29":156045.0,"2024-01-28":186684.0,"2025-02-02":237841.0,"2026-02-01":314910.0}},{"concept":"property_plant_and_equipment","label":"Property and equipment, net","values":{"2023-01-29":1269614.0,"2024-01-28":1545811.0,"2025-02-02":1780617.0,"2026-02-01":2033720.0}},{"concept":"right_of_use_lease_asset","label":"Right-of-use lease assets","values":{"2023-01-29":969419.0,"2024-01-28":1265610.0,"2025-02-02":1416256.0,"2026-02-01":1630181.0}},{"concept":"deferred_tax_liability","label":"Deferred income tax liabilities","values":{"2023-01-29":55084.0,"2024-01-28":29522.0,"2025-02-02":98188.0,"2026-02-01":52278.0}},{"concept":"non_current_income_taxes_payable","label":"Non-current income taxes payable","values":{"2023-01-29":28555.0,"2024-01-28":15864.0,"2025-02-02":0.0,"2026-02-01":null}},{"concept":"lease_liability_noncurrent","label":"Non-current lease liabilities","values":{"2023-01-29":862362.0,"2024-01-28":1154012.0,"2025-02-02":1300637.0,"2026-02-01":1499717.0}},{"concept":"other_non_current_liabilities","label":"Other non-current liabilities","values":{"2023-01-29":20040.0,"2024-01-28":29201.0,"2025-02-02":40790.0,"2026-02-01":55360.0}},{"concept":"accumulated_other_comprehensive_income","label":"Accumulated other comprehensive loss","values":{"2023-01-29":-252584.0,"2024-01-28":-264256.0,"2025-02-02":-424441.0,"2026-02-01":-230690.0}},{"concept":"additional_paid_in_capital","label":"Additional paid-in capital","values":{"2023-01-29":474645.0,"2024-01-28":575369.0,"2025-02-02":638190.0,"2026-02-01":669392.0}},{"concept":"common_stock","label":"Common stock","values":{"2023-01-29":611.0,"2024-01-28":606.0,"2025-02-02":581.0,"2026-02-01":557.0}},{"concept":"retained_earnings","label":"Retained earnings","values":{"2023-01-29":2926127.0,"2024-01-28":3920362.0,"2025-02-02":4109717.0,"2026-02-01":4522581.0}},{"concept":"total_equity","label":"Total stockholders' equity","values":{"2023-01-29":3148799.0,"2024-01-28":4232081.0,"2025-02-02":4324047.0,"2026-02-01":4961840.0}},{"concept":"total_assets","label":"Total assets","values":{"2023-01-29":5607038.0,"2024-01-28":7091941.0,"2025-02-02":7603292.0,"2026-02-01":8456743.0}},{"concept":"total_liabilities_and_equity","label":"Total liabilities and stockholders' equity","values":{"2023-01-29":5607038.0,"2024-01-28":7091941.0,"2025-02-02":7603292.0,"2026-02-01":8456743.0}},{"concept":"total_liabilities","label":"Total liabilities","values":{"2023-01-29":2458239.0,"2024-01-28":2859860.0,"2025-02-02":3279245.0,"2026-02-01":3494903.0}}],"cash_flow":[{"concept":"net_cash_from_financing_activities","label":"Net cash used in financing activities","values":{"2023-01-29":-467487.0,"2024-01-28":-548828.0,"2025-02-02":-1652508.0,"2026-02-01":-1208656.0}},{"concept":"other_financing_activities","label":"Other financing activities","values":{"2023-01-29":-32.0,"2024-01-28":-32.0,"2025-02-02":-32.0,"2026-02-01":-11312.0}},{"concept":"proceeds_from_stock_based_compensation","label":"Proceeds from settlement of stock-based compensation","values":{"2023-01-29":11704.0,"2024-01-28":42430.0,"2025-02-02":19813.0,"2026-02-01":8377.0}},{"concept":"repurchase_of_common_stock","label":"Repurchase of common stock","values":{"2023-01-29":-444001.0,"2024-01-28":-558652.0,"2025-02-02":-1636879.0,"2026-02-01":-1178349.0}},{"concept":"shares_withheld_for_stock_based_compensation","label":"Shares withheld related to net share settlement of stock-based compensation","values":{"2023-01-29":-35158.0,"2024-01-28":-32574.0,"2025-02-02":-35410.0,"2026-02-01":-27372.0}},{"concept":"acquisition_net_of_cash_acquired","label":"Acquisition, net of cash acquired","values":{"2023-01-29":0.0,"2024-01-28":0.0,"2025-02-02":-154146.0,"2026-02-01":0.0}},{"concept":"net_cash_from_investing_activities","label":"Net cash used in investing activities","values":{"2023-01-29":-569937.0,"2024-01-28":-654132.0,"2025-02-02":-798174.0,"2026-02-01":-662118.0}},{"concept":"other_investing_activities","label":"Other investing activities","values":{"2023-01-29":20916.0,"2024-01-28":-658.0,"2025-02-02":-5009.0,"2026-02-01":-8521.0}},{"concept":"capital_expenditures","label":"Purchase of property and equipment","values":{"2023-01-29":-638657.0,"2024-01-28":-651865.0,"2025-02-02":-689232.0,"2026-02-01":-680802.0}},{"concept":"settlement_of_net_investment_hedges","label":"Settlement of net investment hedges","values":{"2023-01-29":47804.0,"2024-01-28":-1609.0,"2025-02-02":50213.0,"2026-02-01":27205.0}},{"concept":"change_in_accounts_payable","label":"Accounts payable","values":{"2023-01-29":-107280.0,"2024-01-28":177367.0,"2025-02-02":-57044.0,"2026-02-01":45856.0}},{"concept":"change_in_accounts_receivable","label":"Accounts receivable, net","values":{"2023-01-29":-58987.0,"2024-01-28":6580.0,"2025-02-02":1626.0,"2026-02-01":-65755.0}},{"concept":"change_in_accrued_compensation_and_related_expenses","label":"Accrued compensation and related expenses","values":{"2023-01-29":47254.0,"2024-01-28":70327.0,"2025-02-02":-112110.0,"2026-02-01":-24737.0}},{"concept":"change_in_accrued_liabilities_and_other","label":"Accrued liabilities and other","values":{"2023-01-29":65364.0,"2024-01-28":-71734.0,"2025-02-02":193139.0,"2026-02-01":98421.0}},{"concept":"change_in_income_taxes_payable","label":"Current and non-current income taxes payable","values":{"2023-01-29":35986.0,"2024-01-28":-173196.0,"2025-02-02":157205.0,"2026-02-01":-150496.0}},{"concept":"deferred_income_taxes","label":"Deferred income taxes","values":{"2023-01-29":3042.0,"2024-01-28":-28383.0,"2025-02-02":57451.0,"2026-02-01":-53379.0}},{"concept":"depreciation_and_amortization","label":"Depreciation and amortization","values":{"2023-01-29":291791.0,"2024-01-28":379384.0,"2025-02-02":446524.0,"2026-02-01":496228.0}},{"concept":"derecognition_of_unredeemed_gift_card_liability","label":"Derecognition of unredeemed gift card liability","values":{"2023-01-29":-23337.0,"2024-01-28":-28547.0,"2025-02-02":-36231.0,"2026-02-01":-37766.0}},{"concept":"change_in_inventories","label":"Inventories","values":{"2023-01-29":-573438.0,"2024-01-28":66584.0,"2025-02-02":-156085.0,"2026-02-01":-188710.0}},{"concept":"studio_obsolescence_provision","label":"lululemon Studio obsolescence provision","values":{"2023-01-29":62928.0,"2024-01-28":23709.0,"2025-02-02":0.0,"2026-02-01":0.0}},{"concept":"net_cash_from_operating_activities","label":"Net cash provided by operating activities","values":{"2023-01-29":966463.0,"2024-01-28":2296164.0,"2025-02-02":2272713.0,"2026-02-01":1602477.0}},{"concept":"cash_flow_net_income","label":"Net income","values":{"2023-01-29":854800.0,"2024-01-28":1550190.0,"2025-02-02":1814616.0,"2026-02-01":1579183.0}},{"concept":"change_in_other_liabilities","label":"Other current and non-current liabilities","values":{"2023-01-29":-2925.0,"2024-01-28":12230.0,"2025-02-02":2488.0,"2026-02-01":20632.0}},{"concept":"change_in_other_non_current_assets","label":"Other non-current assets","values":{"2023-01-29":-36518.0,"2024-01-28":-53280.0,"2025-02-02":-73205.0,"2026-02-01":-70351.0}},{"concept":"change_in_prepaid_and_receivable_income_taxes","label":"Prepaid and receivable income taxes","values":{"2023-01-29":-66714.0,"2024-01-28":1908.0,"2025-02-02":-2031.0,"2026-02-01":-170216.0}},{"concept":"change_in_prepaid_expenses_and_other_current_assets","label":"Prepaid expenses and other current assets","values":{"2023-01-29":-54833.0,"2024-01-28":40587.0,"2025-02-02":-71789.0,"2026-02-01":47779.0}},{"concept":"change_in_lease_assets_and_liabilities","label":"Right-of-use lease assets and current and non-current lease liabilities","values":{"2023-01-29":23905.0,"2024-01-28":37535.0,"2025-02-02":23501.0,"2026-02-01":6884.0}},{"concept":"settlement_of_derivatives","label":"Settlement of derivatives not designated in a hedging relationship","values":{"2023-01-29":-38649.0,"2024-01-28":32527.0,"2025-02-02":-47763.0,"2026-02-01":-34552.0}},{"concept":"stock_based_compensation","label":"Stock-based compensation expense","values":{"2023-01-29":78075.0,"2024-01-28":93560.0,"2025-02-02":90011.0,"2026-02-01":62203.0}},{"concept":"change_in_unredeemed_gift_card_liability","label":"Unredeemed gift card liability","values":{"2023-01-29":68266.0,"2024-01-28":84315.0,"2025-02-02":42410.0,"2026-02-01":41253.0}},{"concept":"cash_beginning","label":"Cash and cash equivalents, beginning of period","values":{"2023-01-29":1259871.0,"2024-01-28":1154867.0,"2025-02-02":2243971.0,"2026-02-01":1984336.0}},{"concept":"cash_ending","label":"Cash and cash equivalents, end of period","values":{"2023-01-29":1154867.0,"2024-01-28":2243971.0,"2025-02-02":1984336.0,"2026-02-01":1807202.0}},{"concept":"effect_of_fx_on_cash","label":"Effect of foreign currency exchange rate changes on cash and cash equivalents","values":{"2023-01-29":-34043.0,"2024-01-28":-4100.0,"2025-02-02":-81666.0,"2026-02-01":91163.0}},{"concept":"change_in_cash","label":"Increase (decrease) in cash and cash equivalents","values":{"2023-01-29":-105004.0,"2024-01-28":1089104.0,"2025-02-02":-259635.0,"2026-02-01":-177134.0}}],"company_name":"lululemon athletica inc.","currency":"USD","historical_lease":null,"historical_shares":{"adjustment_factors":{"2023-01-29":1.0,"2024-01-28":1.0,"2025-02-02":1.0,"2026-02-01":1.0},"basis":"reported","diluted_weighted_average":{"2023-01-29":128017.0,"2024-01-28":127060.0,"2025-02-02":123935.0,"2026-02-01":119068.0},"scale_basis":"financial_statement_units"},"income_statement":[{"concept":"foreign_currency_translation_adjustment","label":"Foreign currency translation adjustment","values":{"2023-01-29":-65571.0,"2024-01-28":-23077.0,"2025-02-02":-253209.0,"2026-02-01":253160.0}},{"concept":"net_investment_hedge_gains_losses","label":"Net investment hedge gains (losses)","values":{"2023-01-29":8904.0,"2024-01-28":11405.0,"2025-02-02":93024.0,"2026-02-01":-59409.0}},{"concept":"amortization_of_intangible_assets","label":"Amortization of intangible assets","values":{"2023-01-29":8752.0,"2024-01-28":5010.0,"2025-02-02":2735.0,"2026-02-01":6961.0}},{"concept":"basic_eps","label":"Basic earnings per share","values":{"2023-01-29":6.7,"2024-01-28":12.23,"2025-02-02":14.67,"2026-02-01":13.27}},{"concept":"comprehensive_income","label":"Comprehensive income","values":{"2023-01-29":798133.0,"2024-01-28":1538518.0,"2025-02-02":1654431.0,"2026-02-01":1772934.0}},{"concept":"cost_of_goods_sold","label":"Cost of goods sold","values":{"2023-01-29":3618178.0,"2024-01-28":4009873.0,"2025-02-02":4317315.0,"2026-02-01":4818468.0}},{"concept":"diluted_eps","label":"Diluted earnings per share","values":{"2023-01-29":6.68,"2024-01-28":12.2,"2025-02-02":14.64,"2026-02-01":13.26}},{"concept":"gross_profit","label":"Gross profit","values":{"2023-01-29":4492340.0,"2024-01-28":5609405.0,"2025-02-02":6270811.0,"2026-02-01":6284132.0}},{"concept":"income_before_tax","label":"Income before income tax expense","values":{"2023-01-29":1332571.0,"2024-01-28":2175735.0,"2025-02-02":2576077.0,"2026-02-01":2238967.0}},{"concept":"operating_income","label":"Income from operations","values":{"2023-01-29":1328408.0,"2024-01-28":2132676.0,"2025-02-02":2505697.0,"2026-02-01":2210615.0}},{"concept":"income_tax_expense","label":"Income tax expense","values":{"2023-01-29":477771.0,"2024-01-28":625545.0,"2025-02-02":761461.0,"2026-02-01":659784.0}},{"concept":"net_income","label":"Net income","values":{"2023-01-29":854800.0,"2024-01-28":1550190.0,"2025-02-02":1814616.0,"2026-02-01":1579183.0}},{"concept":"revenue","label":"Net revenue","values":{"2023-01-29":8110518.0,"2024-01-28":9619278.0,"2025-02-02":10588126.0,"2026-02-01":11102600.0}},{"concept":"other_comprehensive_income","label":"Other comprehensive income (loss), net of tax","values":{"2023-01-29":-56667.0,"2024-01-28":-11672.0,"2025-02-02":-160185.0,"2026-02-01":193751.0}},{"concept":"other_income_expense_net","label":"Other income (expense), net","values":{"2023-01-29":4163.0,"2024-01-28":43059.0,"2025-02-02":70380.0,"2026-02-01":28352.0}},{"concept":"selling_general_and_administrative_expenses","label":"Selling, general and administrative expenses","values":{"2023-01-29":2757447.0,"2024-01-28":3397218.0,"2025-02-02":3762379.0,"2026-02-01":4066556.0}}],"jurisdiction":"US","periods":[{"end_date":"2023-01-29","is_interim":false,"label":"FY2023"},{"end_date":"2024-01-28","is_interim":false,"label":"FY2024"},{"end_date":"2025-02-02","is_interim":false,"label":"FY2025"},{"end_date":"2026-02-01","is_interim":false,"label":"FY2026"}],"stock_code":"LULU","ticker":"LULU","units":"USD in Thousands"}}
